Workbook
Name Exp_Item: 'Ext. Inputs'!$B$7:$B$14
Name Exp_Dev: 'Ext. Inputs'!$C$7:$C$14
Name Exp_Emg: 'Ext. Inputs'!$D$7:$D$14
Name Lvl_Bld: 'Ext. Inputs'!$C$19
Name Lvl_Cnt: 'Ext. Inputs'!$C$20
Name Lvl_MotRen: 'Ext. Inputs'!$C$21
Name Lvl_MotNB: 'Ext. Inputs'!$C$22
Name Lvl_MotNB2: 'Ext. Inputs'!$C$23
Name SI_Thr_Cnt: 'Ext. Inputs'!$C$24
Name SI_Thr_Bld: 'Ext. Inputs'!$C$25
Name SI_Div: 'Ext. Inputs'!$C$26
Name XGB_Base: 'Ext. Inputs'!$C$27
Name XGB_Trend: 'Ext. Inputs'!$C$28
Name Py_ID: 'Ext. Inputs'!$B$32:$B$51
Name Py_Small: 'Ext. Inputs'!$D$32:$D$51
Name Py_Large: 'Ext. Inputs'!$E$32:$E$51
Name Py_AsIs: 'Ext. Inputs'!$F$32:$F$51
Name Py_Final: 'Ext. Inputs'!$G$32:$G$51
Name Sw_Market: 'Int. Inputs'!$C$6
Name In_CompSite: 'Int. Inputs'!$C$7
Name Sw_CatBase: 'Int. Inputs'!$C$8
Name In_CatShare_Bld: 'Int. Inputs'!$C$9
Name In_CatShare_Cnt: 'Int. Inputs'!$C$10
Name Pol_ID: 'Int. Inputs'!$B$16:$B$35
Name Pol_Head: 'Int. Inputs'!$B$14:$BT$14
Name Pol_Data: 'Int. Inputs'!$B$16:$BT$35
Name Terms_Key: 'Lookups'!$B$7:$B$8106
Name Terms_Kind: 'Lookups'!$F$7:$F$8106
Name Terms_Lower: 'Lookups'!$I$7:$I$8106
Name Terms_Contrib: 'Lookups'!$K$7:$K$8106
Name Terms_LCT: 'Lookups'!$N$7:$N$8106
Name Remap_Key: 'Lookups'!$P$7:$P$8
Name Remap_To: 'Lookups'!$Q$7:$Q$8
Name Con_Raw: 'Lookups'!$P$12:$P$15
Name Con_Model: 'Lookups'!$Q$12:$Q$15
Name YB_Rating: 'Lookups'!$P$19:$P$26
Name YB_Fill: 'Lookups'!$Q$19:$Q$26
Name Fmt_LCT: 'Lookups'!$P$30:$P$40
Name Fmt_Str: 'Lookups'!$Q$30:$Q$40
Name Node_Key: 'Lookups Trees'!$B$7:$B$2583
Name Node_Kind: 'Lookups Trees'!$E$7:$E$2583
Name Node_Pos: 'Lookups Trees'!$F$7:$F$2583
Name Node_Thr: 'Lookups Trees'!$H$7:$H$2583
Name Node_RCodes: 'Lookups Trees'!$I$7:$I$2583
Name Node_Miss: 'Lookups Trees'!$K$7:$K$2583
Name Node_Left: 'Lookups Trees'!$L$7:$L$2583
Name Node_Right: 'Lookups Trees'!$M$7:$M$2583
Name Node_Leaf: 'Lookups Trees'!$N$7:$N$2583
Name Feat_Key: 'Lookups Trees'!$P$7:$P$224
Name Feat_Code: 'Lookups Trees'!$T$7:$T$224
Name RM_ID: 'Rating Motor'!$B$10:$B$16
Name RM_Final: 'Rating Motor'!$BP$10:$BP$16
Name RC_ID: 'Rating Contents'!$B$10:$B$15
Name RC_Final: 'Rating Contents'!$BQ$10:$BQ$15
Name RB_ID: 'Rating Buildings Trees'!$BZ$10:$BZ$16
Name RB_Final: 'Rating Buildings Trees'!$CH$10:$CH$16
Name OP_ID: 'Office Premium'!$B$17:$B$36
Name OP_Line: 'Office Premium'!$C$17:$C$36
Name OP_NB: 'Office Premium'!$E$17:$E$36
Name OP_Channel: 'Office Premium'!$D$17:$D$36

Sheet Audit
B2: IAA Hackathon 2026, Week 2: rating model replica
B4: Purpose | C4: Excel replica of the Week 2 submitted model (C0 with segment levels) for the 20 reference policies, and the office premium build-up. Doubles as an independent check of the Python model.
B5: Owner | C5: Cian Herrera Quinn
B6: Team | C6: Alan McDonagh, Bridget MacDonnell, Gerard Murphy, Cian Herrera Quinn
B7: Source | C7: Gerard's Excel export (contents/gerard-week2-emerging, export/excel, run f3548525, commit a56b201) and the emerging data
B8: Last updated | C8: 46324
B9: Version | C9: v0.4 (draft)
B11: Checks summary (0 = pass)
B12: Sheet | C12: Check | D12: Value | E12: Result
B13: Rating Motor | C13: motor: policies where Excel differs from Python by more than 1e-9 | D13: =ROUND('Rating Motor'!BR5,2) | E13: =IF(D13=0,"Pass","Fail")
B14: Rating Motor | C14: motor: rating keys not found in the Lookups | D14: =ROUND('Rating Motor'!BS5,2) | E14: =IF(D14=0,"Pass","Fail")
B15: Rating Buildings | C15: buildings large claims: policies where Excel differs from Python by more than 1e-9 | D15: =ROUND('Rating Buildings'!AS5,2) | E15: =IF(D15=0,"Pass","Fail")
B16: Rating Buildings | C16: buildings: rating keys not found in the Lookups | D16: =ROUND('Rating Buildings'!AT5,2) | E16: =IF(D16=0,"Pass","Fail")
B17: Rating Contents | C17: contents: policies where Excel differs from Python by more than 1e-9 | D17: =ROUND('Rating Contents'!BS5,2) | E17: =IF(D17=0,"Pass","Fail")
B18: Rating Contents | C18: contents: rating keys not found in the Lookups | D18: =ROUND('Rating Contents'!BT5,2) | E18: =IF(D18=0,"Pass","Fail")
B19: Rating Buildings Trees | C19: buildings small claims: policies where Excel differs from XGBoost by more than 1e-5 | D19: =ROUND('Rating Buildings Trees'!CJ5,2) | E19: =IF(D19=0,"Pass","Fail")
B20: Rating Buildings Trees | C20: buildings final: policies where Excel differs from Python by more than 1e-5 | D20: =ROUND('Rating Buildings Trees'!CL5,2) | E20: =IF(D20=0,"Pass","Fail")
B21: Rating Buildings Trees | C21: buildings trees: category inputs with no code (scored as missing) | D21: =ROUND('Rating Buildings Trees'!CM5,2) | E21: =IF(D21=0,"Pass","Fail")
B22: Rating Buildings Trees | C22: buildings trees: walks that did not end at a leaf | D22: =ROUND('Rating Buildings Trees'!CN5,2) | E22: =IF(D22=0,"Pass","Fail")
B23: Office Premium | C23: Office premium components add back to the office premium | D23: =ROUND('Office Premium'!X14,2) | E23: =IF(D23=0,"Pass","Fail")
C24: Workbook total | D24: =SUM(D13:D23) | E24: =IF(D24=0,"Pass","Fail")
B26: Open items (green cells: waiting for data)
B27: Sheet | C27: Item | D27: Cell
B28: None | C28: Every input is present; no cell is waiting for data.
B30: Cell-fill legend
B31: Type | C31: Fill | D31: Example
B32: Variable input (Int. Inputs) | C32: #CCFFCC | D32: Example
B33: Static input (Ext. Inputs) | C33: #CCFFFF | D33: Example
B34: Formula: internal link, copyable | C34: #FFFFCC | D34: Example
B35: Formula: internal link, distinct | C35: #FFFF99 | D35: Example
B36: Formula: external link, copyable | C36: #FCE4D6 | D36: Example
B37: Formula: external link, distinct | C37: #F8CBAD | D37: Example
B38: Check / control (0 = pass) | C38: #FFFF00 | D38: Example
B39: Temporarily highlighted (open item) | C39: #00FF00 | D39: Example
B40: Table heading | C40: #D9D9D9 | D40: Example
B41: Author notes (blue font, no fill) | C41: text #0000FF | D41: Example
B43: Tab colours
B44: Grey: system / master / Audit | C44: #D9D9D9
B45: Blue: static inputs | C45: #CCFFFF
B46: Green: variable inputs | C46: #CCFFCC
B47: Peach: imports / working sheets | C47: #FCE4D6
B48: Yellow: lookups / reference data | C48: #FFFFCC
B49: Navy: dashboards and outputs | C49: #2C3E50
B51: Sheet index
B52: Audit | C52: This page: checks, open items, conventions, index, versions
B53: Ext. Inputs | C53: Expense table, level steps and data-fix thresholds, Python results for the reference policies
B54: Int. Inputs | C54: Switches (expense basis, comparison-site commission, cat reinsurance base) and the 20 reference policies
B55: Lookups | C55: The fitted model as 8,100 rating terms, plus remaps, construction codes, year-built fill and curve precision
B56: Lookups Trees | C56: The buildings small-claim XGBoost as tables: 2,577 tree nodes and 218 feature codes
B57: Rating Motor | C57: Motor small- and large-claim GLMs, level steps, check against Python
B58: Rating Buildings | C58: Buildings inputs, data fixes (D-02, D-27, construction codes) and the large-claim GLM
B59: Rating Buildings Trees | C59: Buildings small claims walked through the 193 trees, small + large, level step, checks
B60: Rating Contents | C60: Contents GLM, level step, check against Python
B61: Office Premium | C61: Risk premium to office premium per reference policy
B62: Graph Data | C62: Relativity curves for every numeric and ordered factor (live), tree curves and the smoothness scan
B63: Reference Policies | C63: Output: office premium against written premium
B64: Graphs | C64: Output: smoothness flags and a chart for every factor
B66: Version control
B67: Version | C67: Date | D67: Author | E67: Detail
B68: v0.1 | C68: 29/10/2026 | D68: Claude, for Cian | E68: Draft. Motor, contents and buildings large claims rebuilt from Ger's export with live formulas; office premium with switches for expense basis, comparison-site commission and cat reinsurance base. Buildings small claims pending. Built without the Root Tech starter template (not available in this session), so named cell styles and custom table styles are not yet applied.
B69: v0.2 | C69: 29/10/2026 | D69: Claude, for Cian | E69: Buildings complete: small claims scored in Excel from Ger's tree tables (export commit 0e75e6c), on two new sheets, Lookups Trees and Rating Buildings Trees; Rating Buildings now ends at the large-claim GLM. 30 inputs the trees use added to Int. Inputs. Buildings Python values now XGBoost 3.2.0 (buildings as is matches Ger's 502.552252). Four new checks; buildings tolerance 1e-5 because Excel adds the leaves in double precision and XGBoost in single. Open items cleared.
B70: v0.3 | C70: 29/10/2026 | D70: Claude, for Cian | E70: Graphs: 33 charts (relativity line over the 2025 book's exposure) for every numeric and ordered factor, the motor typical-driver age profile and the buildings tree curves; a smoothness scan with flags (reversal over 2%, or a step over 10% on a curve) and a first read of each. New sheets Graph Data and Graphs. No change to any premium.
B71: v0.4 | C71: 29/10/2026 | D71: Claude, for Cian | E71: Charts tidied to Cian's clean-up of the NCB chart: no gridlines, title and legend outside the plot area. From the data-visualisation skill: lighter axes and labels, no tick marks or chart border, colour-blind-safe orange line; age profile highlights the combined line. Graphs and Reference Policies unbranded (neutral colours). No change to any premium.
B73: Named ranges
B74: Name | C74: Sheet | D74: Range / purpose
B75: Exp_Item | C75: Ext. Inputs | D75: $B$7:$B$14 (Expense item names)
B76: Exp_Dev | C76: Ext. Inputs | D76: $C$7:$C$14 (Developed-market expense values)
B77: Exp_Emg | C77: Ext. Inputs | D77: $D$7:$D$14 (Emerging-market expense values)
B78: Lvl_Bld | C78: Ext. Inputs | D78: $C$19 (Level step 1, buildings)
B79: Lvl_Cnt | C79: Ext. Inputs | D79: $C$20 (Level step 1, contents)
B80: Lvl_MotRen | C80: Ext. Inputs | D80: $C$21 (Level step 1, motor renewals)
B81: Lvl_MotNB | C81: Ext. Inputs | D81: $C$22 (Level step 1, motor new business)
B82: Lvl_MotNB2 | C82: Ext. Inputs | D82: $C$23 (Level step 2, motor new business)
B83: SI_Thr_Cnt | C83: Ext. Inputs | D83: $C$24 (D-02 contents threshold)
B84: SI_Thr_Bld | C84: Ext. Inputs | D84: $C$25 (D-02 buildings threshold)
B85: SI_Div | C85: Ext. Inputs | D85: $C$26 (D-02 divisor)
... B140: OP_Fixed | C140: Office Premium | D140: $K$17:$K$36 (Office premium: Fixed expense)
B142: Excel Tables
B143: None in v0.1: blocks are plain ranges with grey headings, addressed through the named ranges above.
B145: Flow rule
B146: No formula refers to a cell, range or sheet to its right. Inputs sit on the left, outputs on the right. The checks summary above is the only exception. Each sheet's checks sit above the column they test.

Sheet Ext. Inputs
B2: Ext. Inputs: static inputs delivered with the data or taken from the model export
B3: Blue cells are delivered values: change them only if the source changes. Sources are noted beside each block.
B5: Expense assumptions (expenses.parquet)
B6: Item | C6: Developed | D6: Emerging | E6: Unit
B7: fixed_expense_per_policy | C7: 45 | D7: 85 | E7: CU
B8: variable_expense | C8: 0.12 | D8: 0.15 | E8: share of premium
B9: commission_direct | C9: 0 | D9: 0 | E9: share of premium
B10: commission_comparison_site | C10: 0.1 | E10: share of premium
B11: commission_broker | C11: 0.15 | D11: 0.2 | E11: share of premium
B12: premium_tax | C12: 0.12 | D12: 0.08 | E12: share of premium
B13: cat_reinsurance | C13: 0.06 | D13: 0.12 | E13: share of property risk premium
B14: target_profit_margin | C14: 0.05 | D14: 0.08 | E14: share of premium
B15: The emerging comparison-site commission is blank in the delivered file; Int. Inputs sets what stands in for it.
B17: Model scalars (export scalars.csv, run f3548525)
B18: Item | C18: Value | D18: Note
B19: Level step 1: buildings | C19: 0.95748473 | D19: halfway scale, all buildings rows
B20: Level step 1: contents | C20: 0.86574939 | D20: halfway scale, all contents rows
B21: Level step 1: motor renewals | C21: 0.8614202 | D21: halfway scale
B22: Level step 1: motor new business | C22: 0.9807983 | D22: halfway scale, then step 2
B23: Level step 2: motor new business | C23: 1.05 | D23: x1.05, then divided by its step 1 (final file A31 write4.py)
B24: Sum insured fix D-02: contents threshold | C24: 1000000 | D24: at or above: divide by the divisor
B25: Sum insured fix D-02: buildings threshold | C25: 10000000 | D25: at or above: divide by the divisor
B26: Sum insured fix D-02: divisor | C26: 1000
B27: Buildings XGBoost base rate | C27: 350.18118 | D27: in the offset: ln(base rate) is added to the margin
B28: Buildings small-claim trend multiplier 2025 | C28: 1.1203255 | D28: in the offset: ln(multiplier) is added to the margin
B30: Python results for the reference policies (check values; buildings small claims are an input)
B31: Policy row | C31: Line | D31: Small claim | E31: Large claim | F31: As is | G31: Final
B32: M00118569 | C32: motor | D32: 681.55096 | E32: 69.689487 | F32: 751.24045 | G32: 647.1337
B33: M00129413 | C33: motor | D33: 213.04057 | E33: 13.360613 | F33: 226.40119 | G33: 237.72125
B34: M00153851 | C34: motor | D34: 328.14408 | E34: 7.1410228 | F34: 335.28511 | G34: 352.04936
B35: M00161473 | C35: motor | D35: 1172.0059 | E35: 71.518074 | F35: 1243.524 | G35: 1305.7002
B36: M00167496 | C36: motor | D36: 539.20026 | E36: 75.519747 | F36: 614.72 | G36: 645.456
B37: M00176777 | C37: motor | D37: 834.38404 | E37: 39.971419 | F37: 874.35546 | G37: 918.07323
B38: M00185311 | C38: motor | D38: 1024.3208 | E38: 71.518074 | F38: 1095.8388 | G38: 1150.6308
B39: B00215707 | C39: buildings | D39: 246.71988 | E39: 51.962513 | F39: 298.68239 | G39: 285.98383
B40: B00215809 | C40: buildings | D40: 456.50452 | E40: 113.28205 | F40: 569.78657 | G40: 545.56193
B41: B00217584 | C41: buildings | D41: 1266.0942 | E41: 587.67961 | F41: 1853.7738 | G41: 1774.9601
B42: B00218282 | C42: buildings | D42: 280.72574 | E42: 29.453764 | F42: 310.1795 | G42: 296.99214
B43: B00223369 | C43: buildings | D43: 368.43826 | E43: 46.044228 | F43: 414.48249 | G43: 396.86065
... B51: C00314425 | C51: contents | D51: 7.1380567 | E51: 0 | F51: 7.1380567 | G51: 6.1797682
B52: Source: independent Python pricing from the export tables. Motor and contents match Ger's as-is rates (710.100012 and 130.999602) exactly; buildings small claims are XGBoost 3.2.0 scored from buildings_xgboost.json, and buildings as is matches Ger's 502.552252 exactly.

Sheet Int. Inputs
B2: Int. Inputs: switches and the 20 reference policies
B3: Green cells are yours to change. Edit a policy's details to re-quote it; every sheet to the right recalculates.
B5: Switch / assumption | C5: Value | D5: Note
B6: Expense basis (market column) | C6: emerging | D6: emerging or developed, from expenses.parquet
B7: Comparison-site commission if blank | C7: 0.1 | D7: The emerging rate is blank; Ger's office_premium.py uses the developed 10%. An assumption for the team
B8: Cat reinsurance base | C8: All property risk premium | D8: All property risk premium (Ger's office_premium.py) or Cat perils only (Bridget, discussion #171)
B9: Cat peril share: buildings | C9: 0.3498 | D9: Storm + flood share of emerging 2023-24 buildings claims cost (net incurred, excluding repudiated). Used only when the base is Cat perils only
B10: Cat peril share: contents | C10: 0.3041 | D10: Flood share of emerging 2023-24 contents claims cost (contents has no storm peril). Used only when the base is Cat perils only
B13: Reference policies (reference_policies.parquet, with customer, address and 2025 weather fields joined; blank = missing or not applicable)
B14: row_id | C14: line | D14: new_business | E14: channel | F14: period_start | G14: period_end | H14: exposure | I14: written_premium | J14: driver_age_band | K14: years_licensed | L14: ncb_years | M14: vehicle_value_group | N14: vehicle_age | O14: cover_type | P14: vehicle_use | Q14: voluntary_excess | R14: payment_method | S14: missed_payments_12m | T14: marketing_segment | U14: prior_claims_5y | V14: policyholder_age_band | W14: sum_insured | X14: construction_type | Y14: tenure | Z14: security_level | AA14: high_value_items | AB14: accidental_damage_cover | AC14: bicycle_cover | AD14: works_from_home | AE14: lodgers | AF14: urban_density | AG14: flood_zone | AH14: elevation_m | AI14: distance_to_river_km | AJ14: soil_type | AK14: property_type | AL14: year_built | AM14: energy_rating | AN14: dry_summer_index | AO14: rainfall_mm | AP14: days_unoccupied | AQ14: renewal_count | AR14: days_quote_to_inception | AS14: discount_applied | AT14: occupancy | AU14: smoke_alarms | AV14: mortgage | AW14: household_size | AX14: licence_points | AY14: years_at_address | AZ14: customer_since_year | BA14: marital_status | BB14: email_domain | BC14: marketing_consent | BD14: document_preference | BE14: previous_insurer | BF14: campaign_code | BG14: branch_id | BH14: bedrooms | BI14: roof_type | BJ14: basement | BK14: trees_within_5m | BL14: listed_building | BM14: solar_panels | BN14: hail_days | BO14: wind_exposure_index | BP14: freezing_days | BQ14: wildfire_index | BR14: mean_temperature_c | BS14: customer_id | BT14: address_id
B15: Policy row | C15: Line | D15: New business | E15: Channel | F15: Period start | G15: Period end | H15: Exposure (reference file) | I15: Written premium (CU) | J15: Driver age band | K15: Years licensed | L15: NCB years | M15: Vehicle value group | N15: Vehicle age | O15: Cover type | P15: Vehicle use | Q15: Voluntary excess | R15: Payment method | S15: Missed payments 12m | T15: Marketing segment | U15: Prior claims 5y | V15: Policyholder age band | W15: Sum insured (raw) | X15: Construction code (raw) | Y15: Tenure | Z15: Security level | AA15: High-value items | AB15: Accidental damage cover | AC15: Bicycle cover | AD15: Works from home | AE15: Lodgers | AF15: Urban density | AG15: Flood zone | AH15: Elevation (m) | AI15: Distance to river (km) | AJ15: Soil type | AK15: Property type | AL15: Year built (raw) | AM15: Energy rating | AN15: Dry summer index 2025 | AO15: Rainfall 2025 (mm) | AP15: Days unoccupied | AQ15: Renewal count | AR15: Days quote to inception | AS15: Discount applied | AT15: Occupancy | AU15: Smoke alarms | AV15: Mortgage | AW15: Household size | AX15: Licence points | AY15: Years at address | AZ15: Customer since (year) | BA15: Marital status | BB15: Email domain | BC15: Marketing consent | BD15: Document preference | BE15: Previous insurer | BF15: Campaign code | BG15: Branch | BH15: Bedrooms | BI15: Roof type | BJ15: Basement | BK15: Trees within 5m | BL15: Listed building | BM15: Solar panels | BN15: Hail days 2025 | BO15: Wind exposure index 2025 | BP15: Freezing days 2025 | BQ15: Wildfire index 2025 | BR15: Mean temperature 2025 (C) | BS15: Customer | BT15: Address
B16: M00118569 | C16: motor | D16: false | E16: direct | F16: 45658 | G16: 46000 | H16: 0.9397 | I16: 1095.48 | J16: 17-24 | K16: 2 | L16: 1 | M16: 6 | N16: 11 | O16: third_party_fire_theft | P16: social | Q16: 0 | R16: monthly | S16: 0 | T16: young_mainstream | U16: 0 | AF16: suburban | AG16: 1 | AH16: 10.4 | AI16: 1.37 | AJ16: sand | AK16: terraced | AL16: 2016 | AN16: 0.754 | AO16: 1017 | AQ16: 4 | AR16: 16 | AS16: 0.05 | AW16: 2 | AX16: 0 | AY16: 4 | AZ16: 2021 | BA16: single | BB16: netbox | BC16: false | BD16: email | BE16: INS04 | BG16: 2 | BH16: 3 | BI16: pitched | BJ16: false | BK16: false | BL16: false | BM16: false | BN16: 7 | BO16: 5.7 | BP16: 52 | BQ16: 0.521 | BR16: 13.2 | BS16: 81575987 | BT16: A6924348
B17: M00129413 | C17: motor | D17: true | E17: broker | F17: 45902 | G17: 46022 | H17: 0.3315 | I17: 354.15 | J17: 25-34 | K17: 5 | L17: 5 | M17: 5 | O17: comprehensive | P17: social | Q17: 250 | R17: monthly | S17: 0 | T17: young_budget | U17: 1 | AF17: rural | AG17: 1 | AH17: 15.1 | AI17: 4.66 | AJ17: sand | AK17: detached | AL17: 1991 | AM17: B | AN17: 0.329 | AO17: 1071 | AQ17: 0 | AR17: 2 | AS17: 0 | AW17: 2 | AX17: 0 | AY17: 11 | AZ17: 2025 | BA17: married | BB17: netbox | BC17: false | BD17: email | BE17: INS17 | BF17: CMP09 | BG17: 9 | BH17: 4 | BI17: pitched | BJ17: false | BK17: false | BL17: false | BM17: false | BN17: 10 | BO17: 6.6 | BP17: 39 | BQ17: 0.39 | BR17: 11.5 | BS17: 05068935 | BT17: A0759646
B18: M00153851 | C18: motor | D18: true | E18: broker | F18: 45672 | G18: 46022 | H18: 0.9616 | I18: 414.72 | J18: 35-49 | K18: 29 | L18: 10 | M18: 9 | N18: 4 | O18: comprehensive | P18: commuting | Q18: 0 | R18: annual | S18: 0 | T18: midlife_affluent | U18: 0 | AF18: suburban | AG18: 1 | AH18: 11.8 | AJ18: loam | AK18: detached | AL18: 2012 | AM18: A | AN18: 0.925 | AO18: 1276 | AQ18: 0 | AR18: 18 | AS18: 0 | AW18: 5 | AX18: 0 | AY18: 2 | AZ18: 2025 | BA18: married | BB18: inboxly | BC18: false | BD18: email | BE18: INS26 | BF18: CMP13 | BG18: 5 | BH18: 4 | BI18: pitched | BJ18: false | BK18: false | BL18: false | BM18: false | BN18: 2 | BO18: 4.2 | BP18: 0 | BQ18: 0.69 | BR18: 18.8 | BS18: 72238013 | BT18: A9220498
B19: M00161473 | C19: motor | D19: true | E19: broker | F19: 45671 | G19: 46022 | H19: 0.9644 | I19: 1131.78 | J19: 17-24 | K19: 0 | L19: 0 | M19: 6 | N19: 15 | O19: third_party_fire_theft | P19: social | Q19: 250 | R19: monthly | S19: 0 | T19: young_mainstream | U19: 1 | AF19: rural | AG19: 1 | AH19: 15.2 | AI19: 6.2 | AJ19: clay | AK19: flat | AL19: 1956 | AM19: D | AN19: 0.507 | AO19: 1077 | AQ19: 0 | AR19: 24 | AS19: 0 | AW19: 2 | AX19: 0 | AY19: 2 | AZ19: 2025 | BA19: single | BB19: mailone | BC19: true | BD19: email | BE19: INS36 | BF19: CMP02 | BG19: 21 | BH19: 1 | BI19: pitched | BJ19: false | BK19: true | BL19: false | BM19: false | BN19: 24 | BO19: 7 | BP19: 23 | BQ19: 0.554 | BR19: 14.2 | BS19: 88632978 | BT19: A3687131
B20: M00167496 | C20: motor | D20: true | E20: broker | F20: 45664 | G20: 46022 | H20: 0.9836 | I20: 463.95 | J20: 25-34 | K20: 9 | L20: 6 | M20: 8 | N20: 11 | O20: comprehensive | P20: business | Q20: 250 | R20: monthly | S20: 0 | T20: young_mainstream | U20: 0 | AF20: suburban | AG20: 1 | AH20: 5.5 | AI20: 1.94 | AJ20: loam | AK20: semi_detached | AL20: 1870 | AM20: G | AN20: 0.717 | AO20: 873 | AQ20: 0 | AR20: 12 | AS20: 0 | AW20: 1 | AX20: 0 | AY20: 8 | AZ20: 2025 | BA20: single | BB20: posthub | BC20: true | BD20: email | BE20: INS14 | BF20: CMP12 | BG20: 3 | BH20: 2 | BI20: flat | BJ20: false | BK20: false | BL20: false | BM20: false | BN20: 9 | BO20: 7.1 | BP20: 50 | BQ20: 0.383 | BR20: 13.1 | BS20: 48843509 | BT20: A6557449
B21: M00176777 | C21: motor | D21: true | E21: broker | F21: 45661 | G21: 46022 | H21: 0.9918 | I21: 443.61 | J21: 25-34 | K21: 6 | L21: 5 | M21: 11 | N21: 5 | O21: comprehensive | P21: commuting | Q21: 0 | R21: annual | S21: 0 | T21: young_mainstream | U21: 1 | AF21: urban | AH21: 8.5 | AI21: 5.76 | AJ21: rock | AK21: semi_detached | AL21: 1875 | AM21: G | AN21: 0.81 | AO21: 1095 | AQ21: 0 | AR21: 23 | AS21: 0 | AW21: 1 | AX21: 3 | AZ21: 2025 | BA21: divorced | BB21: other | BC21: true | BD21: email | BE21: INS35 | BF21: CMP09 | BG21: 22 | BH21: 2 | BI21: pitched | BJ21: false | BK21: false | BL21: false | BM21: false | BN21: 10 | BO21: 4.4 | BP21: 44 | BQ21: 0.447 | BR21: 14.1 | BS21: 30215970 | BT21: A8460609
B22: M00185311 | C22: motor | D22: true | E22: direct | F22: 45671 | G22: 46022 | H22: 0.9644 | I22: 872.31 | J22: 17-24 | K22: 0 | L22: 1 | M22: 12 | O22: third_party_only | P22: business | Q22: 1000 | R22: monthly | S22: 0 | T22: young_affluent | U22: 0 | AF22: urban | AG22: 1 | AH22: 5.5 | AI22: 1.05 | AJ22: clay | AK22: terraced | AL22: 2017 | AM22: A | AN22: 0.652 | AO22: 1027 | AQ22: 0 | AR22: 26 | AS22: 0.05 | AW22: 1 | AX22: 0 | AY22: 7 | AZ22: 2025 | BA22: single | BB22: mailone | BC22: false | BD22: post | BE22: INS07 | BF22: CMP14 | BG22: 9 | BH22: 3 | BI22: pitched | BJ22: false | BK22: false | BL22: false | BM22: false | BN22: 13 | BO22: 6.8 | BP22: 13 | BQ22: 0.516 | BR22: 15.8 | BS22: 37533851 | BT22: A1367449
B23: B00215707 | C23: buildings | D23: true | E23: broker | F23: 45663 | G23: 46022 | H23: 0.9863 | I23: 272.44 | Q23: 0 | R23: monthly | S23: 0 | T23: mature_affluent | U23: 0 | V23: 50-64 | W23: 316000 | X23: BRK | AB23: true | AF23: urban | AG23: 1 | AH23: 12.5 | AI23: 5.8 | AJ23: chalk | AK23: detached | AL23: 2006 | AM23: B | AN23: 0.636 | AO23: 1196 | AP23: 9 | AQ23: 0 | AR23: 29 | AS23: 0 | AT23: owner_occupied | AU23: true | AV23: false | AW23: 4 | AX23: 0 | AY23: 14 | AZ23: 2025 | BA23: single | BB23: other | BC23: false | BD23: post | BE23: INS21 | BF23: CMP00 | BG23: 25 | BH23: 6 | BI23: pitched | BJ23: false | BK23: false | BL23: false | BM23: false | BN23: 16 | BO23: 6.7 | BP23: 36 | BQ23: 0.556 | BR23: 13.9 | BS23: 44849767 | BT23: A3936314
B24: B00215809 | C24: buildings | D24: true | E24: direct | F24: 45667 | G24: 46022 | H24: 0.9753 | I24: 237.22 | Q24: 0 | R24: annual | S24: 0 | T24: young_budget | U24: 0 | V24: 17-24 | W24: 362000 | X24: BRK | AB24: false | AF24: urban | AG24: 1 | AH24: 5.6 | AI24: 3.55 | AJ24: clay | AK24: detached | AL24: 1940 | AM24: F | AN24: 0.595 | AO24: 1369 | AP24: 6 | AQ24: 0 | AR24: 5 | AS24: 0.05 | AT24: owner_occupied | AV24: false | AW24: 2 | AX24: 0 | AY24: 5 | AZ24: 2025 | BB24: netbox | BC24: false | BD24: email | BE24: INS28 | BF24: CMP05 | BG24: 12 | BH24: 5 | BJ24: false | BK24: false | BL24: false | BM24: false | BN24: 7 | BO24: 3.4 | BP24: 7 | BQ24: 0.679 | BR24: 16.3 | BS24: 56272063 | BT24: A0629559
B25: B00217584 | C25: buildings | D25: true | E25: broker | F25: 45670 | G25: 46022 | H25: 0.9671 | I25: 323.36 | Q25: 0 | R25: monthly | S25: 0 | T25: mature_mainstream | U25: 0 | V25: 50-64 | W25: 198000 | X25: MIX | AB25: false | AF25: suburban | AH25: 0.6 | AI25: 1.66 | AJ25: sand | AK25: semi_detached | AL25: 1933 | AM25: D | AN25: 0.61 | AO25: 1639 | AQ25: 0 | AR25: 8 | AS25: 0 | AT25: owner_occupied | AU25: true | AV25: false | AW25: 5 | AX25: 0 | AY25: 17 | AZ25: 2025 | BA25: married | BB25: netbox | BC25: true | BD25: app | BE25: INS26 | BF25: CMP07 | BG25: 3 | BH25: 3 | BI25: pitched | BJ25: false | BK25: false | BL25: false | BM25: false | BN25: 13 | BO25: 1.9 | BP25: 26 | BQ25: 0.741 | BR25: 14.8 | BS25: 38298979 | BT25: A4959022
B26: B00218282 | C26: buildings | D26: true | E26: broker | F26: 45668 | G26: 46022 | H26: 0.9726 | I26: 230.8 | Q26: 250 | R26: annual | S26: 0 | T26: mature_affluent | U26: 1 | V26: 65+ | W26: 222000 | X26: MIX | AB26: false | AF26: rural | AG26: 1 | AH26: 10.9 | AI26: 2.16 | AJ26: rock | AK26: detached | AL26: 2020 | AM26: A | AN26: 0.992 | AO26: 1398 | AP26: 8 | AQ26: 0 | AR26: 0 | AS26: 0 | AT26: owner_occupied | AU26: true | AV26: false | AW26: 3 | AX26: 0 | AY26: 1 | AZ26: 2025 | BA26: married | BB26: other | BC26: true | BD26: email | BE26: INS25 | BF26: CMP08 | BG26: 25 | BH26: 3 | BI26: pitched | BJ26: false | BK26: false | BL26: false | BM26: false | BN26: 0 | BO26: 7.6 | BP26: 3 | BQ26: 0.739 | BR26: 19 | BS26: 44487130 | BT26: A6888229
B27: B00223369 | C27: buildings | D27: true | E27: broker | F27: 45660 | G27: 46022 | H27: 0.9945 | I27: 204.56 | Q27: 0 | R27: monthly | S27: 0 | T27: young_affluent | U27: 0 | V27: 17-24 | W27: 222000 | X27: WOD | AB27: false | AF27: suburban | AG27: 1 | AH27: 8.1 | AI27: 6.64 | AJ27: rock | AK27: semi_detached | AL27: 1903 | AM27: E | AN27: 0.577 | AO27: 1080 | AP27: 5 | AQ27: 0 | AR27: 9 | AS27: 0 | AT27: owner_occupied | AU27: true | AV27: true | AW27: 1 | AX27: 6 | AY27: 5 | AZ27: 2025 | BA27: single | BB27: inboxly | BC27: true | BD27: email | BE27: INS38 | BF27: CMP06 | BG27: 19 | BH27: 4 | BI27: pitched | BJ27: true | BK27: true | BL27: false | BM27: false | BN27: 12 | BO27: 7.8 | BP27: 5 | BQ27: 0.437 | BR27: 15.9 | BS27: 24183771 | BT27: A5001830
B28: B00229821 | C28: buildings | D28: true | E28: broker | F28: 45661 | G28: 46022 | H28: 0.9918 | I28: 285.6 | Q28: 250 | R28: monthly | S28: 0 | T28: mature_mainstream | U28: 0 | V28: 50-64 | W28: 378000 | X28: BRK | AB28: false | AF28: rural | AG28: 1 | AH28: 16 | AI28: 2.39 | AJ28: sand | AK28: terraced | AL28: 1979 | AM28: C | AN28: 0.571 | AO28: 1158 | AP28: 3 | AQ28: 0 | AR28: 21 | AS28: 0 | AT28: owner_occupied | AU28: true | AV28: true | AW28: 1 | AX28: 0 | AY28: 9 | AZ28: 2025 | BA28: single | BB28: other | BC28: true | BD28: email | BE28: INS16 | BF28: CMP06 | BG28: 10 | BH28: 4 | BI28: pitched | BJ28: false | BK28: false | BL28: false | BM28: false | BN28: 7 | BO28: 5.4 | BP28: 30 | BQ28: 0.53 | BR28: 14 | BS28: 32030141 | BT28: A4529319
B29: B00250679 | C29: buildings | D29: true | E29: broker | F29: 45983 | G29: 46022 | H29: 0.1096 | I29: 180.72 | Q29: 0 | R29: annual | S29: 0 | T29: midlife_budget | U29: 0 | V29: 35-49 | W29: 236000 | X29: BRK | AB29: true | AF29: rural | AG29: 1 | AH29: 3.2 | AI29: 9.41 | AJ29: clay | AK29: flat | AL29: 2013 | AM29: A | AN29: 0.852 | AO29: 1041 | AP29: 4 | AQ29: 0 | AR29: 20 | AS29: 0 | AT29: let | AU29: false | AV29: true | AW29: 4 | AX29: 0 | AY29: 4 | AZ29: 2025 | BA29: married | BB29: other | BC29: false | BD29: email | BE29: INS39 | BF29: CMP14 | BG29: 12 | BH29: 2 | BI29: flat | BJ29: false | BK29: false | BL29: false | BM29: true | BN29: 19 | BO29: 5.2 | BP29: 44 | BQ29: 0.395 | BR29: 14.4 | BS29: 61828611 | BT29: A3204800
B30: C00259568 | C30: contents | D30: false | E30: broker | F30: 45658 | G30: 46022 | H30: 1 | I30: 83.18 | Q30: 1000 | R30: monthly | S30: 0 | T30: young_affluent | U30: 0 | V30: 25-34 | W30: 22100 | Y30: renter | Z30: alarm_and_locks | AA30: 3 | AB30: false | AC30: false | AD30: false | AE30: false | AF30: suburban | AG30: 1 | AH30: 15.1 | AI30: 4.48 | AJ30: clay | AK30: semi_detached | AL30: 1987 | AM30: C | AN30: 0.515 | AO30: 1911 | AQ30: 14 | AR30: 13 | AS30: 0 | AW30: 3 | AX30: 0 | AY30: 3 | AZ30: 2011 | BA30: single | BB30: netbox | BC30: true | BD30: email | BE30: INS16 | BG30: 3 | BH30: 4 | BI30: pitched | BJ30: false | BK30: false | BL30: false | BM30: true | BN30: 17 | BO30: 3.7 | BP30: 14 | BQ30: 0.797 | BR30: 15.2 | BS30: 92249376 | BT30: A4488430
B31: C00270331 | C31: contents | D31: true | E31: broker | F31: 45668 | G31: 46022 | H31: 0.9726 | I31: 140.29 | Q31: 1000 | R31: annual | S31: 0 | T31: mature_mainstream | U31: 0 | V31: 50-64 | W31: 33400 | Y31: renter | Z31: alarm_and_locks | AB31: true | AC31: false | AD31: true | AE31: false | AF31: suburban | AG31: 1 | AH31: 17.1 | AI31: 1.86 | AJ31: loam | AK31: detached | AL31: 1951 | AM31: C | AN31: 0.809 | AO31: 980 | AQ31: 0 | AR31: 22 | AS31: 0 | AW31: 5 | AX31: 0 | AY31: 6 | AZ31: 2025 | BA31: married | BB31: posthub | BC31: false | BD31: email | BE31: INS18 | BF31: CMP13 | BG31: 3 | BH31: 3 | BI31: pitched | BJ31: false | BK31: false | BL31: false | BM31: false | BN31: 6 | BO31: 5.2 | BP31: 57 | BQ31: 0.309 | BR31: 13.1 | BS31: 58944765 | BT31: A3143736
B32: C00283470 | C32: contents | D32: true | E32: broker | F32: 45668 | G32: 46022 | H32: 0.9726 | I32: 117.97 | Q32: 250 | R32: annual | S32: 0 | T32: senior_affluent | U32: 1 | V32: 65+ | W32: 35700 | Y32: owner | Z32: locks | AA32: 4 | AB32: false | AC32: false | AD32: true | AE32: false | AF32: rural | AG32: 1 | AH32: 17.3 | AI32: 2.94 | AJ32: rock | AK32: terraced | AL32: 1956 | AM32: C | AN32: 0.606 | AO32: 1106 | AQ32: 0 | AR32: 4 | AS32: 0 | AX32: 0 | AY32: 3 | AZ32: 2025 | BA32: married | BB32: other | BC32: false | BD32: email | BE32: INS14 | BF32: CMP05 | BG32: 24 | BH32: 4 | BI32: pitched | BJ32: false | BK32: true | BL32: false | BM32: false | BN32: 10 | BO32: 6.8 | BP32: 18 | BQ32: 0.586 | BR32: 15.1 | BS32: 93454577 | BT32: A2257901
B33: C00286287 | C33: contents | D33: true | E33: broker | F33: 45670 | G33: 46022 | H33: 0.9671 | I33: 269.23 | Q33: 0 | R33: annual | S33: 0 | T33: midlife_mainstream | U33: 0 | V33: 35-49 | W33: 71100 | Y33: owner | Z33: standard | AA33: 0 | AB33: false | AC33: false | AD33: false | AE33: false | AF33: suburban | AG33: 3 | AH33: 1.6 | AI33: 0.23 | AK33: flat | AL33: 1975 | AM33: C | AN33: 0.665 | AO33: 1554 | AQ33: 0 | AR33: 28 | AS33: 0 | AW33: 3 | AX33: 0 | AZ33: 2025 | BA33: single | BB33: netbox | BC33: true | BD33: app | BE33: INS17 | BF33: CMP14 | BG33: 22 | BH33: 1 | BI33: pitched | BJ33: false | BK33: true | BL33: false | BM33: false | BN33: 5 | BO33: 2.4 | BP33: 27 | BQ33: 0.818 | BR33: 15.1 | BS33: 68661780 | BT33: A2307133
B34: C00302985 | C34: contents | D34: true | E34: broker | F34: 45661 | G34: 46022 | H34: 0.9918 | I34: 115.88 | Q34: 250 | R34: annual | S34: 0 | T34: senior_budget | U34: 0 | V34: 65+ | W34: 22900 | Y34: owner | Z34: alarm_and_locks | AA34: 5 | AB34: false | AC34: false | AD34: false | AE34: false | AF34: suburban | AG34: 1 | AH34: 32.4 | AI34: 5.58 | AJ34: clay | AK34: flat | AL34: 1900 | AM34: E | AN34: 0.64 | AO34: 1471 | AQ34: 0 | AR34: 19 | AS34: 0 | AW34: 4 | AX34: 0 | AY34: 9 | AZ34: 2025 | BB34: other | BC34: true | BD34: email | BE34: INS34 | BF34: CMP12 | BG34: 15 | BH34: 1 | BI34: pitched | BJ34: false | BK34: false | BL34: false | BM34: false | BN34: 12 | BO34: 1.3 | BP34: 15 | BQ34: 0.76 | BR34: 15.9 | BS34: 77971827 | BT34: A0664702
B35: C00314425 | C35: contents | D35: true | E35: broker | F35: 45670 | G35: 45694 | H35: 0.0685 | I35: 102.87 | Q35: 250 | R35: annual | S35: 0 | T35: young_affluent | U35: 1 | V35: 25-34 | W35: 27200 | Y35: owner | Z35: standard | AA35: 0 | AB35: false | AC35: false | AD35: false | AE35: false | AF35: rural | AG35: 1 | AH35: 1.5 | AI35: 2.3 | AJ35: clay | AK35: terraced | AL35: 1936 | AM35: C | AN35: 0.467 | AO35: 1009 | AQ35: 0 | AR35: 28 | AS35: 0 | AW35: 3 | AX35: 0 | AY35: 6 | AZ35: 2025 | BA35: married | BB35: netbox | BC35: true | BD35: app | BE35: INS35 | BF35: CMP14 | BG35: 8 | BH35: 3 | BI35: pitched | BJ35: false | BK35: false | BL35: false | BM35: false | BN35: 9 | BO35: 5.9 | BP35: 41 | BQ35: 0.378 | BR35: 12.2 | BS35: 27597742 | BT35: A3128511

Sheet Lookups
B2: Lookups: the fitted model as rating tables (export terms.csv), plus the input maps
B3: Key = line|component|term|level (or the value at the curve's recorded precision). Log contribution is added to the linear predictor; Relativity = EXP of it. Infinite band edges are written as +/-1E+307.
B5: Rating terms (8,100 rows) | P5: Categorical remaps
B6: Key | C6: Line | D6: Component | E6: Term | F6: Kind | G6: Level | H6: Value | I6: Band lower | J6: Band upper | K6: Log contribution | L6: Relativity | M6: Note | N6: Line|component|term | P6: Key | Q6: Scores as
B7: buildings|large|(intercept)| | C7: buildings | D7: large | E7: (intercept) | F7: intercept | K7: 5.9293315 | L7: =IF(ISNUMBER(K7),EXP(K7),"") | N7: buildings|large|(intercept) | P7: contents|small|f_prior_claims|3 | Q7: OTHER
B8: buildings|large|soil_type|MISSING | C8: buildings | D8: large | E8: soil_type | F8: categorical | G8: MISSING | K8: 0 | L8: =IF(ISNUMBER(K8),EXP(K8),"") | M8: base level | N8: buildings|large|soil_type | P8: contents|small|f_missed_pay|3 | Q8: OTHER
B9: buildings|large|soil_type|chalk | C9: buildings | D9: large | E9: soil_type | F9: categorical | G9: chalk | K9: 0.24009212 | L9: =IF(ISNUMBER(K9),EXP(K9),"") | N9: buildings|large|soil_type
B10: buildings|large|soil_type|clay | C10: buildings | D10: large | E10: soil_type | F10: categorical | G10: clay | K10: -0.08814148 | L10: =IF(ISNUMBER(K10),EXP(K10),"") | N10: buildings|large|soil_type | P10: Construction codes (BRK/MIX/STN/WOD)
B11: buildings|large|soil_type|loam | C11: buildings | D11: large | E11: soil_type | F11: categorical | G11: loam | K11: 0.18966518 | L11: =IF(ISNUMBER(K11),EXP(K11),"") | N11: buildings|large|soil_type | P11: Code | Q11: Model level
B12: buildings|large|soil_type|rock | C12: buildings | D12: large | E12: soil_type | F12: categorical | G12: rock | K12: -0.15840931 | L12: =IF(ISNUMBER(K12),EXP(K12),"") | N12: buildings|large|soil_type | P12: BRK | Q12: brick
B13: buildings|large|soil_type|sand | C13: buildings | D13: large | E13: soil_type | F13: categorical | G13: sand | K13: 0.17894645 | L13: =IF(ISNUMBER(K13),EXP(K13),"") | N13: buildings|large|soil_type | P13: MIX | Q13: non_standard
B14: buildings|large|soil_type|(any other level) | C14: buildings | D14: large | E14: soil_type | F14: categorical | G14: (any other level) | K14: 0 | L14: =IF(ISNUMBER(K14),EXP(K14),"") | M14: a level the fit did not see (including MISSING where no row is listed) scores as the base level | N14: buildings|large|soil_type | P14: STN | Q14: stone
B15: buildings|large|construction_type|brick | C15: buildings | D15: large | E15: construction_type | F15: categorical | G15: brick | K15: 0 | L15: =IF(ISNUMBER(K15),EXP(K15),"") | M15: base level | N15: buildings|large|construction_type | P15: WOD | Q15: timber
B16: buildings|large|construction_type|non_standard | C16: buildings | D16: large | E16: construction_type | F16: categorical | G16: non_standard | K16: 0.38602951 | L16: =IF(ISNUMBER(K16),EXP(K16),"") | N16: buildings|large|construction_type
B17: buildings|large|construction_type|stone | C17: buildings | D17: large | E17: construction_type | F17: categorical | G17: stone | K17: 0.2826839 | L17: =IF(ISNUMBER(K17),EXP(K17),"") | N17: buildings|large|construction_type | P17: Year built 1900 placeholder fill (D-27)
B18: buildings|large|construction_type|timber | C18: buildings | D18: large | E18: construction_type | F18: categorical | G18: timber | K18: 0.13627558 | L18: =IF(ISNUMBER(K18),EXP(K18),"") | N18: buildings|large|construction_type | P18: Energy rating | Q18: Year built
B19: buildings|large|construction_type|(any other level) | C19: buildings | D19: large | E19: construction_type | F19: categorical | G19: (any other level) | K19: 0 | L19: =IF(ISNUMBER(K19),EXP(K19),"") | M19: a level the fit did not see (including MISSING where no row is listed) scores as the base level | N19: buildings|large|construction_type | P19: A | Q19: 2008
B20: buildings|large|flood_zone|q00 | C20: buildings | D20: large | E20: flood_zone | F20: band | G20: q00 | I20: -1e+307 | J20: 1 | K20: -0.43961743 | L20: =IF(ISNUMBER(K20),EXP(K20),"") | M20: lower < x <= upper | N20: buildings|large|flood_zone | P20: B | Q20: 1993
B21: buildings|large|flood_zone|q01 | C21: buildings | D21: large | E21: flood_zone | F21: band | G21: q01 | I21: 1 | J21: 2 | K21: -0.42625283 | L21: =IF(ISNUMBER(K21),EXP(K21),"") | M21: lower < x <= upper | N21: buildings|large|flood_zone | P21: C | Q21: 1972
B22: buildings|large|flood_zone|q02 | C22: buildings | D22: large | E22: flood_zone | F22: band | G22: q02 | I22: 2 | J22: 1e+307 | K22: -0.34641947 | L22: =IF(ISNUMBER(K22),EXP(K22),"") | M22: lower < x <= upper | N22: buildings|large|flood_zone | P22: D | Q22: 1951
B23: buildings|large|flood_zone|MISSING | C23: buildings | D23: large | E23: flood_zone | F23: band | G23: MISSING | K23: 0 | L23: =IF(ISNUMBER(K23),EXP(K23),"") | M23: x missing; base level | N23: buildings|large|flood_zone | P23: E | Q23: 1929
B24: buildings|large|sum_insured|44000 | C24: buildings | D24: large | E24: sum_insured | F24: spline value | H24: 44000 | K24: -2.1985792 | L24: =IF(ISNUMBER(K24),EXP(K24),"") | M24: every value from 44000 to 894000 in steps of 1000 | N24: buildings|large|sum_insured | P24: F | Q24: 1902
B25: buildings|large|sum_insured|45000 | C25: buildings | D25: large | E25: sum_insured | F25: spline value | H25: 45000 | K25: -2.189532 | L25: =IF(ISNUMBER(K25),EXP(K25),"") | M25: every value from 44000 to 894000 in steps of 1000 | N25: buildings|large|sum_insured | P25: G | Q25: 1880
B26: buildings|large|sum_insured|46000 | C26: buildings | D26: large | E26: sum_insured | F26: spline value | H26: 46000 | K26: -2.1802154 | L26: =IF(ISNUMBER(K26),EXP(K26),"") | M26: every value from 44000 to 894000 in steps of 1000 | N26: buildings|large|sum_insured | P26: missing | Q26: 1961
B27: buildings|large|sum_insured|47000 | C27: buildings | D27: large | E27: sum_insured | F27: spline value | H27: 47000 | K27: -2.1706327 | L27: =IF(ISNUMBER(K27),EXP(K27),"") | M27: every value from 44000 to 894000 in steps of 1000 | N27: buildings|large|sum_insured
B28: buildings|large|sum_insured|48000 | C28: buildings | D28: large | E28: sum_insured | F28: spline value | H28: 48000 | K28: -2.1607875 | L28: =IF(ISNUMBER(K28),EXP(K28),"") | M28: every value from 44000 to 894000 in steps of 1000 | N28: buildings|large|sum_insured | P28: Curve lookup precision
B29: buildings|large|sum_insured|49000 | C29: buildings | D29: large | E29: sum_insured | F29: spline value | H29: 49000 | K29: -2.1506832 | L29: =IF(ISNUMBER(K29),EXP(K29),"") | M29: every value from 44000 to 894000 in steps of 1000 | N29: buildings|large|sum_insured | P29: Line|component|term | Q29: Key format
B30: buildings|large|sum_insured|50000 | C30: buildings | D30: large | E30: sum_insured | F30: spline value | H30: 50000 | K30: -2.1403233 | L30: =IF(ISNUMBER(K30),EXP(K30),"") | M30: every value from 44000 to 894000 in steps of 1000 | N30: buildings|large|sum_insured | P30: buildings|large|distance_to_river_km | Q30: 0.00
B31: buildings|large|sum_insured|51000 | C31: buildings | D31: large | E31: sum_insured | F31: spline value | H31: 51000 | K31: -2.1297112 | L31: =IF(ISNUMBER(K31),EXP(K31),"") | M31: every value from 44000 to 894000 in steps of 1000 | N31: buildings|large|sum_insured | P31: buildings|large|elevation_m | Q31: 0.0
B32: buildings|large|sum_insured|52000 | C32: buildings | D32: large | E32: sum_insured | F32: spline value | H32: 52000 | K32: -2.1188504 | L32: =IF(ISNUMBER(K32),EXP(K32),"") | M32: every value from 44000 to 894000 in steps of 1000 | N32: buildings|large|sum_insured | P32: buildings|large|sum_insured | Q32: 0
B33: buildings|large|sum_insured|53000 | C33: buildings | D33: large | E33: sum_insured | F33: spline value | H33: 53000 | K33: -2.1077442 | L33: =IF(ISNUMBER(K33),EXP(K33),"") | M33: every value from 44000 to 894000 in steps of 1000 | N33: buildings|large|sum_insured | P33: buildings|large|year_built | Q33: 0
B34: buildings|large|sum_insured|54000 | C34: buildings | D34: large | E34: sum_insured | F34: spline value | H34: 54000 | K34: -2.0963963 | L34: =IF(ISNUMBER(K34),EXP(K34),"") | M34: every value from 44000 to 894000 in steps of 1000 | N34: buildings|large|sum_insured | P34: contents|small|distance_to_river_km | Q34: 0.00
B35: buildings|large|sum_insured|55000 | C35: buildings | D35: large | E35: sum_insured | F35: spline value | H35: 55000 | K35: -2.0848099 | L35: =IF(ISNUMBER(K35),EXP(K35),"") | M35: every value from 44000 to 894000 in steps of 1000 | N35: buildings|large|sum_insured | P35: contents|small|elevation_m | Q35: 0.0
B36: buildings|large|sum_insured|56000 | C36: buildings | D36: large | E36: sum_insured | F36: spline value | H36: 56000 | K36: -2.0729887 | L36: =IF(ISNUMBER(K36),EXP(K36),"") | M36: every value from 44000 to 894000 in steps of 1000 | N36: buildings|large|sum_insured | P36: motor|small|ncb_years | Q36: 0
B37: buildings|large|sum_insured|57000 | C37: buildings | D37: large | E37: sum_insured | F37: spline value | H37: 57000 | K37: -2.0609359 | L37: =IF(ISNUMBER(K37),EXP(K37),"") | M37: every value from 44000 to 894000 in steps of 1000 | N37: buildings|large|sum_insured | P37: motor|small|vehicle_age | Q37: 0
B38: buildings|large|sum_insured|58000 | C38: buildings | D38: large | E38: sum_insured | F38: spline value | H38: 58000 | K38: -2.0486552 | L38: =IF(ISNUMBER(K38),EXP(K38),"") | M38: every value from 44000 to 894000 in steps of 1000 | N38: buildings|large|sum_insured | P38: motor|small|vehicle_value_group | Q38: 0
B39: buildings|large|sum_insured|59000 | C39: buildings | D39: large | E39: sum_insured | F39: spline value | H39: 59000 | K39: -2.0361499 | L39: =IF(ISNUMBER(K39),EXP(K39),"") | M39: every value from 44000 to 894000 in steps of 1000 | N39: buildings|large|sum_insured | P39: motor|small|voluntary_excess | Q39: 0
B40: buildings|large|sum_insured|60000 | C40: buildings | D40: large | E40: sum_insured | F40: spline value | H40: 60000 | K40: -2.0234234 | L40: =IF(ISNUMBER(K40),EXP(K40),"") | M40: every value from 44000 to 894000 in steps of 1000 | N40: buildings|large|sum_insured | P40: motor|small|years_licensed | Q40: 0
B41: buildings|large|sum_insured|61000 | C41: buildings | D41: large | E41: sum_insured | F41: spline value | H41: 61000 | K41: -2.0104793 | L41: =IF(ISNUMBER(K41),EXP(K41),"") | M41: every value from 44000 to 894000 in steps of 1000 | N41: buildings|large|sum_insured
B42: buildings|large|sum_insured|62000 | C42: buildings | D42: large | E42: sum_insured | F42: spline value | H42: 62000 | K42: -1.997321 | L42: =IF(ISNUMBER(K42),EXP(K42),"") | M42: every value from 44000 to 894000 in steps of 1000 | N42: buildings|large|sum_insured
B43: buildings|large|sum_insured|63000 | C43: buildings | D43: large | E43: sum_insured | F43: spline value | H43: 63000 | K43: -1.9839519 | L43: =IF(ISNUMBER(K43),EXP(K43),"") | M43: every value from 44000 to 894000 in steps of 1000 | N43: buildings|large|sum_insured
B44: buildings|large|sum_insured|64000 | C44: buildings | D44: large | E44: sum_insured | F44: spline value | H44: 64000 | K44: -1.9703755 | L44: =IF(ISNUMBER(K44),EXP(K44),"") | M44: every value from 44000 to 894000 in steps of 1000 | N44: buildings|large|sum_insured
B45: buildings|large|sum_insured|65000 | C45: buildings | D45: large | E45: sum_insured | F45: spline value | H45: 65000 | K45: -1.9565953 | L45: =IF(ISNUMBER(K45),EXP(K45),"") | M45: every value from 44000 to 894000 in steps of 1000 | N45: buildings|large|sum_insured
B46: buildings|large|sum_insured|66000 | C46: buildings | D46: large | E46: sum_insured | F46: spline value | H46: 66000 | K46: -1.9426146 | L46: =IF(ISNUMBER(K46),EXP(K46),"") | M46: every value from 44000 to 894000 in steps of 1000 | N46: buildings|large|sum_insured
B47: buildings|large|sum_insured|67000 | C47: buildings | D47: large | E47: sum_insured | F47: spline value | H47: 67000 | K47: -1.928437 | L47: =IF(ISNUMBER(K47),EXP(K47),"") | M47: every value from 44000 to 894000 in steps of 1000 | N47: buildings|large|sum_insured
B48: buildings|large|sum_insured|68000 | C48: buildings | D48: large | E48: sum_insured | F48: spline value | H48: 68000 | K48: -1.9140659 | L48: =IF(ISNUMBER(K48),EXP(K48),"") | M48: every value from 44000 to 894000 in steps of 1000 | N48: buildings|large|sum_insured
B49: buildings|large|sum_insured|69000 | C49: buildings | D49: large | E49: sum_insured | F49: spline value | H49: 69000 | K49: -1.8995047 | L49: =IF(ISNUMBER(K49),EXP(K49),"") | M49: every value from 44000 to 894000 in steps of 1000 | N49: buildings|large|sum_insured
B50: buildings|large|sum_insured|70000 | C50: buildings | D50: large | E50: sum_insured | F50: spline value | H50: 70000 | K50: -1.884757 | L50: =IF(ISNUMBER(K50),EXP(K50),"") | M50: every value from 44000 to 894000 in steps of 1000 | N50: buildings|large|sum_insured
B51: buildings|large|sum_insured|71000 | C51: buildings | D51: large | E51: sum_insured | F51: spline value | H51: 71000 | K51: -1.8698261 | L51: =IF(ISNUMBER(K51),EXP(K51),"") | M51: every value from 44000 to 894000 in steps of 1000 | N51: buildings|large|sum_insured
B52: buildings|large|sum_insured|72000 | C52: buildings | D52: large | E52: sum_insured | F52: spline value | H52: 72000 | K52: -1.8547155 | L52: =IF(ISNUMBER(K52),EXP(K52),"") | M52: every value from 44000 to 894000 in steps of 1000 | N52: buildings|large|sum_insured
... B874: buildings|large|sum_insured|894000 | C874: buildings | D874: large | E874: sum_insured | F874: spline value | H874: 894000 | K874: 1.6150114 | L874: =IF(ISNUMBER(K874),EXP(K874),"") | M874: every value from 44000 to 894000 in steps of 1000 | N874: buildings|large|sum_insured
B875: buildings|large|sum_insured|MISSING | C875: buildings | D875: large | E875: sum_insured | F875: spline missing | G875: MISSING | K875: 0 | L875: =IF(ISNUMBER(K875),EXP(K875),"") | M875: no missing values in the developed fit, so a missing value contributes 0 | N875: buildings|large|sum_insured
B876: buildings|large|elevation_m|0.0 | C876: buildings | D876: large | E876: elevation_m | F876: spline value | H876: 0 | K876: 0.011968581 | L876: =IF(ISNUMBER(K876),EXP(K876),"") | M876: every value from 0 to 60 in steps of 0.1 | N876: buildings|large|elevation_m
B877: buildings|large|elevation_m|0.1 | C877: buildings | D877: large | E877: elevation_m | F877: spline value | H877: 0.1 | K877: -0.052634199 | L877: =IF(ISNUMBER(K877),EXP(K877),"") | M877: every value from 0 to 60 in steps of 0.1 | N877: buildings|large|elevation_m
B878: buildings|large|elevation_m|0.2 | C878: buildings | D878: large | E878: elevation_m | F878: spline value | H878: 0.2 | K878: -0.11521345 | L878: =IF(ISNUMBER(K878),EXP(K878),"") | M878: every value from 0 to 60 in steps of 0.1 | N878: buildings|large|elevation_m
B879: buildings|large|elevation_m|0.3 | C879: buildings | D879: large | E879: elevation_m | F879: spline value | H879: 0.3 | K879: -0.175805 | L879: =IF(ISNUMBER(K879),EXP(K879),"") | M879: every value from 0 to 60 in steps of 0.1 | N879: buildings|large|elevation_m
B880: buildings|large|elevation_m|0.4 | C880: buildings | D880: large | E880: elevation_m | F880: spline value | H880: 0.4 | K880: -0.23444465 | L880: =IF(ISNUMBER(K880),EXP(K880),"") | M880: every value from 0 to 60 in steps of 0.1 | N880: buildings|large|elevation_m
B881: buildings|large|elevation_m|0.5 | C881: buildings | D881: large | E881: elevation_m | F881: spline value | H881: 0.5 | K881: -0.29116823 | L881: =IF(ISNUMBER(K881),EXP(K881),"") | M881: every value from 0 to 60 in steps of 0.1 | N881: buildings|large|elevation_m
B882: buildings|large|elevation_m|0.6 | C882: buildings | D882: large | E882: elevation_m | F882: spline value | H882: 0.6 | K882: -0.34601155 | L882: =IF(ISNUMBER(K882),EXP(K882),"") | M882: every value from 0 to 60 in steps of 0.1 | N882: buildings|large|elevation_m
B883: buildings|large|elevation_m|0.7 | C883: buildings | D883: large | E883: elevation_m | F883: spline value | H883: 0.7 | K883: -0.39901042 | L883: =IF(ISNUMBER(K883),EXP(K883),"") | M883: every value from 0 to 60 in steps of 0.1 | N883: buildings|large|elevation_m
B884: buildings|large|elevation_m|0.8 | C884: buildings | D884: large | E884: elevation_m | F884: spline value | H884: 0.8 | K884: -0.45020067 | L884: =IF(ISNUMBER(K884),EXP(K884),"") | M884: every value from 0 to 60 in steps of 0.1 | N884: buildings|large|elevation_m
B885: buildings|large|elevation_m|0.9 | C885: buildings | D885: large | E885: elevation_m | F885: spline value | H885: 0.9 | K885: -0.49961811 | L885: =IF(ISNUMBER(K885),EXP(K885),"") | M885: every value from 0 to 60 in steps of 0.1 | N885: buildings|large|elevation_m
B886: buildings|large|elevation_m|1.0 | C886: buildings | D886: large | E886: elevation_m | F886: spline value | H886: 1 | K886: -0.54729855 | L886: =IF(ISNUMBER(K886),EXP(K886),"") | M886: every value from 0 to 60 in steps of 0.1 | N886: buildings|large|elevation_m
B887: buildings|large|elevation_m|1.1 | C887: buildings | D887: large | E887: elevation_m | F887: spline value | H887: 1.1 | K887: -0.59327782 | L887: =IF(ISNUMBER(K887),EXP(K887),"") | M887: every value from 0 to 60 in steps of 0.1 | N887: buildings|large|elevation_m
... B1476: buildings|large|elevation_m|60.0 | C1476: buildings | D1476: large | E1476: elevation_m | F1476: spline value | H1476: 60 | K1476: -0.84915595 | L1476: =IF(ISNUMBER(K1476),EXP(K1476),"") | M1476: every value from 0 to 60 in steps of 0.1 | N1476: buildings|large|elevation_m
B1477: buildings|large|elevation_m|MISSING | C1477: buildings | D1477: large | E1477: elevation_m | F1477: spline missing | G1477: MISSING | K1477: 0 | L1477: =IF(ISNUMBER(K1477),EXP(K1477),"") | M1477: no missing values in the developed fit, so a missing value contributes 0 | N1477: buildings|large|elevation_m
B1478: buildings|large|year_built|1862 | C1478: buildings | D1478: large | E1478: year_built | F1478: spline value | H1478: 1862 | K1478: -0.011363602 | L1478: =IF(ISNUMBER(K1478),EXP(K1478),"") | M1478: every value from 1862 to 2021 in steps of 1 | N1478: buildings|large|year_built
B1479: buildings|large|year_built|1863 | C1479: buildings | D1479: large | E1479: year_built | F1479: spline value | H1479: 1863 | K1479: 0.0034938194 | L1479: =IF(ISNUMBER(K1479),EXP(K1479),"") | M1479: every value from 1862 to 2021 in steps of 1 | N1479: buildings|large|year_built
B1480: buildings|large|year_built|1864 | C1480: buildings | D1480: large | E1480: year_built | F1480: spline value | H1480: 1864 | K1480: 0.01757407 | L1480: =IF(ISNUMBER(K1480),EXP(K1480),"") | M1480: every value from 1862 to 2021 in steps of 1 | N1480: buildings|large|year_built
B1481: buildings|large|year_built|1865 | C1481: buildings | D1481: large | E1481: year_built | F1481: spline value | H1481: 1865 | K1481: 0.03089108 | L1481: =IF(ISNUMBER(K1481),EXP(K1481),"") | M1481: every value from 1862 to 2021 in steps of 1 | N1481: buildings|large|year_built
B1482: buildings|large|year_built|1866 | C1482: buildings | D1482: large | E1482: year_built | F1482: spline value | H1482: 1866 | K1482: 0.043458779 | L1482: =IF(ISNUMBER(K1482),EXP(K1482),"") | M1482: every value from 1862 to 2021 in steps of 1 | N1482: buildings|large|year_built
B1483: buildings|large|year_built|1867 | C1483: buildings | D1483: large | E1483: year_built | F1483: spline value | H1483: 1867 | K1483: 0.055291098 | L1483: =IF(ISNUMBER(K1483),EXP(K1483),"") | M1483: every value from 1862 to 2021 in steps of 1 | N1483: buildings|large|year_built
B1484: buildings|large|year_built|1868 | C1484: buildings | D1484: large | E1484: year_built | F1484: spline value | H1484: 1868 | K1484: 0.066401969 | L1484: =IF(ISNUMBER(K1484),EXP(K1484),"") | M1484: every value from 1862 to 2021 in steps of 1 | N1484: buildings|large|year_built
B1485: buildings|large|year_built|1869 | C1485: buildings | D1485: large | E1485: year_built | F1485: spline value | H1485: 1869 | K1485: 0.07680532 | L1485: =IF(ISNUMBER(K1485),EXP(K1485),"") | M1485: every value from 1862 to 2021 in steps of 1 | N1485: buildings|large|year_built
B1486: buildings|large|year_built|1870 | C1486: buildings | D1486: large | E1486: year_built | F1486: spline value | H1486: 1870 | K1486: 0.086515083 | L1486: =IF(ISNUMBER(K1486),EXP(K1486),"") | M1486: every value from 1862 to 2021 in steps of 1 | N1486: buildings|large|year_built
B1487: buildings|large|year_built|1871 | C1487: buildings | D1487: large | E1487: year_built | F1487: spline value | H1487: 1871 | K1487: 0.095545188 | L1487: =IF(ISNUMBER(K1487),EXP(K1487),"") | M1487: every value from 1862 to 2021 in steps of 1 | N1487: buildings|large|year_built
B1488: buildings|large|year_built|1872 | C1488: buildings | D1488: large | E1488: year_built | F1488: spline value | H1488: 1872 | K1488: 0.10390957 | L1488: =IF(ISNUMBER(K1488),EXP(K1488),"") | M1488: every value from 1862 to 2021 in steps of 1 | N1488: buildings|large|year_built
B1489: buildings|large|year_built|1873 | C1489: buildings | D1489: large | E1489: year_built | F1489: spline value | H1489: 1873 | K1489: 0.11162215 | L1489: =IF(ISNUMBER(K1489),EXP(K1489),"") | M1489: every value from 1862 to 2021 in steps of 1 | N1489: buildings|large|year_built
... B1637: buildings|large|year_built|2021 | C1637: buildings | D1637: large | E1637: year_built | F1637: spline value | H1637: 2021 | K1637: -0.65183811 | L1637: =IF(ISNUMBER(K1637),EXP(K1637),"") | M1637: every value from 1862 to 2021 in steps of 1 | N1637: buildings|large|year_built
B1638: buildings|large|year_built|MISSING | C1638: buildings | D1638: large | E1638: year_built | F1638: spline missing | G1638: MISSING | K1638: 0 | L1638: =IF(ISNUMBER(K1638),EXP(K1638),"") | M1638: no missing values in the developed fit, so a missing value contributes 0 | N1638: buildings|large|year_built
B1639: buildings|large|distance_to_river_km|0.01 | C1639: buildings | D1639: large | E1639: distance_to_river_km | F1639: spline value | H1639: 0.01 | K1639: -0.29246037 | L1639: =IF(ISNUMBER(K1639),EXP(K1639),"") | M1639: every value from 0.01 to 24.55 in steps of 0.01 | N1639: buildings|large|distance_to_river_km
B1640: buildings|large|distance_to_river_km|0.02 | C1640: buildings | D1640: large | E1640: distance_to_river_km | F1640: spline value | H1640: 0.02 | K1640: -0.31338041 | L1640: =IF(ISNUMBER(K1640),EXP(K1640),"") | M1640: every value from 0.01 to 24.55 in steps of 0.01 | N1640: buildings|large|distance_to_river_km
B1641: buildings|large|distance_to_river_km|0.03 | C1641: buildings | D1641: large | E1641: distance_to_river_km | F1641: spline value | H1641: 0.03 | K1641: -0.33394237 | L1641: =IF(ISNUMBER(K1641),EXP(K1641),"") | M1641: every value from 0.01 to 24.55 in steps of 0.01 | N1641: buildings|large|distance_to_river_km
B1642: buildings|large|distance_to_river_km|0.04 | C1642: buildings | D1642: large | E1642: distance_to_river_km | F1642: spline value | H1642: 0.04 | K1642: -0.35414898 | L1642: =IF(ISNUMBER(K1642),EXP(K1642),"") | M1642: every value from 0.01 to 24.55 in steps of 0.01 | N1642: buildings|large|distance_to_river_km
B1643: buildings|large|distance_to_river_km|0.05 | C1643: buildings | D1643: large | E1643: distance_to_river_km | F1643: spline value | H1643: 0.05 | K1643: -0.37400296 | L1643: =IF(ISNUMBER(K1643),EXP(K1643),"") | M1643: every value from 0.01 to 24.55 in steps of 0.01 | N1643: buildings|large|distance_to_river_km
B1644: buildings|large|distance_to_river_km|0.06 | C1644: buildings | D1644: large | E1644: distance_to_river_km | F1644: spline value | H1644: 0.06 | K1644: -0.393507 | L1644: =IF(ISNUMBER(K1644),EXP(K1644),"") | M1644: every value from 0.01 to 24.55 in steps of 0.01 | N1644: buildings|large|distance_to_river_km
B1645: buildings|large|distance_to_river_km|0.07 | C1645: buildings | D1645: large | E1645: distance_to_river_km | F1645: spline value | H1645: 0.07 | K1645: -0.41266384 | L1645: =IF(ISNUMBER(K1645),EXP(K1645),"") | M1645: every value from 0.01 to 24.55 in steps of 0.01 | N1645: buildings|large|distance_to_river_km
B1646: buildings|large|distance_to_river_km|0.08 | C1646: buildings | D1646: large | E1646: distance_to_river_km | F1646: spline value | H1646: 0.08 | K1646: -0.43147619 | L1646: =IF(ISNUMBER(K1646),EXP(K1646),"") | M1646: every value from 0.01 to 24.55 in steps of 0.01 | N1646: buildings|large|distance_to_river_km
B1647: buildings|large|distance_to_river_km|0.09 | C1647: buildings | D1647: large | E1647: distance_to_river_km | F1647: spline value | H1647: 0.09 | K1647: -0.44994676 | L1647: =IF(ISNUMBER(K1647),EXP(K1647),"") | M1647: every value from 0.01 to 24.55 in steps of 0.01 | N1647: buildings|large|distance_to_river_km
B1648: buildings|large|distance_to_river_km|0.10 | C1648: buildings | D1648: large | E1648: distance_to_river_km | F1648: spline value | H1648: 0.1 | K1648: -0.46807827 | L1648: =IF(ISNUMBER(K1648),EXP(K1648),"") | M1648: every value from 0.01 to 24.55 in steps of 0.01 | N1648: buildings|large|distance_to_river_km
B1649: buildings|large|distance_to_river_km|0.11 | C1649: buildings | D1649: large | E1649: distance_to_river_km | F1649: spline value | H1649: 0.11 | K1649: -0.48587344 | L1649: =IF(ISNUMBER(K1649),EXP(K1649),"") | M1649: every value from 0.01 to 24.55 in steps of 0.01 | N1649: buildings|large|distance_to_river_km
B1650: buildings|large|distance_to_river_km|0.12 | C1650: buildings | D1650: large | E1650: distance_to_river_km | F1650: spline value | H1650: 0.12 | K1650: -0.50333497 | L1650: =IF(ISNUMBER(K1650),EXP(K1650),"") | M1650: every value from 0.01 to 24.55 in steps of 0.01 | N1650: buildings|large|distance_to_river_km
... B4093: buildings|large|distance_to_river_km|24.55 | C4093: buildings | D4093: large | E4093: distance_to_river_km | F4093: spline value | H4093: 24.55 | K4093: -1.0772761 | L4093: =IF(ISNUMBER(K4093),EXP(K4093),"") | M4093: every value from 0.01 to 24.55 in steps of 0.01 | N4093: buildings|large|distance_to_river_km
B4094: buildings|large|distance_to_river_km|MISSING | C4094: buildings | D4094: large | E4094: distance_to_river_km | F4094: spline missing | G4094: MISSING | K4094: -0.40780402 | L4094: =IF(ISNUMBER(K4094),EXP(K4094),"") | M4094: a missing value takes this instead of the curve | N4094: buildings|large|distance_to_river_km
B4095: buildings|large|x_clay_dry|per unit | C4095: buildings | D4095: large | E4095: x_clay_dry | F4095: continuous | G4095: per unit | K4095: 0.87874392 | L4095: =IF(ISNUMBER(K4095),EXP(K4095),"") | M4095: coalesce((soil_type = 'clay') x dry_summer_index, 0) (sql/11, A28) | N4095: buildings|large|x_clay_dry
B4096: buildings|large|x_fz3_rain|per unit | C4096: buildings | D4096: large | E4096: x_fz3_rain | F4096: continuous | G4096: per unit | K4096: 0.48487798 | L4096: =IF(ISNUMBER(K4096),EXP(K4096),"") | M4096: coalesce((coalesce(flood_zone, 99) >= 3) x rainfall_mm / 1000, 0): a missing flood zone counts as 3 or above (sql/11, A28) | N4096: buildings|large|x_fz3_rain
B4097: buildings|large|trend|coefficient per year | C4097: buildings | D4097: large | E4097: trend | F4097: trend | G4097: coefficient per year | K4097: 0.045875259 | L4097: =IF(ISNUMBER(K4097),EXP(K4097),"") | M4097: no year term of its own: the small-claim model's slope, from this GLM's origin | N4097: buildings|large|trend
B4098: buildings|large|trend|origin (exposure-weighted mean fitting year) | C4098: buildings | D4098: large | E4098: trend | F4098: trend | G4098: origin (exposure-weighted mean fitting year) | H4098: 2022.5233 | L4098: =IF(ISNUMBER(K4098),EXP(K4098),"") | N4098: buildings|large|trend
B4099: buildings|large|trend|log contribution in 2025 | C4099: buildings | D4099: large | E4099: trend | F4099: trend | G4099: log contribution in 2025 | H4099: 2.4767012 | K4099: 0.11361931 | L4099: =IF(ISNUMBER(K4099),EXP(K4099),"") | M4099: value = 2025 - origin; multiplier 1.1203255482391414 | N4099: buildings|large|trend
B4100: buildings|large|ln(exposure)| | C4100: buildings | D4100: large | E4100: ln(exposure) | F4100: offset | L4100: =IF(ISNUMBER(K4100),EXP(K4100),"") | M4100: add ln(exposure in years), exposure = (period end - period start + 1) / 365 (D-01) | N4100: buildings|large|ln(exposure)
...

Sheet Lookups Trees
B2: Lookups Trees: the buildings small-claim XGBoost as tables (export buildings_xgboost_nodes.csv and _features.csv)
B3: Walk each tree from node 0: split -> left if x < Threshold, else right; category split -> right if the input's code is in Right codes, else left; a missing input goes to Missing goes; at a leaf take Leaf value. One leaf per tree, 193 trees.
B5: Tree nodes (2,577 rows) | P5: Features and category codes (218 rows)
B6: Key | C6: Tree | D6: Node | E6: Kind | F6: Position | G6: Feature | H6: Threshold | I6: Right codes | J6: Right levels | K6: Missing goes | L6: Left | M6: Right | N6: Leaf value | P6: Key | Q6: Position | R6: Feature | S6: Type | T6: Code | U6: Level | V6: Note
B7: 0|0 | C7: 0 | D7: 0 | E7: split | F7: 12 | G7: flood_zone | H7: 3.9999999 | K7: right | L7: 1 | M7: 2 | P7: sum_insured| | Q7: 0 | R7: sum_insured | S7: numeric | V7: after D-02 (divided by 1,000 at 10m or more)
B8: 0|1 | C8: 0 | D8: 1 | E8: split | F8: 15 | G8: year_built | H8: 1943.9999 | K8: right | L8: 3 | M8: 4 | P8: days_unoccupied| | Q8: 1 | R8: days_unoccupied | S8: numeric
B9: 0|2 | C9: 0 | D9: 2 | E9: split | F9: 14 | G9: elevation_m | H9: 2.1999999 | K9: right | L9: 5 | M9: 6 | P9: voluntary_excess| | Q9: 2 | R9: voluntary_excess | S9: numeric
B10: 0|3 | C10: 0 | D10: 3 | E10: split | F10: 16 | G10: bedrooms | H10: 1.9999999 | K10: right | L10: 7 | M10: 8 | P10: missed_payments_12m| | Q10: 3 | R10: missed_payments_12m | S10: numeric
B11: 0|4 | C11: 0 | D11: 4 | E11: split | F11: 16 | G11: bedrooms | H11: 2.9999999 | K11: right | L11: 9 | M11: 10 | P11: renewal_count| | Q11: 4 | R11: renewal_count | S11: numeric
B12: 0|5 | C12: 0 | D12: 5 | E12: split | F12: 12 | G12: flood_zone | H12: 4.9999998 | K12: left | L12: 11 | M12: 12 | P12: days_quote_to_inception| | Q12: 5 | R12: days_quote_to_inception | S12: numeric
B13: 0|6 | C13: 0 | D13: 6 | E13: split | F13: 13 | G13: distance_to_river_km | H13: 0.46999998 | K13: left | L13: 13 | M13: 14 | P13: discount_applied| | Q13: 6 | R13: discount_applied | S13: numeric
B14: 0|7 | C14: 0 | D14: 7 | E14: leaf | N14: -0.026052235 | P14: household_size| | Q14: 7 | R14: household_size | S14: numeric
B15: 0|8 | C15: 0 | D15: 8 | E15: leaf | N15: 0.0063153445 | P15: prior_claims_5y| | Q15: 8 | R15: prior_claims_5y | S15: numeric
B16: 0|9 | C16: 0 | D16: 9 | E16: leaf | N16: -0.030850871 | P16: licence_points| | Q16: 9 | R16: licence_points | S16: numeric
B17: 0|10 | C17: 0 | D17: 10 | E17: leaf | N17: -0.014001446 | P17: years_at_address| | Q17: 10 | R17: years_at_address | S17: numeric
B18: 0|11 | C18: 0 | D18: 11 | E18: leaf | N18: 0.050961323 | P18: customer_since_year| | Q18: 11 | R18: customer_since_year | S18: numeric
B19: 0|12 | C19: 0 | D19: 12 | E19: leaf | N19: 0.072398752 | P19: flood_zone| | Q19: 12 | R19: flood_zone | S19: numeric
B20: 0|13 | C20: 0 | D20: 13 | E20: leaf | N20: 0.027706048 | P20: distance_to_river_km| | Q20: 13 | R20: distance_to_river_km | S20: numeric
B21: 0|14 | C21: 0 | D21: 14 | E21: leaf | N21: 0.00059787929 | P21: elevation_m| | Q21: 14 | R21: elevation_m | S21: numeric
B22: 1|0 | C22: 1 | D22: 0 | E22: split | F22: 25 | G22: x_fz3_rain | H22: 0.71399996 | K22: right | L22: 1 | M22: 2 | P22: year_built| | Q22: 15 | R22: year_built | S22: numeric
B23: 1|1 | C23: 1 | D23: 1 | E23: split | F23: 15 | G23: year_built | H23: 1943.9999 | K23: right | L23: 3 | M23: 4 | P23: bedrooms| | Q23: 16 | R23: bedrooms | S23: numeric
B24: 1|2 | C24: 1 | D24: 2 | E24: split | F24: 13 | G24: distance_to_river_km | H24: 0.49999999 | K24: left | L24: 5 | M24: 6 | P24: hail_days| | Q24: 17 | R24: hail_days | S24: numeric
B25: 1|3 | C25: 1 | D25: 3 | E25: split | F25: 0 | G25: sum_insured | H25: 204999.99 | K25: right | L25: 7 | M25: 8 | P25: wind_exposure_index| | Q25: 18 | R25: wind_exposure_index | S25: numeric
B26: 1|4 | C26: 1 | D26: 4 | E26: split | F26: 0 | G26: sum_insured | H26: 206999.99 | K26: right | L26: 9 | M26: 10 | P26: freezing_days| | Q26: 19 | R26: freezing_days | S26: numeric
B27: 1|5 | C27: 1 | D27: 5 | E27: split | F27: 0 | G27: sum_insured | H27: 231999.99 | K27: right | L27: 11 | M27: 12 | P27: dry_summer_index| | Q27: 20 | R27: dry_summer_index | S27: numeric
B28: 1|6 | C28: 1 | D28: 6 | E28: split | F28: 13 | G28: distance_to_river_km | H28: 0.86999997 | K28: right | L28: 13 | M28: 14 | P28: wildfire_index| | Q28: 21 | R28: wildfire_index | S28: numeric
B29: 1|7 | C29: 1 | D29: 7 | E29: leaf | N29: -0.011357153 | P29: rainfall_mm| | Q29: 22 | R29: rainfall_mm | S29: numeric
B30: 1|8 | C30: 1 | D30: 8 | E30: leaf | N30: 0.010176425 | P30: mean_temperature_c| | Q30: 23 | R30: mean_temperature_c | S30: numeric
B31: 1|9 | C31: 1 | D31: 9 | E31: leaf | N31: -0.032427829 | P31: x_clay_dry| | Q31: 24 | R31: x_clay_dry | S31: numeric | V31: coalesce((soil_type = 'clay') x dry_summer_index, 0) (sql/11, A28)
B32: 1|10 | C32: 1 | D32: 10 | E32: leaf | N32: -0.012212122 | P32: x_fz3_rain| | Q32: 25 | R32: x_fz3_rain | S32: numeric | V32: coalesce((coalesce(flood_zone, 99) >= 3) x rainfall_mm / 1000, 0): a missing flood zone counts as 3 or above (sql/11, A28)
B33: 1|11 | C33: 1 | D33: 11 | E33: leaf | N33: 0.035709471 | P33: construction_type|brick | Q33: 26 | R33: construction_type | S33: categorical | T33: 0 | U33: brick
B34: 1|12 | C34: 1 | D34: 12 | E34: leaf | N34: 0.05500263 | P34: construction_type|non_standard | Q34: 26 | R34: construction_type | S34: categorical | T34: 1 | U34: non_standard
B35: 1|13 | C35: 1 | D35: 13 | E35: leaf | N35: 0.025253523 | P35: construction_type|stone | Q35: 26 | R35: construction_type | S35: categorical | T35: 2 | U35: stone
B36: 1|14 | C36: 1 | D36: 14 | E36: leaf | N36: 0.0046834233 | P36: construction_type|timber | Q36: 26 | R36: construction_type | S36: categorical | T36: 3 | U36: timber
B37: 2|0 | C37: 2 | D37: 0 | E37: split | F37: 12 | G37: flood_zone | H37: 3.9999999 | K37: right | L37: 1 | M37: 2 | P37: construction_type|(any other level) | Q37: 26 | R37: construction_type | S37: categorical | U37: (any other level) | V37: no code: missing, so each split's default branch
B38: 2|1 | C38: 2 | D38: 1 | E38: split | F38: 0 | G38: sum_insured | H38: 208999.99 | K38: right | L38: 3 | M38: 4 | P38: occupancy|let | Q38: 27 | R38: occupancy | S38: categorical | T38: 0 | U38: let
B39: 2|2 | C39: 2 | D39: 2 | E39: split | F39: 14 | G39: elevation_m | H39: 2.1999999 | K39: right | L39: 5 | M39: 6 | P39: occupancy|owner_occupied | Q39: 27 | R39: occupancy | S39: categorical | T39: 1 | U39: owner_occupied
B40: 2|3 | C40: 2 | D40: 3 | E40: category split | F40: 49 | G40: energy_rating | I40: 0;1;2;3 | J40: A;B;C;D | K40: left | L40: 7 | M40: 8 | P40: occupancy|(any other level) | Q40: 27 | R40: occupancy | S40: categorical | U40: (any other level) | V40: no code: missing, so each split's default branch
B41: 2|4 | C41: 2 | D41: 4 | E41: category split | F41: 49 | G41: energy_rating | I41: 0;1;2;3 | J41: A;B;C;D | K41: left | L41: 9 | M41: 10 | P41: smoke_alarms|False | Q41: 28 | R41: smoke_alarms | S41: categorical | T41: 0 | U41: False
B42: 2|5 | C42: 2 | D42: 5 | E42: split | F42: 12 | G42: flood_zone | H42: 4.9999998 | K42: left | L42: 11 | M42: 12 | P42: smoke_alarms|MISSING | Q42: 28 | R42: smoke_alarms | S42: categorical | T42: 1 | U42: MISSING
B43: 2|6 | C43: 2 | D43: 6 | E43: split | F43: 14 | G43: elevation_m | H43: 3.6999999 | K43: right | L43: 13 | M43: 14 | P43: smoke_alarms|True | Q43: 28 | R43: smoke_alarms | S43: categorical | T43: 2 | U43: True
B44: 2|7 | C44: 2 | D44: 7 | E44: leaf | N44: -0.010326927 | P44: smoke_alarms|(any other level) | Q44: 28 | R44: smoke_alarms | S44: categorical | U44: (any other level) | V44: no code: missing, so each split's default branch
B45: 2|8 | C45: 2 | D45: 8 | E45: leaf | N45: -0.027486552 | P45: accidental_damage_cover|False | Q45: 29 | R45: accidental_damage_cover | S45: categorical | T45: 0 | U45: False
B46: 2|9 | C46: 2 | D46: 9 | E46: leaf | N46: 0.010403736 | P46: accidental_damage_cover|True | Q46: 29 | R46: accidental_damage_cover | S46: categorical | T46: 1 | U46: True
B47: 2|10 | C47: 2 | D47: 10 | E47: leaf | N47: -0.0080945315 | P47: accidental_damage_cover|(any other level) | Q47: 29 | R47: accidental_damage_cover | S47: categorical | U47: (any other level) | V47: no code: missing, so each split's default branch
B48: 2|11 | C48: 2 | D48: 11 | E48: leaf | N48: 0.050927419 | P48: mortgage|False | Q48: 30 | R48: mortgage | S48: categorical | T48: 0 | U48: False
B49: 2|12 | C49: 2 | D49: 12 | E49: leaf | N49: 0.068984106 | P49: mortgage|True | Q49: 30 | R49: mortgage | S49: categorical | T49: 1 | U49: True
B50: 2|13 | C50: 2 | D50: 13 | E50: leaf | N50: 0.023319088 | P50: mortgage|(any other level) | Q50: 30 | R50: mortgage | S50: categorical | U50: (any other level) | V50: no code: missing, so each split's default branch
B51: 2|14 | C51: 2 | D51: 14 | E51: leaf | N51: -0.006676794 | P51: channel|broker | Q51: 31 | R51: channel | S51: categorical | T51: 0 | U51: broker
B52: 3|0 | C52: 3 | D52: 0 | E52: split | F52: 12 | G52: flood_zone | H52: 3.9999999 | K52: right | L52: 1 | M52: 2 | P52: channel|comparison_site | Q52: 31 | R52: channel | S52: categorical | T52: 1 | U52: comparison_site
B53: 3|1 | C53: 3 | D53: 1 | E53: split | F53: 15 | G53: year_built | H53: 1944.9999 | K53: right | L53: 3 | M53: 4 | P53: channel|direct | Q53: 31 | R53: channel | S53: categorical | T53: 2 | U53: direct
B54: 3|2 | C54: 3 | D54: 2 | E54: split | F54: 13 | G54: distance_to_river_km | H54: 0.84999999 | K54: left | L54: 5 | M54: 6 | P54: channel|(any other level) | Q54: 31 | R54: channel | S54: categorical | U54: (any other level) | V54: no code: missing, so each split's default branch
B55: 3|3 | C55: 3 | D55: 3 | E55: split | F55: 0 | G55: sum_insured | H55: 185999.99 | K55: right | L55: 7 | M55: 8 | P55: payment_method|annual | Q55: 32 | R55: payment_method | S55: categorical | T55: 0 | U55: annual
B56: 3|4 | C56: 3 | D56: 4 | E56: split | F56: 0 | G56: sum_insured | H56: 201999.99 | K56: right | L56: 9 | M56: 10 | P56: payment_method|monthly | Q56: 32 | R56: payment_method | S56: categorical | T56: 1 | U56: monthly
B57: 3|5 | C57: 3 | D57: 5 | E57: split | F57: 12 | G57: flood_zone | H57: 4.9999998 | K57: left | L57: 11 | M57: 12 | P57: payment_method|(any other level) | Q57: 32 | R57: payment_method | S57: categorical | U57: (any other level) | V57: no code: missing, so each split's default branch
B58: 3|6 | C58: 3 | D58: 6 | E58: leaf | N58: 0.0034727405 | P58: new_business|False | Q58: 33 | R58: new_business | S58: categorical | T58: 0 | U58: False
B59: 3|7 | C59: 3 | D59: 7 | E59: leaf | N59: -0.01280721 | P59: new_business|True | Q59: 33 | R59: new_business | S59: categorical | T59: 1 | U59: True
B60: 3|8 | C60: 3 | D60: 8 | E60: leaf | N60: 0.009201861 | P60: new_business|(any other level) | Q60: 33 | R60: new_business | S60: categorical | U60: (any other level) | V60: no code: missing, so each split's default branch
B61: 3|9 | C61: 3 | D61: 9 | E61: leaf | N61: -0.030082539 | P61: marital_status|MISSING | Q61: 34 | R61: marital_status | S61: categorical | T61: 0 | U61: MISSING
B62: 3|10 | C62: 3 | D62: 10 | E62: leaf | N62: -0.0099955518 | P62: marital_status|divorced | Q62: 34 | R62: marital_status | S62: categorical | T62: 1 | U62: divorced
B63: 3|11 | C63: 3 | D63: 11 | E63: leaf | N63: 0.04178866 | P63: marital_status|married | Q63: 34 | R63: marital_status | S63: categorical | T63: 2 | U63: married
B64: 3|12 | C64: 3 | D64: 12 | E64: leaf | N64: 0.066214792 | P64: marital_status|single | Q64: 34 | R64: marital_status | S64: categorical | T64: 3 | U64: single
B65: 4|0 | C65: 4 | D65: 0 | E65: split | F65: 14 | G65: elevation_m | H65: 2.0999998 | K65: right | L65: 1 | M65: 2 | P65: marital_status|widowed | Q65: 34 | R65: marital_status | S65: categorical | T65: 4 | U65: widowed
B66: 4|1 | C66: 4 | D66: 1 | E66: split | F66: 25 | G66: x_fz3_rain | H66: 0.65599999 | K66: right | L66: 3 | M66: 4 | P66: marital_status|(any other level) | Q66: 34 | R66: marital_status | S66: categorical | U66: (any other level) | V66: no code: missing, so each split's default branch
B67: 4|2 | C67: 4 | D67: 2 | E67: split | F67: 15 | G67: year_built | H67: 1944.9999 | K67: right | L67: 5 | M67: 6 | P67: email_domain|inboxly | Q67: 35 | R67: email_domain | S67: categorical | T67: 0 | U67: inboxly
B68: 4|3 | C68: 4 | D68: 3 | E68: split | F68: 15 | G68: year_built | H68: 1942.9999 | K68: right | L68: 7 | M68: 8 | P68: email_domain|mailone | Q68: 35 | R68: email_domain | S68: categorical | T68: 1 | U68: mailone
B69: 4|4 | C69: 4 | D69: 4 | E69: split | F69: 14 | G69: elevation_m | H69: 1.4899999 | K69: right | L69: 9 | M69: 10 | P69: email_domain|netbox | Q69: 35 | R69: email_domain | S69: categorical | T69: 2 | U69: netbox
B70: 4|5 | C70: 4 | D70: 5 | E70: split | F70: 16 | G70: bedrooms | H70: 2.9999999 | K70: right | L70: 11 | M70: 12 | P70: email_domain|other | Q70: 35 | R70: email_domain | S70: categorical | T70: 3 | U70: other
B71: 4|6 | C71: 4 | D71: 6 | E71: split | F71: 16 | G71: bedrooms | H71: 2.9999999 | K71: right | L71: 13 | M71: 14 | P71: email_domain|posthub | Q71: 35 | R71: email_domain | S71: categorical | T71: 4 | U71: posthub
B72: 4|7 | C72: 4 | D72: 7 | E72: leaf | N72: 0.016655132 | P72: email_domain|(any other level) | Q72: 35 | R72: email_domain | S72: categorical | U72: (any other level) | V72: no code: missing, so each split's default branch
B73: 4|8 | C73: 4 | D73: 8 | E73: leaf | N73: -0.0016096212 | P73: marketing_consent|False | Q73: 36 | R73: marketing_consent | S73: categorical | T73: 0 | U73: False
B74: 4|9 | C74: 4 | D74: 9 | E74: leaf | N74: 0.051623464 | P74: marketing_consent|True | Q74: 36 | R74: marketing_consent | S74: categorical | T74: 1 | U74: True
B75: 4|10 | C75: 4 | D75: 10 | E75: leaf | N75: 0.034432776 | P75: marketing_consent|(any other level) | Q75: 36 | R75: marketing_consent | S75: categorical | U75: (any other level) | V75: no code: missing, so each split's default branch
B76: 4|11 | C76: 4 | D76: 11 | E76: leaf | N76: -0.0081409216 | P76: document_preference|app | Q76: 37 | R76: document_preference | S76: categorical | T76: 0 | U76: app
B77: 4|12 | C77: 4 | D77: 12 | E77: leaf | N77: 0.0068536038 | P77: document_preference|email | Q77: 37 | R77: document_preference | S77: categorical | T77: 1 | U77: email
B78: 4|13 | C78: 4 | D78: 13 | E78: leaf | N78: -0.03035002 | P78: document_preference|post | Q78: 37 | R78: document_preference | S78: categorical | T78: 2 | U78: post
B79: 4|14 | C79: 4 | D79: 14 | E79: leaf | N79: -0.012324039 | P79: document_preference|(any other level) | Q79: 37 | R79: document_preference | S79: categorical | U79: (any other level) | V79: no code: missing, so each split's default branch
B80: 5|0 | C80: 5 | D80: 0 | E80: split | F80: 12 | G80: flood_zone | H80: 3.9999999 | K80: right | L80: 1 | M80: 2 | P80: previous_insurer|INS00 | Q80: 38 | R80: previous_insurer | S80: categorical | T80: 0 | U80: INS00
B81: 5|1 | C81: 5 | D81: 1 | E81: split | F81: 0 | G81: sum_insured | H81: 205999.99 | K81: right | L81: 3 | M81: 4 | P81: previous_insurer|INS01 | Q81: 38 | R81: previous_insurer | S81: categorical | T81: 1 | U81: INS01
B82: 5|2 | C82: 5 | D82: 2 | E82: split | F82: 14 | G82: elevation_m | H82: 2.0999998 | K82: right | L82: 5 | M82: 6 | P82: previous_insurer|INS02 | Q82: 38 | R82: previous_insurer | S82: categorical | T82: 2 | U82: INS02
B83: 5|3 | C83: 5 | D83: 3 | E83: split | F83: 24 | G83: x_clay_dry | H83: 0.69599995 | K83: right | L83: 7 | M83: 8 | P83: previous_insurer|INS03 | Q83: 38 | R83: previous_insurer | S83: categorical | T83: 3 | U83: INS03
B84: 5|4 | C84: 5 | D84: 4 | E84: split | F84: 24 | G84: x_clay_dry | H84: 0.73099998 | K84: right | L84: 9 | M84: 10 | P84: previous_insurer|INS04 | Q84: 38 | R84: previous_insurer | S84: categorical | T84: 4 | U84: INS04
B85: 5|5 | C85: 5 | D85: 5 | E85: split | F85: 12 | G85: flood_zone | H85: 4.9999998 | K85: left | L85: 11 | M85: 12 | P85: previous_insurer|INS05 | Q85: 38 | R85: previous_insurer | S85: categorical | T85: 5 | U85: INS05
B86: 5|6 | C86: 5 | D86: 6 | E86: split | F86: 12 | G86: flood_zone | H86: 10.000009 | K86: right | L86: 13 | M86: 14 | P86: previous_insurer|INS06 | Q86: 38 | R86: previous_insurer | S86: categorical | T86: 6 | U86: INS06
B87: 5|7 | C87: 5 | D87: 7 | E87: leaf | N87: -0.023413286 | P87: previous_insurer|INS07 | Q87: 38 | R87: previous_insurer | S87: categorical | T87: 7 | U87: INS07
B88: 5|8 | C88: 5 | D88: 8 | E88: leaf | N88: 0.0010996496 | P88: previous_insurer|INS08 | Q88: 38 | R88: previous_insurer | S88: categorical | T88: 8 | U88: INS08
B89: 5|9 | C89: 5 | D89: 9 | E89: leaf | N89: -0.0036953099 | P89: previous_insurer|INS09 | Q89: 38 | R89: previous_insurer | S89: categorical | T89: 9 | U89: INS09
B90: 5|10 | C90: 5 | D90: 10 | E90: leaf | N90: 0.0156518 | P90: previous_insurer|INS10 | Q90: 38 | R90: previous_insurer | S90: categorical | T90: 10 | U90: INS10
B91: 5|11 | C91: 5 | D91: 11 | E91: leaf | N91: 0.046790555 | P91: previous_insurer|INS11 | Q91: 38 | R91: previous_insurer | S91: categorical | T91: 11 | U91: INS11
B92: 5|12 | C92: 5 | D92: 12 | E92: leaf | N92: 0.065233581 | P92: previous_insurer|INS12 | Q92: 38 | R92: previous_insurer | S92: categorical | T92: 12 | U92: INS12
B93: 5|13 | C93: 5 | D93: 13 | E93: leaf | N93: 0.02095121 | P93: previous_insurer|INS13 | Q93: 38 | R93: previous_insurer | S93: categorical | T93: 13 | U93: INS13
B94: 5|14 | C94: 5 | D94: 14 | E94: leaf | N94: -0.0024810268 | P94: previous_insurer|INS14 | Q94: 38 | R94: previous_insurer | S94: categorical | T94: 14 | U94: INS14
B95: 6|0 | C95: 6 | D95: 0 | E95: split | F95: 12 | G95: flood_zone | H95: 3.9999999 | K95: right | L95: 1 | M95: 2 | P95: previous_insurer|INS15 | Q95: 38 | R95: previous_insurer | S95: categorical | T95: 15 | U95: INS15
B96: 6|1 | C96: 6 | D96: 1 | E96: split | F96: 15 | G96: year_built | H96: 1944.9999 | K96: right | L96: 3 | M96: 4 | P96: previous_insurer|INS16 | Q96: 38 | R96: previous_insurer | S96: categorical | T96: 16 | U96: INS16
B97: 6|2 | C97: 6 | D97: 2 | E97: split | F97: 14 | G97: elevation_m | H97: 2.1999999 | K97: right | L97: 5 | M97: 6 | P97: previous_insurer|INS17 | Q97: 38 | R97: previous_insurer | S97: categorical | T97: 17 | U97: INS17
B98: 6|3 | C98: 6 | D98: 3 | E98: split | F98: 8 | G98: prior_claims_5y | H98: 0.99999997 | K98: right | L98: 7 | M98: 8 | P98: previous_insurer|INS18 | Q98: 38 | R98: previous_insurer | S98: categorical | T98: 18 | U98: INS18
B99: 6|4 | C99: 6 | D99: 4 | E99: split | F99: 14 | G99: elevation_m | H99: 3.1999999 | K99: right | L99: 9 | M99: 10 | P99: previous_insurer|INS19 | Q99: 38 | R99: previous_insurer | S99: categorical | T99: 19 | U99: INS19
B100: 6|5 | C100: 6 | D100: 5 | E100: split | F100: 12 | G100: flood_zone | H100: 4.9999998 | K100: left | L100: 11 | M100: 12 | P100: previous_insurer|INS20 | Q100: 38 | R100: previous_insurer | S100: categorical | T100: 20 | U100: INS20
B101: 6|6 | C101: 6 | D101: 6 | E101: split | F101: 14 | G101: elevation_m | H101: 3.6999999 | K101: right | L101: 13 | M101: 14 | P101: previous_insurer|INS21 | Q101: 38 | R101: previous_insurer | S101: categorical | T101: 21 | U101: INS21
B102: 6|7 | C102: 6 | D102: 7 | E102: leaf | N102: -0.0010047824 | P102: previous_insurer|INS22 | Q102: 38 | R102: previous_insurer | S102: categorical | T102: 22 | U102: INS22
...

Sheet Rating Motor
B2: Rating Motor: small-claim GLM + large-claim GLM, then the level steps
B3: Each term: the key it looks up (line|component|term|level) and its log contribution. Row 8 holds the term's key prefix. Prediction = EXP(sum of logs) per component.
BR4: Rows off Python (0 = pass) | BS4: Keys not found (0 = pass)
B5: Checks sit above their own columns at the right. | BR5: =COUNTIF(BR10:BR16,">1E-9") | BS5: =SUM(BS10:BS16)
B7: Policy | G7: Inputs | U7: Small claims GLM | BB7: Large claims GLM | BN7: Prediction | BQ7: Check against Python
U8: motor|small|marketing_segment | W8: motor|small|cover_type | Y8: motor|small|urban_density | AA8: motor|small|channel | AC8: motor|small|vehicle_use | AE8: motor|small|payment_method | AG8: motor|small|driver_age_band | AI8: motor|small|prior_claims_5y | AK8: motor|small|missed_payments_12m | AM8: motor|small|ncb_years | AO8: motor|small|years_licensed | AQ8: motor|small|vehicle_age | AS8: motor|small|vehicle_value_group | AU8: motor|small|voluntary_excess | AW8: motor|small|(intercept)| | AX8: motor|small|trend|log contribution in 2025 | BB8: motor|large|driver_age_band | BD8: motor|large|ncb_years | BF8: motor|large|years_licensed | BH8: motor|large|(intercept)| | BI8: motor|large|trend|log contribution in 2025 | BK8: motor|large|Pareto adjustment|
B9: Policy row | C9: New business | D9: Period start | E9: Period end | F9: Exposure (model, D-01) | G9: marketing_segment | H9: cover_type | I9: urban_density | J9: channel | K9: vehicle_use | L9: payment_method | M9: driver_age_band | N9: prior_claims_5y | O9: missed_payments_12m | P9: ncb_years | Q9: years_licensed | R9: vehicle_age | S9: vehicle_value_group | T9: voluntary_excess | U9: marketing_segment: key | V9: marketing_segment: log | W9: cover_type: key | X9: cover_type: log | Y9: urban_density: key | Z9: urban_density: log | AA9: channel: key | AB9: channel: log | AC9: vehicle_use: key | AD9: vehicle_use: log | AE9: payment_method: key | AF9: payment_method: log | AG9: driver_age_band: key | AH9: driver_age_band: log | AI9: prior_claims_5y: band | AJ9: prior_claims_5y: log | AK9: missed_payments_12m: band | AL9: missed_payments_12m: log | AM9: ncb_years: key | AN9: ncb_years: log | AO9: years_licensed: key | AP9: years_licensed: log | AQ9: vehicle_age: key | AR9: vehicle_age: log | AS9: vehicle_value_group: key | AT9: vehicle_value_group: log | AU9: voluntary_excess: key | AV9: voluntary_excess: log | AW9: Intercept | AX9: Trend to 2025 | AY9: ln(exposure) | AZ9: Log prediction | BA9: Small claim (CU) | BB9: driver_age_band: key | BC9: driver_age_band: log | BD9: ncb_years: band | BE9: ncb_years: log | BF9: years_licensed: band | BG9: years_licensed: log | BH9: Intercept | BI9: Trend to 2025 | BJ9: ln(exposure) | BK9: ln(Pareto adj.) | BL9: Log prediction | BM9: Large claim (CU) | BN9: As is (CU) | BO9: Level step 1 | BP9: Final risk premium (CU) | BQ9: Python final | BR9: Relative difference | BS9: Keys not found
B10: ='Int. Inputs'!$B$16 | C10: =IF(ISBLANK(INDEX(Pol_Data,MATCH($B10,Pol_ID,0),MATCH("new_business",Pol_Head,0))),"",INDEX(Pol_Data,MATCH($B10,Pol_ID,0),MATCH("new_business",Pol_Head,0))) | D10: =IF(ISBLANK(INDEX(Pol_Data,MATCH($B10,Pol_ID,0),MATCH("period_start",Pol_Head,0))),"",INDEX(Pol_Data,MATCH($B10,Pol_ID,0),MATCH("period_start",Pol_Head,0))) | E10: =IF(ISBLANK(INDEX(Pol_Data,MATCH($B10,Pol_ID,0),MATCH("period_end",Pol_Head,0))),"",INDEX(Pol_Data,MATCH($B10,Pol_ID,0),MATCH("period_end",Pol_Head,0))) | F10: =(E10-D10+1)/365 | G10: =IF(ISBLANK(INDEX(Pol_Data,MATCH($B10,Pol_ID,0),MATCH("marketing_segment",Pol_Head,0))),"",INDEX(Pol_Data,MATCH($B10,Pol_ID,0),MATCH("marketing_segment",Pol_Head,0))) | H10: =IF(ISBLANK(INDEX(Pol_Data,MATCH($B10,Pol_ID,0),MATCH("cover_type",Pol_Head,0))),"",INDEX(Pol_Data,MATCH($B10,Pol_ID,0),MATCH("cover_type",Pol_Head,0))) | I10: =IF(ISBLANK(INDEX(Pol_Data,MATCH($B10,Pol_ID,0),MATCH("urban_density",Pol_Head,0))),"",INDEX(Pol_Data,MATCH($B10,Pol_ID,0),MATCH("urban_density",Pol_Head,0))) | J10: =IF(ISBLANK(INDEX(Pol_Data,MATCH($B10,Pol_ID,0),MATCH("channel",Pol_Head,0))),"",INDEX(Pol_Data,MATCH($B10,Pol_ID,0),MATCH("channel",Pol_Head,0))) | K10: =IF(ISBLANK(INDEX(Pol_Data,MATCH($B10,Pol_ID,0),MATCH("vehicle_use",Pol_Head,0))),"",INDEX(Pol_Data,MATCH($B10,Pol_ID,0),MATCH("vehicle_use",Pol_Head,0))) | L10: =IF(ISBLANK(INDEX(Pol_Data,MATCH($B10,Pol_ID,0),MATCH("payment_method",Pol_Head,0))),"",INDEX(Pol_Data,MATCH($B10,Pol_ID,0),MATCH("payment_method",Pol_Head,0))) | M10: =IF(ISBLANK(INDEX(Pol_Data,MATCH($B10,Pol_ID,0),MATCH("driver_age_band",Pol_Head,0))),"",INDEX(Pol_Data,MATCH($B10,Pol_ID,0),MATCH("driver_age_band",Pol_Head,0))) | N10: =IF(ISBLANK(INDEX(Pol_Data,MATCH($B10,Pol_ID,0),MATCH("prior_claims_5y",Pol_Head,0))),"",INDEX(Pol_Data,MATCH($B10,Pol_ID,0),MATCH("prior_claims_5y",Pol_Head,0))) | O10: =IF(ISBLANK(INDEX(Pol_Data,MATCH($B10,Pol_ID,0),MATCH("missed_payments_12m",Pol_Head,0))),"",INDEX(Pol_Data,MATCH($B10,Pol_ID,0),MATCH("missed_payments_12m",Pol_Head,0))) | P10: =IF(ISBLANK(INDEX(Pol_Data,MATCH($B10,Pol_ID,0),MATCH("ncb_years",Pol_Head,0))),"",INDEX(Pol_Data,MATCH($B10,Pol_ID,0),MATCH("ncb_years",Pol_Head,0))) | Q10: =IF(ISBLANK(INDEX(Pol_Data,MATCH($B10,Pol_ID,0),MATCH("years_licensed",Pol_Head,0))),"",INDEX(Pol_Data,MATCH($B10,Pol_ID,0),MATCH("years_licensed",Pol_Head,0))) | R10: =IF(ISBLANK(INDEX(Pol_Data,MATCH($B10,Pol_ID,0),MATCH("vehicle_age",Pol_Head,0))),"",INDEX(Pol_Data,MATCH($B10,Pol_ID,0),MATCH("vehicle_age",Pol_Head,0))) | S10: =IF(ISBLANK(INDEX(Pol_Data,MATCH($B10,Pol_ID,0),MATCH("vehicle_value_group",Pol_Head,0))),"",INDEX(Pol_Data,MATCH($B10,Pol_ID,0),MATCH("vehicle_value_group",Pol_Head,0))) | T10: =IF(ISBLANK(INDEX(Pol_Data,MATCH($B10,Pol_ID,0),MATCH("voluntary_excess",Pol_Head,0))),"",INDEX(Pol_Data,MATCH($B10,Pol_ID,0),MATCH("voluntary_excess",Pol_Head,0))) | U10: =IFERROR(INDEX(Remap_To,MATCH(U$8&"|"&IF(G10="","MISSING",G10&""),Remap_Key,0)),U$8&"|"&IF(G10="","MISSING",G10&"")) | V10: =IFERROR(INDEX(Terms_Contrib,MATCH(U10,Terms_Key,0)),0) | W10: =IFERROR(INDEX(Remap_To,MATCH(W$8&"|"&IF(H10="","MISSING",H10&""),Remap_Key,0)),W$8&"|"&IF(H10="","MISSING",H10&"")) | X10: =IFERROR(INDEX(Terms_Contrib,MATCH(W10,Terms_Key,0)),0) | Y10: =IFERROR(INDEX(Remap_To,MATCH(Y$8&"|"&IF(I10="","MISSING",I10&""),Remap_Key,0)),Y$8&"|"&IF(I10="","MISSING",I10&"")) | Z10: =IFERROR(INDEX(Terms_Contrib,MATCH(Y10,Terms_Key,0)),0) | AA10: =IFERROR(INDEX(Remap_To,MATCH(AA$8&"|"&IF(J10="","MISSING",J10&""),Remap_Key,0)),AA$8&"|"&IF(J10="","MISSING",J10&"")) | AB10: =IFERROR(INDEX(Terms_Contrib,MATCH(AA10,Terms_Key,0)),0) | AC10: =IFERROR(INDEX(Remap_To,MATCH(AC$8&"|"&IF(K10="","MISSING",K10&""),Remap_Key,0)),AC$8&"|"&IF(K10="","MISSING",K10&"")) | AD10: =IFERROR(INDEX(Terms_Contrib,MATCH(AC10,Terms_Key,0)),0) | AE10: =IFERROR(INDEX(Remap_To,MATCH(AE$8&"|"&IF(L10="","MISSING",L10&""),Remap_Key,0)),AE$8&"|"&IF(L10="","MISSING",L10&"")) | AF10: =IFERROR(INDEX(Terms_Contrib,MATCH(AE10,Terms_Key,0)),0) | AG10: =IFERROR(INDEX(Remap_To,MATCH(AG$8&"|"&IF(M10="","MISSING",M10&""),Remap_Key,0)),AG$8&"|"&IF(M10="","MISSING",M10&"")) | AH10: =IFERROR(INDEX(Terms_Contrib,MATCH(AG10,Terms_Key,0)),0) | AI10: =IF(N10="",AI$8&"|MISSING",AI$8&"|q"&TEXT(COUNTIFS(Terms_LCT,AI$8,Terms_Kind,"band",Terms_Lower,"<"&N10)-1,"00")) | AJ10: =IFERROR(INDEX(Terms_Contrib,MATCH(AI10,Terms_Key,0)),0) | AK10: =IF(O10="",AK$8&"|MISSING",AK$8&"|q"&TEXT(COUNTIFS(Terms_LCT,AK$8,Terms_Kind,"band",Terms_Lower,"<"&O10)-1,"00")) | AL10: =IFERROR(INDEX(Terms_Contrib,MATCH(AK10,Terms_Key,0)),0) | AM10: =IF(P10="",AM$8&"|MISSING",AM$8&"|"&TEXT(P10,INDEX(Fmt_Str,MATCH(AM$8,Fmt_LCT,0)))) | AN10: =IFERROR(INDEX(Terms_Contrib,MATCH(AM10,Terms_Key,0)),0) | AO10: =IF(Q10="",AO$8&"|MISSING",AO$8&"|"&TEXT(Q10,INDEX(Fmt_Str,MATCH(AO$8,Fmt_LCT,0)))) | AP10: =IFERROR(INDEX(Terms_Contrib,MATCH(AO10,Terms_Key,0)),0) | AQ10: =IF(R10="",AQ$8&"|MISSING",AQ$8&"|"&TEXT(R10,INDEX(Fmt_Str,MATCH(AQ$8,Fmt_LCT,0)))) | AR10: =IFERROR(INDEX(Terms_Contrib,MATCH(AQ10,Terms_Key,0)),0) | AS10: =IF(S10="",AS$8&"|MISSING",AS$8&"|"&TEXT(S10,INDEX(Fmt_Str,MATCH(AS$8,Fmt_LCT,0)))) | AT10: =IFERROR(INDEX(Terms_Contrib,MATCH(AS10,Terms_Key,0)),0) | AU10: =IF(T10="",AU$8&"|MISSING",AU$8&"|"&TEXT(T10,INDEX(Fmt_Str,MATCH(AU$8,Fmt_LCT,0)))) | AV10: =IFERROR(INDEX(Terms_Contrib,MATCH(AU10,Terms_Key,0)),0) | AW10: =INDEX(Terms_Contrib,MATCH(AW$8,Terms_Key,0)) | AX10: =INDEX(Terms_Contrib,MATCH(AX$8,Terms_Key,0)) | AY10: =LN(F10) | AZ10: =V10+X10+Z10+AB10+AD10+AF10+AH10+AJ10+AL10+AN10+AP10+AR10+AT10+AV10+AW10+AX10+AY10 | BA10: =EXP(AZ10) | BB10: =IFERROR(INDEX(Remap_To,MATCH(BB$8&"|"&IF(M10="","MISSING",M10&""),Remap_Key,0)),BB$8&"|"&IF(M10="","MISSING",M10&"")) | BC10: =IFERROR(INDEX(Terms_Contrib,MATCH(BB10,Terms_Key,0)),0) | BD10: =IF(P10="",BD$8&"|MISSING",BD$8&"|q"&TEXT(COUNTIFS(Terms_LCT,BD$8,Terms_Kind,"band",Terms_Lower,"<"&P10)-1,"00")) | BE10: =IFERROR(INDEX(Terms_Contrib,MATCH(BD10,Terms_Key,0)),0) | BF10: =IF(Q10="",BF$8&"|MISSING",BF$8&"|q"&TEXT(COUNTIFS(Terms_LCT,BF$8,Terms_Kind,"band",Terms_Lower,"<"&Q10)-1,"00")) | BG10: =IFERROR(INDEX(Terms_Contrib,MATCH(BF10,Terms_Key,0)),0) | BH10: =INDEX(Terms_Contrib,MATCH(BH$8,Terms_Key,0)) | BI10: =INDEX(Terms_Contrib,MATCH(BI$8,Terms_Key,0)) | BJ10: =LN(F10) | BK10: =INDEX(Terms_Contrib,MATCH(BK$8,Terms_Key,0)) | BL10: =BC10+BE10+BG10+BH10+BI10+BJ10+BK10 | BM10: =EXP(BL10) | BN10: =BA10+BM10 | BO10: =IF(C10="true",Lvl_MotNB,Lvl_MotRen) | BP10: =IF(C10="true",BN10*BO10*Lvl_MotNB2/BO10,BN10*BO10) | BQ10: =INDEX(Py_Final,MATCH($B10,Py_ID,0)) | BR10: =ABS(BP10/BQ10-1) | BS10: =ISNA(MATCH(U10,Terms_Key,0))+ISNA(MATCH(W10,Terms_Key,0))+ISNA(MATCH(Y10,Terms_Key,0))+ISNA(MATCH(AA10,Terms_Key,0))+ISNA(MATCH(AC10,Terms_Key,0))+ISNA(MATCH(AE10,Terms_Key,0))+ISNA(MATCH(AG10,Terms_Key,0))+ISNA(MATCH(AI10,Terms_Key,0))+ISNA(MATCH(AK10,Terms_Key,0))+ISNA(MATCH(AM10,Terms_Key,0))+ISNA(MATCH(AO10,Terms_Key,0))+ISNA(MATCH(AQ10,Terms_Key,0))+ISNA(MATCH(AS10,Terms_Key,0))+ISNA(MATCH(AU10,Terms_Key,0))+ISNA(MATCH(AW$8,Terms_Key,0))+ISNA(MATCH(AX$8,Terms_Key,0))+ISNA(MATCH(BB10,Terms_Key,0))+ISNA(MATCH(BD10,Terms_Key,0))+ISNA(MATCH(BF10,Terms_Key,0))+ISNA(MATCH(BH$8,Terms_Key,0))+ISNA(MATCH(BI$8,Terms_Key,0))+ISNA(MATCH(BK$8,Terms_Key,0))
B11: ='Int. Inputs'!$B$17 | C11: =IF(ISBLANK(INDEX(Pol_Data,MATCH($B11,Pol_ID,0),MATCH("new_business",Pol_Head,0))),"",INDEX(Pol_Data,MATCH($B11,Pol_ID,0),MATCH("new_business",Pol_Head,0))) | D11: =IF(ISBLANK(INDEX(Pol_Data,MATCH($B11,Pol_ID,0),MATCH("period_start",Pol_Head,0))),"",INDEX(Pol_Data,MATCH($B11,Pol_ID,0),MATCH("period_start",Pol_Head,0))) | E11: =IF(ISBLANK(INDEX(Pol_Data,MATCH($B11,Pol_ID,0),MATCH("period_end",Pol_Head,0))),"",INDEX(Pol_Data,MATCH($B11,Pol_ID,0),MATCH("period_end",Pol_Head,0))) | F11: =(E11-D11+1)/365 | G11: =IF(ISBLANK(INDEX(Pol_Data,MATCH($B11,Pol_ID,0),MATCH("marketing_segment",Pol_Head,0))),"",INDEX(Pol_Data,MATCH($B11,Pol_ID,0),MATCH("marketing_segment",Pol_Head,0))) | H11: =IF(ISBLANK(INDEX(Pol_Data,MATCH($B11,Pol_ID,0),MATCH("cover_type",Pol_Head,0))),"",INDEX(Pol_Data,MATCH($B11,Pol_ID,0),MATCH("cover_type",Pol_Head,0))) | I11: =IF(ISBLANK(INDEX(Pol_Data,MATCH($B11,Pol_ID,0),MATCH("urban_density",Pol_Head,0))),"",INDEX(Pol_Data,MATCH($B11,Pol_ID,0),MATCH("urban_density",Pol_Head,0))) | J11: =IF(ISBLANK(INDEX(Pol_Data,MATCH($B11,Pol_ID,0),MATCH("channel",Pol_Head,0))),"",INDEX(Pol_Data,MATCH($B11,Pol_ID,0),MATCH("channel",Pol_Head,0))) | K11: =IF(ISBLANK(INDEX(Pol_Data,MATCH($B11,Pol_ID,0),MATCH("vehicle_use",Pol_Head,0))),"",INDEX(Pol_Data,MATCH($B11,Pol_ID,0),MATCH("vehicle_use",Pol_Head,0))) | L11: =IF(ISBLANK(INDEX(Pol_Data,MATCH($B11,Pol_ID,0),MATCH("payment_method",Pol_Head,0))),"",INDEX(Pol_Data,MATCH($B11,Pol_ID,0),MATCH("payment_method",Pol_Head,0))) | M11: =IF(ISBLANK(INDEX(Pol_Data,MATCH($B11,Pol_ID,0),MATCH("driver_age_band",Pol_Head,0))),"",INDEX(Pol_Data,MATCH($B11,Pol_ID,0),MATCH("driver_age_band",Pol_Head,0))) | N11: =IF(ISBLANK(INDEX(Pol_Data,MATCH($B11,Pol_ID,0),MATCH("prior_claims_5y",Pol_Head,0))),"",INDEX(Pol_Data,MATCH($B11,Pol_ID,0),MATCH("prior_claims_5y",Pol_Head,0))) | O11: =IF(ISBLANK(INDEX(Pol_Data,MATCH($B11,Pol_ID,0),MATCH("missed_payments_12m",Pol_Head,0))),"",INDEX(Pol_Data,MATCH($B11,Pol_ID,0),MATCH("missed_payments_12m",Pol_Head,0))) | P11: =IF(ISBLANK(INDEX(Pol_Data,MATCH($B11,Pol_ID,0),MATCH("ncb_years",Pol_Head,0))),"",INDEX(Pol_Data,MATCH($B11,Pol_ID,0),MATCH("ncb_years",Pol_Head,0))) | Q11: =IF(ISBLANK(INDEX(Pol_Data,MATCH($B11,Pol_ID,0),MATCH("years_licensed",Pol_Head,0))),"",INDEX(Pol_Data,MATCH($B11,Pol_ID,0),MATCH("years_licensed",Pol_Head,0))) | R11: =IF(ISBLANK(INDEX(Pol_Data,MATCH($B11,Pol_ID,0),MATCH("vehicle_age",Pol_Head,0))),"",INDEX(Pol_Data,MATCH($B11,Pol_ID,0),MATCH("vehicle_age",Pol_Head,0))) | S11: =IF(ISBLANK(INDEX(Pol_Data,MATCH($B11,Pol_ID,0),MATCH("vehicle_value_group",Pol_Head,0))),"",INDEX(Pol_Data,MATCH($B11,Pol_ID,0),MATCH("vehicle_value_group",Pol_Head,0))) | T11: =IF(ISBLANK(INDEX(Pol_Data,MATCH($B11,Pol_ID,0),MATCH("voluntary_excess",Pol_Head,0))),"",INDEX(Pol_Data,MATCH($B11,Pol_ID,0),MATCH("voluntary_excess",Pol_Head,0))) | U11: =IFERROR(INDEX(Remap_To,MATCH(U$8&"|"&IF(G11="","MISSING",G11&""),Remap_Key,0)),U$8&"|"&IF(G11="","MISSING",G11&"")) | V11: =IFERROR(INDEX(Terms_Contrib,MATCH(U11,Terms_Key,0)),0) | W11: =IFERROR(INDEX(Remap_To,MATCH(W$8&"|"&IF(H11="","MISSING",H11&""),Remap_Key,0)),W$8&"|"&IF(H11="","MISSING",H11&"")) | X11: =IFERROR(INDEX(Terms_Contrib,MATCH(W11,Terms_Key,0)),0) | Y11: =IFERROR(INDEX(Remap_To,MATCH(Y$8&"|"&IF(I11="","MISSING",I11&""),Remap_Key,0)),Y$8&"|"&IF(I11="","MISSING",I11&"")) | Z11: =IFERROR(INDEX(Terms_Contrib,MATCH(Y11,Terms_Key,0)),0) | AA11: =IFERROR(INDEX(Remap_To,MATCH(AA$8&"|"&IF(J11="","MISSING",J11&""),Remap_Key,0)),AA$8&"|"&IF(J11="","MISSING",J11&"")) | AB11: =IFERROR(INDEX(Terms_Contrib,MATCH(AA11,Terms_Key,0)),0) | AC11: =IFERROR(INDEX(Remap_To,MATCH(AC$8&"|"&IF(K11="","MISSING",K11&""),Remap_Key,0)),AC$8&"|"&IF(K11="","MISSING",K11&"")) | AD11: =IFERROR(INDEX(Terms_Contrib,MATCH(AC11,Terms_Key,0)),0) | AE11: =IFERROR(INDEX(Remap_To,MATCH(AE$8&"|"&IF(L11="","MISSING",L11&""),Remap_Key,0)),AE$8&"|"&IF(L11="","MISSING",L11&"")) | AF11: =IFERROR(INDEX(Terms_Contrib,MATCH(AE11,Terms_Key,0)),0) | AG11: =IFERROR(INDEX(Remap_To,MATCH(AG$8&"|"&IF(M11="","MISSING",M11&""),Remap_Key,0)),AG$8&"|"&IF(M11="","MISSING",M11&"")) | AH11: =IFERROR(INDEX(Terms_Contrib,MATCH(AG11,Terms_Key,0)),0) | AI11: =IF(N11="",AI$8&"|MISSING",AI$8&"|q"&TEXT(COUNTIFS(Terms_LCT,AI$8,Terms_Kind,"band",Terms_Lower,"<"&N11)-1,"00")) | AJ11: =IFERROR(INDEX(Terms_Contrib,MATCH(AI11,Terms_Key,0)),0) | AK11: =IF(O11="",AK$8&"|MISSING",AK$8&"|q"&TEXT(COUNTIFS(Terms_LCT,AK$8,Terms_Kind,"band",Terms_Lower,"<"&O11)-1,"00")) | AL11: =IFERROR(INDEX(Terms_Contrib,MATCH(AK11,Terms_Key,0)),0) | AM11: =IF(P11="",AM$8&"|MISSING",AM$8&"|"&TEXT(P11,INDEX(Fmt_Str,MATCH(AM$8,Fmt_LCT,0)))) | AN11: =IFERROR(INDEX(Terms_Contrib,MATCH(AM11,Terms_Key,0)),0) | AO11: =IF(Q11="",AO$8&"|MISSING",AO$8&"|"&TEXT(Q11,INDEX(Fmt_Str,MATCH(AO$8,Fmt_LCT,0)))) | AP11: =IFERROR(INDEX(Terms_Contrib,MATCH(AO11,Terms_Key,0)),0) | AQ11: =IF(R11="",AQ$8&"|MISSING",AQ$8&"|"&TEXT(R11,INDEX(Fmt_Str,MATCH(AQ$8,Fmt_LCT,0)))) | AR11: =IFERROR(INDEX(Terms_Contrib,MATCH(AQ11,Terms_Key,0)),0) | AS11: =IF(S11="",AS$8&"|MISSING",AS$8&"|"&TEXT(S11,INDEX(Fmt_Str,MATCH(AS$8,Fmt_LCT,0)))) | AT11: =IFERROR(INDEX(Terms_Contrib,MATCH(AS11,Terms_Key,0)),0) | AU11: =IF(T11="",AU$8&"|MISSING",AU$8&"|"&TEXT(T11,INDEX(Fmt_Str,MATCH(AU$8,Fmt_LCT,0)))) | AV11: =IFERROR(INDEX(Terms_Contrib,MATCH(AU11,Terms_Key,0)),0) | AW11: =INDEX(Terms_Contrib,MATCH(AW$8,Terms_Key,0)) | AX11: =INDEX(Terms_Contrib,MATCH(AX$8,Terms_Key,0)) | AY11: =LN(F11) | AZ11: =V11+X11+Z11+AB11+AD11+AF11+AH11+AJ11+AL11+AN11+AP11+AR11+AT11+AV11+AW11+AX11+AY11 | BA11: =EXP(AZ11) | BB11: =IFERROR(INDEX(Remap_To,MATCH(BB$8&"|"&IF(M11="","MISSING",M11&""),Remap_Key,0)),BB$8&"|"&IF(M11="","MISSING",M11&"")) | BC11: =IFERROR(INDEX(Terms_Contrib,MATCH(BB11,Terms_Key,0)),0) | BD11: =IF(P11="",BD$8&"|MISSING",BD$8&"|q"&TEXT(COUNTIFS(Terms_LCT,BD$8,Terms_Kind,"band",Terms_Lower,"<"&P11)-1,"00")) | BE11: =IFERROR(INDEX(Terms_Contrib,MATCH(BD11,Terms_Key,0)),0) | BF11: =IF(Q11="",BF$8&"|MISSING",BF$8&"|q"&TEXT(COUNTIFS(Terms_LCT,BF$8,Terms_Kind,"band",Terms_Lower,"<"&Q11)-1,"00")) | BG11: =IFERROR(INDEX(Terms_Contrib,MATCH(BF11,Terms_Key,0)),0) | BH11: =INDEX(Terms_Contrib,MATCH(BH$8,Terms_Key,0)) | BI11: =INDEX(Terms_Contrib,MATCH(BI$8,Terms_Key,0)) | BJ11: =LN(F11) | BK11: =INDEX(Terms_Contrib,MATCH(BK$8,Terms_Key,0)) | BL11: =BC11+BE11+BG11+BH11+BI11+BJ11+BK11 | BM11: =EXP(BL11) | BN11: =BA11+BM11 | BO11: =IF(C11="true",Lvl_MotNB,Lvl_MotRen) | BP11: =IF(C11="true",BN11*BO11*Lvl_MotNB2/BO11,BN11*BO11) | BQ11: =INDEX(Py_Final,MATCH($B11,Py_ID,0)) | BR11: =ABS(BP11/BQ11-1) | BS11: =ISNA(MATCH(U11,Terms_Key,0))+ISNA(MATCH(W11,Terms_Key,0))+ISNA(MATCH(Y11,Terms_Key,0))+ISNA(MATCH(AA11,Terms_Key,0))+ISNA(MATCH(AC11,Terms_Key,0))+ISNA(MATCH(AE11,Terms_Key,0))+ISNA(MATCH(AG11,Terms_Key,0))+ISNA(MATCH(AI11,Terms_Key,0))+ISNA(MATCH(AK11,Terms_Key,0))+ISNA(MATCH(AM11,Terms_Key,0))+ISNA(MATCH(AO11,Terms_Key,0))+ISNA(MATCH(AQ11,Terms_Key,0))+ISNA(MATCH(AS11,Terms_Key,0))+ISNA(MATCH(AU11,Terms_Key,0))+ISNA(MATCH(AW$8,Terms_Key,0))+ISNA(MATCH(AX$8,Terms_Key,0))+ISNA(MATCH(BB11,Terms_Key,0))+ISNA(MATCH(BD11,Terms_Key,0))+ISNA(MATCH(BF11,Terms_Key,0))+ISNA(MATCH(BH$8,Terms_Key,0))+ISNA(MATCH(BI$8,Terms_Key,0))+ISNA(MATCH(BK$8,Terms_Key,0))
B12: ='Int. Inputs'!$B$18 | C12: =IF(ISBLANK(INDEX(Pol_Data,MATCH($B12,Pol_ID,0),MATCH("new_business",Pol_Head,0))),"",INDEX(Pol_Data,MATCH($B12,Pol_ID,0),MATCH("new_business",Pol_Head,0))) | D12: =IF(ISBLANK(INDEX(Pol_Data,MATCH($B12,Pol_ID,0),MATCH("period_start",Pol_Head,0))),"",INDEX(Pol_Data,MATCH($B12,Pol_ID,0),MATCH("period_start",Pol_Head,0))) | E12: =IF(ISBLANK(INDEX(Pol_Data,MATCH($B12,Pol_ID,0),MATCH("period_end",Pol_Head,0))),"",INDEX(Pol_Data,MATCH($B12,Pol_ID,0),MATCH("period_end",Pol_Head,0))) | F12: =(E12-D12+1)/365 | G12: =IF(ISBLANK(INDEX(Pol_Data,MATCH($B12,Pol_ID,0),MATCH("marketing_segment",Pol_Head,0))),"",INDEX(Pol_Data,MATCH($B12,Pol_ID,0),MATCH("marketing_segment",Pol_Head,0))) | H12: =IF(ISBLANK(INDEX(Pol_Data,MATCH($B12,Pol_ID,0),MATCH("cover_type",Pol_Head,0))),"",INDEX(Pol_Data,MATCH($B12,Pol_ID,0),MATCH("cover_type",Pol_Head,0))) | I12: =IF(ISBLANK(INDEX(Pol_Data,MATCH($B12,Pol_ID,0),MATCH("urban_density",Pol_Head,0))),"",INDEX(Pol_Data,MATCH($B12,Pol_ID,0),MATCH("urban_density",Pol_Head,0))) | J12: =IF(ISBLANK(INDEX(Pol_Data,MATCH($B12,Pol_ID,0),MATCH("channel",Pol_Head,0))),"",INDEX(Pol_Data,MATCH($B12,Pol_ID,0),MATCH("channel",Pol_Head,0))) | K12: =IF(ISBLANK(INDEX(Pol_Data,MATCH($B12,Pol_ID,0),MATCH("vehicle_use",Pol_Head,0))),"",INDEX(Pol_Data,MATCH($B12,Pol_ID,0),MATCH("vehicle_use",Pol_Head,0))) | L12: =IF(ISBLANK(INDEX(Pol_Data,MATCH($B12,Pol_ID,0),MATCH("payment_method",Pol_Head,0))),"",INDEX(Pol_Data,MATCH($B12,Pol_ID,0),MATCH("payment_method",Pol_Head,0))) | M12: =IF(ISBLANK(INDEX(Pol_Data,MATCH($B12,Pol_ID,0),MATCH("driver_age_band",Pol_Head,0))),"",INDEX(Pol_Data,MATCH($B12,Pol_ID,0),MATCH("driver_age_band",Pol_Head,0))) | N12: =IF(ISBLANK(INDEX(Pol_Data,MATCH($B12,Pol_ID,0),MATCH("prior_claims_5y",Pol_Head,0))),"",INDEX(Pol_Data,MATCH($B12,Pol_ID,0),MATCH("prior_claims_5y",Pol_Head,0))) | O12: =IF(ISBLANK(INDEX(Pol_Data,MATCH($B12,Pol_ID,0),MATCH("missed_payments_12m",Pol_Head,0))),"",INDEX(Pol_Data,MATCH($B12,Pol_ID,0),MATCH("missed_payments_12m",Pol_Head,0))) | P12: =IF(ISBLANK(INDEX(Pol_Data,MATCH($B12,Pol_ID,0),MATCH("ncb_years",Pol_Head,0))),"",INDEX(Pol_Data,MATCH($B12,Pol_ID,0),MATCH("ncb_years",Pol_Head,0))) | Q12: =IF(ISBLANK(INDEX(Pol_Data,MATCH($B12,Pol_ID,0),MATCH("years_licensed",Pol_Head,0))),"",INDEX(Pol_Data,MATCH($B12,Pol_ID,0),MATCH("years_licensed",Pol_Head,0))) | R12: =IF(ISBLANK(INDEX(Pol_Data,MATCH($B12,Pol_ID,0),MATCH("vehicle_age",Pol_Head,0))),"",INDEX(Pol_Data,MATCH($B12,Pol_ID,0),MATCH("vehicle_age",Pol_Head,0))) | S12: =IF(ISBLANK(INDEX(Pol_Data,MATCH($B12,Pol_ID,0),MATCH("vehicle_value_group",Pol_Head,0))),"",INDEX(Pol_Data,MATCH($B12,Pol_ID,0),MATCH("vehicle_value_group",Pol_Head,0))) | T12: =IF(ISBLANK(INDEX(Pol_Data,MATCH($B12,Pol_ID,0),MATCH("voluntary_excess",Pol_Head,0))),"",INDEX(Pol_Data,MATCH($B12,Pol_ID,0),MATCH("voluntary_excess",Pol_Head,0))) | U12: =IFERROR(INDEX(Remap_To,MATCH(U$8&"|"&IF(G12="","MISSING",G12&""),Remap_Key,0)),U$8&"|"&IF(G12="","MISSING",G12&"")) | V12: =IFERROR(INDEX(Terms_Contrib,MATCH(U12,Terms_Key,0)),0) | W12: =IFERROR(INDEX(Remap_To,MATCH(W$8&"|"&IF(H12="","MISSING",H12&""),Remap_Key,0)),W$8&"|"&IF(H12="","MISSING",H12&"")) | X12: =IFERROR(INDEX(Terms_Contrib,MATCH(W12,Terms_Key,0)),0) | Y12: =IFERROR(INDEX(Remap_To,MATCH(Y$8&"|"&IF(I12="","MISSING",I12&""),Remap_Key,0)),Y$8&"|"&IF(I12="","MISSING",I12&"")) | Z12: =IFERROR(INDEX(Terms_Contrib,MATCH(Y12,Terms_Key,0)),0) | AA12: =IFERROR(INDEX(Remap_To,MATCH(AA$8&"|"&IF(J12="","MISSING",J12&""),Remap_Key,0)),AA$8&"|"&IF(J12="","MISSING",J12&"")) | AB12: =IFERROR(INDEX(Terms_Contrib,MATCH(AA12,Terms_Key,0)),0) | AC12: =IFERROR(INDEX(Remap_To,MATCH(AC$8&"|"&IF(K12="","MISSING",K12&""),Remap_Key,0)),AC$8&"|"&IF(K12="","MISSING",K12&"")) | AD12: =IFERROR(INDEX(Terms_Contrib,MATCH(AC12,Terms_Key,0)),0) | AE12: =IFERROR(INDEX(Remap_To,MATCH(AE$8&"|"&IF(L12="","MISSING",L12&""),Remap_Key,0)),AE$8&"|"&IF(L12="","MISSING",L12&"")) | AF12: =IFERROR(INDEX(Terms_Contrib,MATCH(AE12,Terms_Key,0)),0) | AG12: =IFERROR(INDEX(Remap_To,MATCH(AG$8&"|"&IF(M12="","MISSING",M12&""),Remap_Key,0)),AG$8&"|"&IF(M12="","MISSING",M12&"")) | AH12: =IFERROR(INDEX(Terms_Contrib,MATCH(AG12,Terms_Key,0)),0) | AI12: =IF(N12="",AI$8&"|MISSING",AI$8&"|q"&TEXT(COUNTIFS(Terms_LCT,AI$8,Terms_Kind,"band",Terms_Lower,"<"&N12)-1,"00")) | AJ12: =IFERROR(INDEX(Terms_Contrib,MATCH(AI12,Terms_Key,0)),0) | AK12: =IF(O12="",AK$8&"|MISSING",AK$8&"|q"&TEXT(COUNTIFS(Terms_LCT,AK$8,Terms_Kind,"band",Terms_Lower,"<"&O12)-1,"00")) | AL12: =IFERROR(INDEX(Terms_Contrib,MATCH(AK12,Terms_Key,0)),0) | AM12: =IF(P12="",AM$8&"|MISSING",AM$8&"|"&TEXT(P12,INDEX(Fmt_Str,MATCH(AM$8,Fmt_LCT,0)))) | AN12: =IFERROR(INDEX(Terms_Contrib,MATCH(AM12,Terms_Key,0)),0) | AO12: =IF(Q12="",AO$8&"|MISSING",AO$8&"|"&TEXT(Q12,INDEX(Fmt_Str,MATCH(AO$8,Fmt_LCT,0)))) | AP12: =IFERROR(INDEX(Terms_Contrib,MATCH(AO12,Terms_Key,0)),0) | AQ12: =IF(R12="",AQ$8&"|MISSING",AQ$8&"|"&TEXT(R12,INDEX(Fmt_Str,MATCH(AQ$8,Fmt_LCT,0)))) | AR12: =IFERROR(INDEX(Terms_Contrib,MATCH(AQ12,Terms_Key,0)),0) | AS12: =IF(S12="",AS$8&"|MISSING",AS$8&"|"&TEXT(S12,INDEX(Fmt_Str,MATCH(AS$8,Fmt_LCT,0)))) | AT12: =IFERROR(INDEX(Terms_Contrib,MATCH(AS12,Terms_Key,0)),0) | AU12: =IF(T12="",AU$8&"|MISSING",AU$8&"|"&TEXT(T12,INDEX(Fmt_Str,MATCH(AU$8,Fmt_LCT,0)))) | AV12: =IFERROR(INDEX(Terms_Contrib,MATCH(AU12,Terms_Key,0)),0) | AW12: =INDEX(Terms_Contrib,MATCH(AW$8,Terms_Key,0)) | AX12: =INDEX(Terms_Contrib,MATCH(AX$8,Terms_Key,0)) | AY12: =LN(F12) | AZ12: =V12+X12+Z12+AB12+AD12+AF12+AH12+AJ12+AL12+AN12+AP12+AR12+AT12+AV12+AW12+AX12+AY12 | BA12: =EXP(AZ12) | BB12: =IFERROR(INDEX(Remap_To,MATCH(BB$8&"|"&IF(M12="","MISSING",M12&""),Remap_Key,0)),BB$8&"|"&IF(M12="","MISSING",M12&"")) | BC12: =IFERROR(INDEX(Terms_Contrib,MATCH(BB12,Terms_Key,0)),0) | BD12: =IF(P12="",BD$8&"|MISSING",BD$8&"|q"&TEXT(COUNTIFS(Terms_LCT,BD$8,Terms_Kind,"band",Terms_Lower,"<"&P12)-1,"00")) | BE12: =IFERROR(INDEX(Terms_Contrib,MATCH(BD12,Terms_Key,0)),0) | BF12: =IF(Q12="",BF$8&"|MISSING",BF$8&"|q"&TEXT(COUNTIFS(Terms_LCT,BF$8,Terms_Kind,"band",Terms_Lower,"<"&Q12)-1,"00")) | BG12: =IFERROR(INDEX(Terms_Contrib,MATCH(BF12,Terms_Key,0)),0) | BH12: =INDEX(Terms_Contrib,MATCH(BH$8,Terms_Key,0)) | BI12: =INDEX(Terms_Contrib,MATCH(BI$8,Terms_Key,0)) | BJ12: =LN(F12) | BK12: =INDEX(Terms_Contrib,MATCH(BK$8,Terms_Key,0)) | BL12: =BC12+BE12+BG12+BH12+BI12+BJ12+BK12 | BM12: =EXP(BL12) | BN12: =BA12+BM12 | BO12: =IF(C12="true",Lvl_MotNB,Lvl_MotRen) | BP12: =IF(C12="true",BN12*BO12*Lvl_MotNB2/BO12,BN12*BO12) | BQ12: =INDEX(Py_Final,MATCH($B12,Py_ID,0)) | BR12: =ABS(BP12/BQ12-1) | BS12: =ISNA(MATCH(U12,Terms_Key,0))+ISNA(MATCH(W12,Terms_Key,0))+ISNA(MATCH(Y12,Terms_Key,0))+ISNA(MATCH(AA12,Terms_Key,0))+ISNA(MATCH(AC12,Terms_Key,0))+ISNA(MATCH(AE12,Terms_Key,0))+ISNA(MATCH(AG12,Terms_Key,0))+ISNA(MATCH(AI12,Terms_Key,0))+ISNA(MATCH(AK12,Terms_Key,0))+ISNA(MATCH(AM12,Terms_Key,0))+ISNA(MATCH(AO12,Terms_Key,0))+ISNA(MATCH(AQ12,Terms_Key,0))+ISNA(MATCH(AS12,Terms_Key,0))+ISNA(MATCH(AU12,Terms_Key,0))+ISNA(MATCH(AW$8,Terms_Key,0))+ISNA(MATCH(AX$8,Terms_Key,0))+ISNA(MATCH(BB12,Terms_Key,0))+ISNA(MATCH(BD12,Terms_Key,0))+ISNA(MATCH(BF12,Terms_Key,0))+ISNA(MATCH(BH$8,Terms_Key,0))+ISNA(MATCH(BI$8,Terms_Key,0))+ISNA(MATCH(BK$8,Terms_Key,0))
B13: ='Int. Inputs'!$B$19 | C13: =IF(ISBLANK(INDEX(Pol_Data,MATCH($B13,Pol_ID,0),MATCH("new_business",Pol_Head,0))),"",INDEX(Pol_Data,MATCH($B13,Pol_ID,0),MATCH("new_business",Pol_Head,0))) | D13: =IF(ISBLANK(INDEX(Pol_Data,MATCH($B13,Pol_ID,0),MATCH("period_start",Pol_Head,0))),"",INDEX(Pol_Data,MATCH($B13,Pol_ID,0),MATCH("period_start",Pol_Head,0))) | E13: =IF(ISBLANK(INDEX(Pol_Data,MATCH($B13,Pol_ID,0),MATCH("period_end",Pol_Head,0))),"",INDEX(Pol_Data,MATCH($B13,Pol_ID,0),MATCH("period_end",Pol_Head,0))) | F13: =(E13-D13+1)/365 | G13: =IF(ISBLANK(INDEX(Pol_Data,MATCH($B13,Pol_ID,0),MATCH("marketing_segment",Pol_Head,0))),"",INDEX(Pol_Data,MATCH($B13,Pol_ID,0),MATCH("marketing_segment",Pol_Head,0))) | H13: =IF(ISBLANK(INDEX(Pol_Data,MATCH($B13,Pol_ID,0),MATCH("cover_type",Pol_Head,0))),"",INDEX(Pol_Data,MATCH($B13,Pol_ID,0),MATCH("cover_type",Pol_Head,0))) | I13: =IF(ISBLANK(INDEX(Pol_Data,MATCH($B13,Pol_ID,0),MATCH("urban_density",Pol_Head,0))),"",INDEX(Pol_Data,MATCH($B13,Pol_ID,0),MATCH("urban_density",Pol_Head,0))) | J13: =IF(ISBLANK(INDEX(Pol_Data,MATCH($B13,Pol_ID,0),MATCH("channel",Pol_Head,0))),"",INDEX(Pol_Data,MATCH($B13,Pol_ID,0),MATCH("channel",Pol_Head,0))) | K13: =IF(ISBLANK(INDEX(Pol_Data,MATCH($B13,Pol_ID,0),MATCH("vehicle_use",Pol_Head,0))),"",INDEX(Pol_Data,MATCH($B13,Pol_ID,0),MATCH("vehicle_use",Pol_Head,0))) | L13: =IF(ISBLANK(INDEX(Pol_Data,MATCH($B13,Pol_ID,0),MATCH("payment_method",Pol_Head,0))),"",INDEX(Pol_Data,MATCH($B13,Pol_ID,0),MATCH("payment_method",Pol_Head,0))) | M13: =IF(ISBLANK(INDEX(Pol_Data,MATCH($B13,Pol_ID,0),MATCH("driver_age_band",Pol_Head,0))),"",INDEX(Pol_Data,MATCH($B13,Pol_ID,0),MATCH("driver_age_band",Pol_Head,0))) | N13: =IF(ISBLANK(INDEX(Pol_Data,MATCH($B13,Pol_ID,0),MATCH("prior_claims_5y",Pol_Head,0))),"",INDEX(Pol_Data,MATCH($B13,Pol_ID,0),MATCH("prior_claims_5y",Pol_Head,0))) | O13: =IF(ISBLANK(INDEX(Pol_Data,MATCH($B13,Pol_ID,0),MATCH("missed_payments_12m",Pol_Head,0))),"",INDEX(Pol_Data,MATCH($B13,Pol_ID,0),MATCH("missed_payments_12m",Pol_Head,0))) | P13: =IF(ISBLANK(INDEX(Pol_Data,MATCH($B13,Pol_ID,0),MATCH("ncb_years",Pol_Head,0))),"",INDEX(Pol_Data,MATCH($B13,Pol_ID,0),MATCH("ncb_years",Pol_Head,0))) | Q13: =IF(ISBLANK(INDEX(Pol_Data,MATCH($B13,Pol_ID,0),MATCH("years_licensed",Pol_Head,0))),"",INDEX(Pol_Data,MATCH($B13,Pol_ID,0),MATCH("years_licensed",Pol_Head,0))) | R13: =IF(ISBLANK(INDEX(Pol_Data,MATCH($B13,Pol_ID,0),MATCH("vehicle_age",Pol_Head,0))),"",INDEX(Pol_Data,MATCH($B13,Pol_ID,0),MATCH("vehicle_age",Pol_Head,0))) | S13: =IF(ISBLANK(INDEX(Pol_Data,MATCH($B13,Pol_ID,0),MATCH("vehicle_value_group",Pol_Head,0))),"",INDEX(Pol_Data,MATCH($B13,Pol_ID,0),MATCH("vehicle_value_group",Pol_Head,0))) | T13: =IF(ISBLANK(INDEX(Pol_Data,MATCH($B13,Pol_ID,0),MATCH("voluntary_excess",Pol_Head,0))),"",INDEX(Pol_Data,MATCH($B13,Pol_ID,0),MATCH("voluntary_excess",Pol_Head,0))) | U13: =IFERROR(INDEX(Remap_To,MATCH(U$8&"|"&IF(G13="","MISSING",G13&""),Remap_Key,0)),U$8&"|"&IF(G13="","MISSING",G13&"")) | V13: =IFERROR(INDEX(Terms_Contrib,MATCH(U13,Terms_Key,0)),0) | W13: =IFERROR(INDEX(Remap_To,MATCH(W$8&"|"&IF(H13="","MISSING",H13&""),Remap_Key,0)),W$8&"|"&IF(H13="","MISSING",H13&"")) | X13: =IFERROR(INDEX(Terms_Contrib,MATCH(W13,Terms_Key,0)),0) | Y13: =IFERROR(INDEX(Remap_To,MATCH(Y$8&"|"&IF(I13="","MISSING",I13&""),Remap_Key,0)),Y$8&"|"&IF(I13="","MISSING",I13&"")) | Z13: =IFERROR(INDEX(Terms_Contrib,MATCH(Y13,Terms_Key,0)),0) | AA13: =IFERROR(INDEX(Remap_To,MATCH(AA$8&"|"&IF(J13="","MISSING",J13&""),Remap_Key,0)),AA$8&"|"&IF(J13="","MISSING",J13&"")) | AB13: =IFERROR(INDEX(Terms_Contrib,MATCH(AA13,Terms_Key,0)),0) | AC13: =IFERROR(INDEX(Remap_To,MATCH(AC$8&"|"&IF(K13="","MISSING",K13&""),Remap_Key,0)),AC$8&"|"&IF(K13="","MISSING",K13&"")) | AD13: =IFERROR(INDEX(Terms_Contrib,MATCH(AC13,Terms_Key,0)),0) | AE13: =IFERROR(INDEX(Remap_To,MATCH(AE$8&"|"&IF(L13="","MISSING",L13&""),Remap_Key,0)),AE$8&"|"&IF(L13="","MISSING",L13&"")) | AF13: =IFERROR(INDEX(Terms_Contrib,MATCH(AE13,Terms_Key,0)),0) | AG13: =IFERROR(INDEX(Remap_To,MATCH(AG$8&"|"&IF(M13="","MISSING",M13&""),Remap_Key,0)),AG$8&"|"&IF(M13="","MISSING",M13&"")) | AH13: =IFERROR(INDEX(Terms_Contrib,MATCH(AG13,Terms_Key,0)),0) | AI13: =IF(N13="",AI$8&"|MISSING",AI$8&"|q"&TEXT(COUNTIFS(Terms_LCT,AI$8,Terms_Kind,"band",Terms_Lower,"<"&N13)-1,"00")) | AJ13: =IFERROR(INDEX(Terms_Contrib,MATCH(AI13,Terms_Key,0)),0) | AK13: =IF(O13="",AK$8&"|MISSING",AK$8&"|q"&TEXT(COUNTIFS(Terms_LCT,AK$8,Terms_Kind,"band",Terms_Lower,"<"&O13)-1,"00")) | AL13: =IFERROR(INDEX(Terms_Contrib,MATCH(AK13,Terms_Key,0)),0) | AM13: =IF(P13="",AM$8&"|MISSING",AM$8&"|"&TEXT(P13,INDEX(Fmt_Str,MATCH(AM$8,Fmt_LCT,0)))) | AN13: =IFERROR(INDEX(Terms_Contrib,MATCH(AM13,Terms_Key,0)),0) | AO13: =IF(Q13="",AO$8&"|MISSING",AO$8&"|"&TEXT(Q13,INDEX(Fmt_Str,MATCH(AO$8,Fmt_LCT,0)))) | AP13: =IFERROR(INDEX(Terms_Contrib,MATCH(AO13,Terms_Key,0)),0) | AQ13: =IF(R13="",AQ$8&"|MISSING",AQ$8&"|"&TEXT(R13,INDEX(Fmt_Str,MATCH(AQ$8,Fmt_LCT,0)))) | AR13: =IFERROR(INDEX(Terms_Contrib,MATCH(AQ13,Terms_Key,0)),0) | AS13: =IF(S13="",AS$8&"|MISSING",AS$8&"|"&TEXT(S13,INDEX(Fmt_Str,MATCH(AS$8,Fmt_LCT,0)))) | AT13: =IFERROR(INDEX(Terms_Contrib,MATCH(AS13,Terms_Key,0)),0) | AU13: =IF(T13="",AU$8&"|MISSING",AU$8&"|"&TEXT(T13,INDEX(Fmt_Str,MATCH(AU$8,Fmt_LCT,0)))) | AV13: =IFERROR(INDEX(Terms_Contrib,MATCH(AU13,Terms_Key,0)),0) | AW13: =INDEX(Terms_Contrib,MATCH(AW$8,Terms_Key,0)) | AX13: =INDEX(Terms_Contrib,MATCH(AX$8,Terms_Key,0)) | AY13: =LN(F13) | AZ13: =V13+X13+Z13+AB13+AD13+AF13+AH13+AJ13+AL13+AN13+AP13+AR13+AT13+AV13+AW13+AX13+AY13 | BA13: =EXP(AZ13) | BB13: =IFERROR(INDEX(Remap_To,MATCH(BB$8&"|"&IF(M13="","MISSING",M13&""),Remap_Key,0)),BB$8&"|"&IF(M13="","MISSING",M13&"")) | BC13: =IFERROR(INDEX(Terms_Contrib,MATCH(BB13,Terms_Key,0)),0) | BD13: =IF(P13="",BD$8&"|MISSING",BD$8&"|q"&TEXT(COUNTIFS(Terms_LCT,BD$8,Terms_Kind,"band",Terms_Lower,"<"&P13)-1,"00")) | BE13: =IFERROR(INDEX(Terms_Contrib,MATCH(BD13,Terms_Key,0)),0) | BF13: =IF(Q13="",BF$8&"|MISSING",BF$8&"|q"&TEXT(COUNTIFS(Terms_LCT,BF$8,Terms_Kind,"band",Terms_Lower,"<"&Q13)-1,"00")) | BG13: =IFERROR(INDEX(Terms_Contrib,MATCH(BF13,Terms_Key,0)),0) | BH13: =INDEX(Terms_Contrib,MATCH(BH$8,Terms_Key,0)) | BI13: =INDEX(Terms_Contrib,MATCH(BI$8,Terms_Key,0)) | BJ13: =LN(F13) | BK13: =INDEX(Terms_Contrib,MATCH(BK$8,Terms_Key,0)) | BL13: =BC13+BE13+BG13+BH13+BI13+BJ13+BK13 | BM13: =EXP(BL13) | BN13: =BA13+BM13 | BO13: =IF(C13="true",Lvl_MotNB,Lvl_MotRen) | BP13: =IF(C13="true",BN13*BO13*Lvl_MotNB2/BO13,BN13*BO13) | BQ13: =INDEX(Py_Final,MATCH($B13,Py_ID,0)) | BR13: =ABS(BP13/BQ13-1) | BS13: =ISNA(MATCH(U13,Terms_Key,0))+ISNA(MATCH(W13,Terms_Key,0))+ISNA(MATCH(Y13,Terms_Key,0))+ISNA(MATCH(AA13,Terms_Key,0))+ISNA(MATCH(AC13,Terms_Key,0))+ISNA(MATCH(AE13,Terms_Key,0))+ISNA(MATCH(AG13,Terms_Key,0))+ISNA(MATCH(AI13,Terms_Key,0))+ISNA(MATCH(AK13,Terms_Key,0))+ISNA(MATCH(AM13,Terms_Key,0))+ISNA(MATCH(AO13,Terms_Key,0))+ISNA(MATCH(AQ13,Terms_Key,0))+ISNA(MATCH(AS13,Terms_Key,0))+ISNA(MATCH(AU13,Terms_Key,0))+ISNA(MATCH(AW$8,Terms_Key,0))+ISNA(MATCH(AX$8,Terms_Key,0))+ISNA(MATCH(BB13,Terms_Key,0))+ISNA(MATCH(BD13,Terms_Key,0))+ISNA(MATCH(BF13,Terms_Key,0))+ISNA(MATCH(BH$8,Terms_Key,0))+ISNA(MATCH(BI$8,Terms_Key,0))+ISNA(MATCH(BK$8,Terms_Key,0))
B14: ='Int. Inputs'!$B$20 | C14: =IF(ISBLANK(INDEX(Pol_Data,MATCH($B14,Pol_ID,0),MATCH("new_business",Pol_Head,0))),"",INDEX(Pol_Data,MATCH($B14,Pol_ID,0),MATCH("new_business",Pol_Head,0))) | D14: =IF(ISBLANK(INDEX(Pol_Data,MATCH($B14,Pol_ID,0),MATCH("period_start",Pol_Head,0))),"",INDEX(Pol_Data,MATCH($B14,Pol_ID,0),MATCH("period_start",Pol_Head,0))) | E14: =IF(ISBLANK(INDEX(Pol_Data,MATCH($B14,Pol_ID,0),MATCH("period_end",Pol_Head,0))),"",INDEX(Pol_Data,MATCH($B14,Pol_ID,0),MATCH("period_end",Pol_Head,0))) | F14: =(E14-D14+1)/365 | G14: =IF(ISBLANK(INDEX(Pol_Data,MATCH($B14,Pol_ID,0),MATCH("marketing_segment",Pol_Head,0))),"",INDEX(Pol_Data,MATCH($B14,Pol_ID,0),MATCH("marketing_segment",Pol_Head,0))) | H14: =IF(ISBLANK(INDEX(Pol_Data,MATCH($B14,Pol_ID,0),MATCH("cover_type",Pol_Head,0))),"",INDEX(Pol_Data,MATCH($B14,Pol_ID,0),MATCH("cover_type",Pol_Head,0))) | I14: =IF(ISBLANK(INDEX(Pol_Data,MATCH($B14,Pol_ID,0),MATCH("urban_density",Pol_Head,0))),"",INDEX(Pol_Data,MATCH($B14,Pol_ID,0),MATCH("urban_density",Pol_Head,0))) | J14: =IF(ISBLANK(INDEX(Pol_Data,MATCH($B14,Pol_ID,0),MATCH("channel",Pol_Head,0))),"",INDEX(Pol_Data,MATCH($B14,Pol_ID,0),MATCH("channel",Pol_Head,0))) | K14: =IF(ISBLANK(INDEX(Pol_Data,MATCH($B14,Pol_ID,0),MATCH("vehicle_use",Pol_Head,0))),"",INDEX(Pol_Data,MATCH($B14,Pol_ID,0),MATCH("vehicle_use",Pol_Head,0))) | L14: =IF(ISBLANK(INDEX(Pol_Data,MATCH($B14,Pol_ID,0),MATCH("payment_method",Pol_Head,0))),"",INDEX(Pol_Data,MATCH($B14,Pol_ID,0),MATCH("payment_method",Pol_Head,0))) | M14: =IF(ISBLANK(INDEX(Pol_Data,MATCH($B14,Pol_ID,0),MATCH("driver_age_band",Pol_Head,0))),"",INDEX(Pol_Data,MATCH($B14,Pol_ID,0),MATCH("driver_age_band",Pol_Head,0))) | N14: =IF(ISBLANK(INDEX(Pol_Data,MATCH($B14,Pol_ID,0),MATCH("prior_claims_5y",Pol_Head,0))),"",INDEX(Pol_Data,MATCH($B14,Pol_ID,0),MATCH("prior_claims_5y",Pol_Head,0))) | O14: =IF(ISBLANK(INDEX(Pol_Data,MATCH($B14,Pol_ID,0),MATCH("missed_payments_12m",Pol_Head,0))),"",INDEX(Pol_Data,MATCH($B14,Pol_ID,0),MATCH("missed_payments_12m",Pol_Head,0))) | P14: =IF(ISBLANK(INDEX(Pol_Data,MATCH($B14,Pol_ID,0),MATCH("ncb_years",Pol_Head,0))),"",INDEX(Pol_Data,MATCH($B14,Pol_ID,0),MATCH("ncb_years",Pol_Head,0))) | Q14: =IF(ISBLANK(INDEX(Pol_Data,MATCH($B14,Pol_ID,0),MATCH("years_licensed",Pol_Head,0))),"",INDEX(Pol_Data,MATCH($B14,Pol_ID,0),MATCH("years_licensed",Pol_Head,0))) | R14: =IF(ISBLANK(INDEX(Pol_Data,MATCH($B14,Pol_ID,0),MATCH("vehicle_age",Pol_Head,0))),"",INDEX(Pol_Data,MATCH($B14,Pol_ID,0),MATCH("vehicle_age",Pol_Head,0))) | S14: =IF(ISBLANK(INDEX(Pol_Data,MATCH($B14,Pol_ID,0),MATCH("vehicle_value_group",Pol_Head,0))),"",INDEX(Pol_Data,MATCH($B14,Pol_ID,0),MATCH("vehicle_value_group",Pol_Head,0))) | T14: =IF(ISBLANK(INDEX(Pol_Data,MATCH($B14,Pol_ID,0),MATCH("voluntary_excess",Pol_Head,0))),"",INDEX(Pol_Data,MATCH($B14,Pol_ID,0),MATCH("voluntary_excess",Pol_Head,0))) | U14: =IFERROR(INDEX(Remap_To,MATCH(U$8&"|"&IF(G14="","MISSING",G14&""),Remap_Key,0)),U$8&"|"&IF(G14="","MISSING",G14&"")) | V14: =IFERROR(INDEX(Terms_Contrib,MATCH(U14,Terms_Key,0)),0) | W14: =IFERROR(INDEX(Remap_To,MATCH(W$8&"|"&IF(H14="","MISSING",H14&""),Remap_Key,0)),W$8&"|"&IF(H14="","MISSING",H14&"")) | X14: =IFERROR(INDEX(Terms_Contrib,MATCH(W14,Terms_Key,0)),0) | Y14: =IFERROR(INDEX(Remap_To,MATCH(Y$8&"|"&IF(I14="","MISSING",I14&""),Remap_Key,0)),Y$8&"|"&IF(I14="","MISSING",I14&"")) | Z14: =IFERROR(INDEX(Terms_Contrib,MATCH(Y14,Terms_Key,0)),0) | AA14: =IFERROR(INDEX(Remap_To,MATCH(AA$8&"|"&IF(J14="","MISSING",J14&""),Remap_Key,0)),AA$8&"|"&IF(J14="","MISSING",J14&"")) | AB14: =IFERROR(INDEX(Terms_Contrib,MATCH(AA14,Terms_Key,0)),0) | AC14: =IFERROR(INDEX(Remap_To,MATCH(AC$8&"|"&IF(K14="","MISSING",K14&""),Remap_Key,0)),AC$8&"|"&IF(K14="","MISSING",K14&"")) | AD14: =IFERROR(INDEX(Terms_Contrib,MATCH(AC14,Terms_Key,0)),0) | AE14: =IFERROR(INDEX(Remap_To,MATCH(AE$8&"|"&IF(L14="","MISSING",L14&""),Remap_Key,0)),AE$8&"|"&IF(L14="","MISSING",L14&"")) | AF14: =IFERROR(INDEX(Terms_Contrib,MATCH(AE14,Terms_Key,0)),0) | AG14: =IFERROR(INDEX(Remap_To,MATCH(AG$8&"|"&IF(M14="","MISSING",M14&""),Remap_Key,0)),AG$8&"|"&IF(M14="","MISSING",M14&"")) | AH14: =IFERROR(INDEX(Terms_Contrib,MATCH(AG14,Terms_Key,0)),0) | AI14: =IF(N14="",AI$8&"|MISSING",AI$8&"|q"&TEXT(COUNTIFS(Terms_LCT,AI$8,Terms_Kind,"band",Terms_Lower,"<"&N14)-1,"00")) | AJ14: =IFERROR(INDEX(Terms_Contrib,MATCH(AI14,Terms_Key,0)),0) | AK14: =IF(O14="",AK$8&"|MISSING",AK$8&"|q"&TEXT(COUNTIFS(Terms_LCT,AK$8,Terms_Kind,"band",Terms_Lower,"<"&O14)-1,"00")) | AL14: =IFERROR(INDEX(Terms_Contrib,MATCH(AK14,Terms_Key,0)),0) | AM14: =IF(P14="",AM$8&"|MISSING",AM$8&"|"&TEXT(P14,INDEX(Fmt_Str,MATCH(AM$8,Fmt_LCT,0)))) | AN14: =IFERROR(INDEX(Terms_Contrib,MATCH(AM14,Terms_Key,0)),0) | AO14: =IF(Q14="",AO$8&"|MISSING",AO$8&"|"&TEXT(Q14,INDEX(Fmt_Str,MATCH(AO$8,Fmt_LCT,0)))) | AP14: =IFERROR(INDEX(Terms_Contrib,MATCH(AO14,Terms_Key,0)),0) | AQ14: =IF(R14="",AQ$8&"|MISSING",AQ$8&"|"&TEXT(R14,INDEX(Fmt_Str,MATCH(AQ$8,Fmt_LCT,0)))) | AR14: =IFERROR(INDEX(Terms_Contrib,MATCH(AQ14,Terms_Key,0)),0) | AS14: =IF(S14="",AS$8&"|MISSING",AS$8&"|"&TEXT(S14,INDEX(Fmt_Str,MATCH(AS$8,Fmt_LCT,0)))) | AT14: =IFERROR(INDEX(Terms_Contrib,MATCH(AS14,Terms_Key,0)),0) | AU14: =IF(T14="",AU$8&"|MISSING",AU$8&"|"&TEXT(T14,INDEX(Fmt_Str,MATCH(AU$8,Fmt_LCT,0)))) | AV14: =IFERROR(INDEX(Terms_Contrib,MATCH(AU14,Terms_Key,0)),0) | AW14: =INDEX(Terms_Contrib,MATCH(AW$8,Terms_Key,0)) | AX14: =INDEX(Terms_Contrib,MATCH(AX$8,Terms_Key,0)) | AY14: =LN(F14) | AZ14: =V14+X14+Z14+AB14+AD14+AF14+AH14+AJ14+AL14+AN14+AP14+AR14+AT14+AV14+AW14+AX14+AY14 | BA14: =EXP(AZ14) | BB14: =IFERROR(INDEX(Remap_To,MATCH(BB$8&"|"&IF(M14="","MISSING",M14&""),Remap_Key,0)),BB$8&"|"&IF(M14="","MISSING",M14&"")) | BC14: =IFERROR(INDEX(Terms_Contrib,MATCH(BB14,Terms_Key,0)),0) | BD14: =IF(P14="",BD$8&"|MISSING",BD$8&"|q"&TEXT(COUNTIFS(Terms_LCT,BD$8,Terms_Kind,"band",Terms_Lower,"<"&P14)-1,"00")) | BE14: =IFERROR(INDEX(Terms_Contrib,MATCH(BD14,Terms_Key,0)),0) | BF14: =IF(Q14="",BF$8&"|MISSING",BF$8&"|q"&TEXT(COUNTIFS(Terms_LCT,BF$8,Terms_Kind,"band",Terms_Lower,"<"&Q14)-1,"00")) | BG14: =IFERROR(INDEX(Terms_Contrib,MATCH(BF14,Terms_Key,0)),0) | BH14: =INDEX(Terms_Contrib,MATCH(BH$8,Terms_Key,0)) | BI14: =INDEX(Terms_Contrib,MATCH(BI$8,Terms_Key,0)) | BJ14: =LN(F14) | BK14: =INDEX(Terms_Contrib,MATCH(BK$8,Terms_Key,0)) | BL14: =BC14+BE14+BG14+BH14+BI14+BJ14+BK14 | BM14: =EXP(BL14) | BN14: =BA14+BM14 | BO14: =IF(C14="true",Lvl_MotNB,Lvl_MotRen) | BP14: =IF(C14="true",BN14*BO14*Lvl_MotNB2/BO14,BN14*BO14) | BQ14: =INDEX(Py_Final,MATCH($B14,Py_ID,0)) | BR14: =ABS(BP14/BQ14-1) | BS14: =ISNA(MATCH(U14,Terms_Key,0))+ISNA(MATCH(W14,Terms_Key,0))+ISNA(MATCH(Y14,Terms_Key,0))+ISNA(MATCH(AA14,Terms_Key,0))+ISNA(MATCH(AC14,Terms_Key,0))+ISNA(MATCH(AE14,Terms_Key,0))+ISNA(MATCH(AG14,Terms_Key,0))+ISNA(MATCH(AI14,Terms_Key,0))+ISNA(MATCH(AK14,Terms_Key,0))+ISNA(MATCH(AM14,Terms_Key,0))+ISNA(MATCH(AO14,Terms_Key,0))+ISNA(MATCH(AQ14,Terms_Key,0))+ISNA(MATCH(AS14,Terms_Key,0))+ISNA(MATCH(AU14,Terms_Key,0))+ISNA(MATCH(AW$8,Terms_Key,0))+ISNA(MATCH(AX$8,Terms_Key,0))+ISNA(MATCH(BB14,Terms_Key,0))+ISNA(MATCH(BD14,Terms_Key,0))+ISNA(MATCH(BF14,Terms_Key,0))+ISNA(MATCH(BH$8,Terms_Key,0))+ISNA(MATCH(BI$8,Terms_Key,0))+ISNA(MATCH(BK$8,Terms_Key,0))
B15: ='Int. Inputs'!$B$21 | C15: =IF(ISBLANK(INDEX(Pol_Data,MATCH($B15,Pol_ID,0),MATCH("new_business",Pol_Head,0))),"",INDEX(Pol_Data,MATCH($B15,Pol_ID,0),MATCH("new_business",Pol_Head,0))) | D15: =IF(ISBLANK(INDEX(Pol_Data,MATCH($B15,Pol_ID,0),MATCH("period_start",Pol_Head,0))),"",INDEX(Pol_Data,MATCH($B15,Pol_ID,0),MATCH("period_start",Pol_Head,0))) | E15: =IF(ISBLANK(INDEX(Pol_Data,MATCH($B15,Pol_ID,0),MATCH("period_end",Pol_Head,0))),"",INDEX(Pol_Data,MATCH($B15,Pol_ID,0),MATCH("period_end",Pol_Head,0))) | F15: =(E15-D15+1)/365 | G15: =IF(ISBLANK(INDEX(Pol_Data,MATCH($B15,Pol_ID,0),MATCH("marketing_segment",Pol_Head,0))),"",INDEX(Pol_Data,MATCH($B15,Pol_ID,0),MATCH("marketing_segment",Pol_Head,0))) | H15: =IF(ISBLANK(INDEX(Pol_Data,MATCH($B15,Pol_ID,0),MATCH("cover_type",Pol_Head,0))),"",INDEX(Pol_Data,MATCH($B15,Pol_ID,0),MATCH("cover_type",Pol_Head,0))) | I15: =IF(ISBLANK(INDEX(Pol_Data,MATCH($B15,Pol_ID,0),MATCH("urban_density",Pol_Head,0))),"",INDEX(Pol_Data,MATCH($B15,Pol_ID,0),MATCH("urban_density",Pol_Head,0))) | J15: =IF(ISBLANK(INDEX(Pol_Data,MATCH($B15,Pol_ID,0),MATCH("channel",Pol_Head,0))),"",INDEX(Pol_Data,MATCH($B15,Pol_ID,0),MATCH("channel",Pol_Head,0))) | K15: =IF(ISBLANK(INDEX(Pol_Data,MATCH($B15,Pol_ID,0),MATCH("vehicle_use",Pol_Head,0))),"",INDEX(Pol_Data,MATCH($B15,Pol_ID,0),MATCH("vehicle_use",Pol_Head,0))) | L15: =IF(ISBLANK(INDEX(Pol_Data,MATCH($B15,Pol_ID,0),MATCH("payment_method",Pol_Head,0))),"",INDEX(Pol_Data,MATCH($B15,Pol_ID,0),MATCH("payment_method",Pol_Head,0))) | M15: =IF(ISBLANK(INDEX(Pol_Data,MATCH($B15,Pol_ID,0),MATCH("driver_age_band",Pol_Head,0))),"",INDEX(Pol_Data,MATCH($B15,Pol_ID,0),MATCH("driver_age_band",Pol_Head,0))) | N15: =IF(ISBLANK(INDEX(Pol_Data,MATCH($B15,Pol_ID,0),MATCH("prior_claims_5y",Pol_Head,0))),"",INDEX(Pol_Data,MATCH($B15,Pol_ID,0),MATCH("prior_claims_5y",Pol_Head,0))) | O15: =IF(ISBLANK(INDEX(Pol_Data,MATCH($B15,Pol_ID,0),MATCH("missed_payments_12m",Pol_Head,0))),"",INDEX(Pol_Data,MATCH($B15,Pol_ID,0),MATCH("missed_payments_12m",Pol_Head,0))) | P15: =IF(ISBLANK(INDEX(Pol_Data,MATCH($B15,Pol_ID,0),MATCH("ncb_years",Pol_Head,0))),"",INDEX(Pol_Data,MATCH($B15,Pol_ID,0),MATCH("ncb_years",Pol_Head,0))) | Q15: =IF(ISBLANK(INDEX(Pol_Data,MATCH($B15,Pol_ID,0),MATCH("years_licensed",Pol_Head,0))),"",INDEX(Pol_Data,MATCH($B15,Pol_ID,0),MATCH("years_licensed",Pol_Head,0))) | R15: =IF(ISBLANK(INDEX(Pol_Data,MATCH($B15,Pol_ID,0),MATCH("vehicle_age",Pol_Head,0))),"",INDEX(Pol_Data,MATCH($B15,Pol_ID,0),MATCH("vehicle_age",Pol_Head,0))) | S15: =IF(ISBLANK(INDEX(Pol_Data,MATCH($B15,Pol_ID,0),MATCH("vehicle_value_group",Pol_Head,0))),"",INDEX(Pol_Data,MATCH($B15,Pol_ID,0),MATCH("vehicle_value_group",Pol_Head,0))) | T15: =IF(ISBLANK(INDEX(Pol_Data,MATCH($B15,Pol_ID,0),MATCH("voluntary_excess",Pol_Head,0))),"",INDEX(Pol_Data,MATCH($B15,Pol_ID,0),MATCH("voluntary_excess",Pol_Head,0))) | U15: =IFERROR(INDEX(Remap_To,MATCH(U$8&"|"&IF(G15="","MISSING",G15&""),Remap_Key,0)),U$8&"|"&IF(G15="","MISSING",G15&"")) | V15: =IFERROR(INDEX(Terms_Contrib,MATCH(U15,Terms_Key,0)),0) | W15: =IFERROR(INDEX(Remap_To,MATCH(W$8&"|"&IF(H15="","MISSING",H15&""),Remap_Key,0)),W$8&"|"&IF(H15="","MISSING",H15&"")) | X15: =IFERROR(INDEX(Terms_Contrib,MATCH(W15,Terms_Key,0)),0) | Y15: =IFERROR(INDEX(Remap_To,MATCH(Y$8&"|"&IF(I15="","MISSING",I15&""),Remap_Key,0)),Y$8&"|"&IF(I15="","MISSING",I15&"")) | Z15: =IFERROR(INDEX(Terms_Contrib,MATCH(Y15,Terms_Key,0)),0) | AA15: =IFERROR(INDEX(Remap_To,MATCH(AA$8&"|"&IF(J15="","MISSING",J15&""),Remap_Key,0)),AA$8&"|"&IF(J15="","MISSING",J15&"")) | AB15: =IFERROR(INDEX(Terms_Contrib,MATCH(AA15,Terms_Key,0)),0) | AC15: =IFERROR(INDEX(Remap_To,MATCH(AC$8&"|"&IF(K15="","MISSING",K15&""),Remap_Key,0)),AC$8&"|"&IF(K15="","MISSING",K15&"")) | AD15: =IFERROR(INDEX(Terms_Contrib,MATCH(AC15,Terms_Key,0)),0) | AE15: =IFERROR(INDEX(Remap_To,MATCH(AE$8&"|"&IF(L15="","MISSING",L15&""),Remap_Key,0)),AE$8&"|"&IF(L15="","MISSING",L15&"")) | AF15: =IFERROR(INDEX(Terms_Contrib,MATCH(AE15,Terms_Key,0)),0) | AG15: =IFERROR(INDEX(Remap_To,MATCH(AG$8&"|"&IF(M15="","MISSING",M15&""),Remap_Key,0)),AG$8&"|"&IF(M15="","MISSING",M15&"")) | AH15: =IFERROR(INDEX(Terms_Contrib,MATCH(AG15,Terms_Key,0)),0) | AI15: =IF(N15="",AI$8&"|MISSING",AI$8&"|q"&TEXT(COUNTIFS(Terms_LCT,AI$8,Terms_Kind,"band",Terms_Lower,"<"&N15)-1,"00")) | AJ15: =IFERROR(INDEX(Terms_Contrib,MATCH(AI15,Terms_Key,0)),0) | AK15: =IF(O15="",AK$8&"|MISSING",AK$8&"|q"&TEXT(COUNTIFS(Terms_LCT,AK$8,Terms_Kind,"band",Terms_Lower,"<"&O15)-1,"00")) | AL15: =IFERROR(INDEX(Terms_Contrib,MATCH(AK15,Terms_Key,0)),0) | AM15: =IF(P15="",AM$8&"|MISSING",AM$8&"|"&TEXT(P15,INDEX(Fmt_Str,MATCH(AM$8,Fmt_LCT,0)))) | AN15: =IFERROR(INDEX(Terms_Contrib,MATCH(AM15,Terms_Key,0)),0) | AO15: =IF(Q15="",AO$8&"|MISSING",AO$8&"|"&TEXT(Q15,INDEX(Fmt_Str,MATCH(AO$8,Fmt_LCT,0)))) | AP15: =IFERROR(INDEX(Terms_Contrib,MATCH(AO15,Terms_Key,0)),0) | AQ15: =IF(R15="",AQ$8&"|MISSING",AQ$8&"|"&TEXT(R15,INDEX(Fmt_Str,MATCH(AQ$8,Fmt_LCT,0)))) | AR15: =IFERROR(INDEX(Terms_Contrib,MATCH(AQ15,Terms_Key,0)),0) | AS15: =IF(S15="",AS$8&"|MISSING",AS$8&"|"&TEXT(S15,INDEX(Fmt_Str,MATCH(AS$8,Fmt_LCT,0)))) | AT15: =IFERROR(INDEX(Terms_Contrib,MATCH(AS15,Terms_Key,0)),0) | AU15: =IF(T15="",AU$8&"|MISSING",AU$8&"|"&TEXT(T15,INDEX(Fmt_Str,MATCH(AU$8,Fmt_LCT,0)))) | AV15: =IFERROR(INDEX(Terms_Contrib,MATCH(AU15,Terms_Key,0)),0) | AW15: =INDEX(Terms_Contrib,MATCH(AW$8,Terms_Key,0)) | AX15: =INDEX(Terms_Contrib,MATCH(AX$8,Terms_Key,0)) | AY15: =LN(F15) | AZ15: =V15+X15+Z15+AB15+AD15+AF15+AH15+AJ15+AL15+AN15+AP15+AR15+AT15+AV15+AW15+AX15+AY15 | BA15: =EXP(AZ15) | BB15: =IFERROR(INDEX(Remap_To,MATCH(BB$8&"|"&IF(M15="","MISSING",M15&""),Remap_Key,0)),BB$8&"|"&IF(M15="","MISSING",M15&"")) | BC15: =IFERROR(INDEX(Terms_Contrib,MATCH(BB15,Terms_Key,0)),0) | BD15: =IF(P15="",BD$8&"|MISSING",BD$8&"|q"&TEXT(COUNTIFS(Terms_LCT,BD$8,Terms_Kind,"band",Terms_Lower,"<"&P15)-1,"00")) | BE15: =IFERROR(INDEX(Terms_Contrib,MATCH(BD15,Terms_Key,0)),0) | BF15: =IF(Q15="",BF$8&"|MISSING",BF$8&"|q"&TEXT(COUNTIFS(Terms_LCT,BF$8,Terms_Kind,"band",Terms_Lower,"<"&Q15)-1,"00")) | BG15: =IFERROR(INDEX(Terms_Contrib,MATCH(BF15,Terms_Key,0)),0) | BH15: =INDEX(Terms_Contrib,MATCH(BH$8,Terms_Key,0)) | BI15: =INDEX(Terms_Contrib,MATCH(BI$8,Terms_Key,0)) | BJ15: =LN(F15) | BK15: =INDEX(Terms_Contrib,MATCH(BK$8,Terms_Key,0)) | BL15: =BC15+BE15+BG15+BH15+BI15+BJ15+BK15 | BM15: =EXP(BL15) | BN15: =BA15+BM15 | BO15: =IF(C15="true",Lvl_MotNB,Lvl_MotRen) | BP15: =IF(C15="true",BN15*BO15*Lvl_MotNB2/BO15,BN15*BO15) | BQ15: =INDEX(Py_Final,MATCH($B15,Py_ID,0)) | BR15: =ABS(BP15/BQ15-1) | BS15: =ISNA(MATCH(U15,Terms_Key,0))+ISNA(MATCH(W15,Terms_Key,0))+ISNA(MATCH(Y15,Terms_Key,0))+ISNA(MATCH(AA15,Terms_Key,0))+ISNA(MATCH(AC15,Terms_Key,0))+ISNA(MATCH(AE15,Terms_Key,0))+ISNA(MATCH(AG15,Terms_Key,0))+ISNA(MATCH(AI15,Terms_Key,0))+ISNA(MATCH(AK15,Terms_Key,0))+ISNA(MATCH(AM15,Terms_Key,0))+ISNA(MATCH(AO15,Terms_Key,0))+ISNA(MATCH(AQ15,Terms_Key,0))+ISNA(MATCH(AS15,Terms_Key,0))+ISNA(MATCH(AU15,Terms_Key,0))+ISNA(MATCH(AW$8,Terms_Key,0))+ISNA(MATCH(AX$8,Terms_Key,0))+ISNA(MATCH(BB15,Terms_Key,0))+ISNA(MATCH(BD15,Terms_Key,0))+ISNA(MATCH(BF15,Terms_Key,0))+ISNA(MATCH(BH$8,Terms_Key,0))+ISNA(MATCH(BI$8,Terms_Key,0))+ISNA(MATCH(BK$8,Terms_Key,0))
B16: ='Int. Inputs'!$B$22 | C16: =IF(ISBLANK(INDEX(Pol_Data,MATCH($B16,Pol_ID,0),MATCH("new_business",Pol_Head,0))),"",INDEX(Pol_Data,MATCH($B16,Pol_ID,0),MATCH("new_business",Pol_Head,0))) | D16: =IF(ISBLANK(INDEX(Pol_Data,MATCH($B16,Pol_ID,0),MATCH("period_start",Pol_Head,0))),"",INDEX(Pol_Data,MATCH($B16,Pol_ID,0),MATCH("period_start",Pol_Head,0))) | E16: =IF(ISBLANK(INDEX(Pol_Data,MATCH($B16,Pol_ID,0),MATCH("period_end",Pol_Head,0))),"",INDEX(Pol_Data,MATCH($B16,Pol_ID,0),MATCH("period_end",Pol_Head,0))) | F16: =(E16-D16+1)/365 | G16: =IF(ISBLANK(INDEX(Pol_Data,MATCH($B16,Pol_ID,0),MATCH("marketing_segment",Pol_Head,0))),"",INDEX(Pol_Data,MATCH($B16,Pol_ID,0),MATCH("marketing_segment",Pol_Head,0))) | H16: =IF(ISBLANK(INDEX(Pol_Data,MATCH($B16,Pol_ID,0),MATCH("cover_type",Pol_Head,0))),"",INDEX(Pol_Data,MATCH($B16,Pol_ID,0),MATCH("cover_type",Pol_Head,0))) | I16: =IF(ISBLANK(INDEX(Pol_Data,MATCH($B16,Pol_ID,0),MATCH("urban_density",Pol_Head,0))),"",INDEX(Pol_Data,MATCH($B16,Pol_ID,0),MATCH("urban_density",Pol_Head,0))) | J16: =IF(ISBLANK(INDEX(Pol_Data,MATCH($B16,Pol_ID,0),MATCH("channel",Pol_Head,0))),"",INDEX(Pol_Data,MATCH($B16,Pol_ID,0),MATCH("channel",Pol_Head,0))) | K16: =IF(ISBLANK(INDEX(Pol_Data,MATCH($B16,Pol_ID,0),MATCH("vehicle_use",Pol_Head,0))),"",INDEX(Pol_Data,MATCH($B16,Pol_ID,0),MATCH("vehicle_use",Pol_Head,0))) | L16: =IF(ISBLANK(INDEX(Pol_Data,MATCH($B16,Pol_ID,0),MATCH("payment_method",Pol_Head,0))),"",INDEX(Pol_Data,MATCH($B16,Pol_ID,0),MATCH("payment_method",Pol_Head,0))) | M16: =IF(ISBLANK(INDEX(Pol_Data,MATCH($B16,Pol_ID,0),MATCH("driver_age_band",Pol_Head,0))),"",INDEX(Pol_Data,MATCH($B16,Pol_ID,0),MATCH("driver_age_band",Pol_Head,0))) | N16: =IF(ISBLANK(INDEX(Pol_Data,MATCH($B16,Pol_ID,0),MATCH("prior_claims_5y",Pol_Head,0))),"",INDEX(Pol_Data,MATCH($B16,Pol_ID,0),MATCH("prior_claims_5y",Pol_Head,0))) | O16: =IF(ISBLANK(INDEX(Pol_Data,MATCH($B16,Pol_ID,0),MATCH("missed_payments_12m",Pol_Head,0))),"",INDEX(Pol_Data,MATCH($B16,Pol_ID,0),MATCH("missed_payments_12m",Pol_Head,0))) | P16: =IF(ISBLANK(INDEX(Pol_Data,MATCH($B16,Pol_ID,0),MATCH("ncb_years",Pol_Head,0))),"",INDEX(Pol_Data,MATCH($B16,Pol_ID,0),MATCH("ncb_years",Pol_Head,0))) | Q16: =IF(ISBLANK(INDEX(Pol_Data,MATCH($B16,Pol_ID,0),MATCH("years_licensed",Pol_Head,0))),"",INDEX(Pol_Data,MATCH($B16,Pol_ID,0),MATCH("years_licensed",Pol_Head,0))) | R16: =IF(ISBLANK(INDEX(Pol_Data,MATCH($B16,Pol_ID,0),MATCH("vehicle_age",Pol_Head,0))),"",INDEX(Pol_Data,MATCH($B16,Pol_ID,0),MATCH("vehicle_age",Pol_Head,0))) | S16: =IF(ISBLANK(INDEX(Pol_Data,MATCH($B16,Pol_ID,0),MATCH("vehicle_value_group",Pol_Head,0))),"",INDEX(Pol_Data,MATCH($B16,Pol_ID,0),MATCH("vehicle_value_group",Pol_Head,0))) | T16: =IF(ISBLANK(INDEX(Pol_Data,MATCH($B16,Pol_ID,0),MATCH("voluntary_excess",Pol_Head,0))),"",INDEX(Pol_Data,MATCH($B16,Pol_ID,0),MATCH("voluntary_excess",Pol_Head,0))) | U16: =IFERROR(INDEX(Remap_To,MATCH(U$8&"|"&IF(G16="","MISSING",G16&""),Remap_Key,0)),U$8&"|"&IF(G16="","MISSING",G16&"")) | V16: =IFERROR(INDEX(Terms_Contrib,MATCH(U16,Terms_Key,0)),0) | W16: =IFERROR(INDEX(Remap_To,MATCH(W$8&"|"&IF(H16="","MISSING",H16&""),Remap_Key,0)),W$8&"|"&IF(H16="","MISSING",H16&"")) | X16: =IFERROR(INDEX(Terms_Contrib,MATCH(W16,Terms_Key,0)),0) | Y16: =IFERROR(INDEX(Remap_To,MATCH(Y$8&"|"&IF(I16="","MISSING",I16&""),Remap_Key,0)),Y$8&"|"&IF(I16="","MISSING",I16&"")) | Z16: =IFERROR(INDEX(Terms_Contrib,MATCH(Y16,Terms_Key,0)),0) | AA16: =IFERROR(INDEX(Remap_To,MATCH(AA$8&"|"&IF(J16="","MISSING",J16&""),Remap_Key,0)),AA$8&"|"&IF(J16="","MISSING",J16&"")) | AB16: =IFERROR(INDEX(Terms_Contrib,MATCH(AA16,Terms_Key,0)),0) | AC16: =IFERROR(INDEX(Remap_To,MATCH(AC$8&"|"&IF(K16="","MISSING",K16&""),Remap_Key,0)),AC$8&"|"&IF(K16="","MISSING",K16&"")) | AD16: =IFERROR(INDEX(Terms_Contrib,MATCH(AC16,Terms_Key,0)),0) | AE16: =IFERROR(INDEX(Remap_To,MATCH(AE$8&"|"&IF(L16="","MISSING",L16&""),Remap_Key,0)),AE$8&"|"&IF(L16="","MISSING",L16&"")) | AF16: =IFERROR(INDEX(Terms_Contrib,MATCH(AE16,Terms_Key,0)),0) | AG16: =IFERROR(INDEX(Remap_To,MATCH(AG$8&"|"&IF(M16="","MISSING",M16&""),Remap_Key,0)),AG$8&"|"&IF(M16="","MISSING",M16&"")) | AH16: =IFERROR(INDEX(Terms_Contrib,MATCH(AG16,Terms_Key,0)),0) | AI16: =IF(N16="",AI$8&"|MISSING",AI$8&"|q"&TEXT(COUNTIFS(Terms_LCT,AI$8,Terms_Kind,"band",Terms_Lower,"<"&N16)-1,"00")) | AJ16: =IFERROR(INDEX(Terms_Contrib,MATCH(AI16,Terms_Key,0)),0) | AK16: =IF(O16="",AK$8&"|MISSING",AK$8&"|q"&TEXT(COUNTIFS(Terms_LCT,AK$8,Terms_Kind,"band",Terms_Lower,"<"&O16)-1,"00")) | AL16: =IFERROR(INDEX(Terms_Contrib,MATCH(AK16,Terms_Key,0)),0) | AM16: =IF(P16="",AM$8&"|MISSING",AM$8&"|"&TEXT(P16,INDEX(Fmt_Str,MATCH(AM$8,Fmt_LCT,0)))) | AN16: =IFERROR(INDEX(Terms_Contrib,MATCH(AM16,Terms_Key,0)),0) | AO16: =IF(Q16="",AO$8&"|MISSING",AO$8&"|"&TEXT(Q16,INDEX(Fmt_Str,MATCH(AO$8,Fmt_LCT,0)))) | AP16: =IFERROR(INDEX(Terms_Contrib,MATCH(AO16,Terms_Key,0)),0) | AQ16: =IF(R16="",AQ$8&"|MISSING",AQ$8&"|"&TEXT(R16,INDEX(Fmt_Str,MATCH(AQ$8,Fmt_LCT,0)))) | AR16: =IFERROR(INDEX(Terms_Contrib,MATCH(AQ16,Terms_Key,0)),0) | AS16: =IF(S16="",AS$8&"|MISSING",AS$8&"|"&TEXT(S16,INDEX(Fmt_Str,MATCH(AS$8,Fmt_LCT,0)))) | AT16: =IFERROR(INDEX(Terms_Contrib,MATCH(AS16,Terms_Key,0)),0) | AU16: =IF(T16="",AU$8&"|MISSING",AU$8&"|"&TEXT(T16,INDEX(Fmt_Str,MATCH(AU$8,Fmt_LCT,0)))) | AV16: =IFERROR(INDEX(Terms_Contrib,MATCH(AU16,Terms_Key,0)),0) | AW16: =INDEX(Terms_Contrib,MATCH(AW$8,Terms_Key,0)) | AX16: =INDEX(Terms_Contrib,MATCH(AX$8,Terms_Key,0)) | AY16: =LN(F16) | AZ16: =V16+X16+Z16+AB16+AD16+AF16+AH16+AJ16+AL16+AN16+AP16+AR16+AT16+AV16+AW16+AX16+AY16 | BA16: =EXP(AZ16) | BB16: =IFERROR(INDEX(Remap_To,MATCH(BB$8&"|"&IF(M16="","MISSING",M16&""),Remap_Key,0)),BB$8&"|"&IF(M16="","MISSING",M16&"")) | BC16: =IFERROR(INDEX(Terms_Contrib,MATCH(BB16,Terms_Key,0)),0) | BD16: =IF(P16="",BD$8&"|MISSING",BD$8&"|q"&TEXT(COUNTIFS(Terms_LCT,BD$8,Terms_Kind,"band",Terms_Lower,"<"&P16)-1,"00")) | BE16: =IFERROR(INDEX(Terms_Contrib,MATCH(BD16,Terms_Key,0)),0) | BF16: =IF(Q16="",BF$8&"|MISSING",BF$8&"|q"&TEXT(COUNTIFS(Terms_LCT,BF$8,Terms_Kind,"band",Terms_Lower,"<"&Q16)-1,"00")) | BG16: =IFERROR(INDEX(Terms_Contrib,MATCH(BF16,Terms_Key,0)),0) | BH16: =INDEX(Terms_Contrib,MATCH(BH$8,Terms_Key,0)) | BI16: =INDEX(Terms_Contrib,MATCH(BI$8,Terms_Key,0)) | BJ16: =LN(F16) | BK16: =INDEX(Terms_Contrib,MATCH(BK$8,Terms_Key,0)) | BL16: =BC16+BE16+BG16+BH16+BI16+BJ16+BK16 | BM16: =EXP(BL16) | BN16: =BA16+BM16 | BO16: =IF(C16="true",Lvl_MotNB,Lvl_MotRen) | BP16: =IF(C16="true",BN16*BO16*Lvl_MotNB2/BO16,BN16*BO16) | BQ16: =INDEX(Py_Final,MATCH($B16,Py_ID,0)) | BR16: =ABS(BP16/BQ16-1) | BS16: =ISNA(MATCH(U16,Terms_Key,0))+ISNA(MATCH(W16,Terms_Key,0))+ISNA(MATCH(Y16,Terms_Key,0))+ISNA(MATCH(AA16,Terms_Key,0))+ISNA(MATCH(AC16,Terms_Key,0))+ISNA(MATCH(AE16,Terms_Key,0))+ISNA(MATCH(AG16,Terms_Key,0))+ISNA(MATCH(AI16,Terms_Key,0))+ISNA(MATCH(AK16,Terms_Key,0))+ISNA(MATCH(AM16,Terms_Key,0))+ISNA(MATCH(AO16,Terms_Key,0))+ISNA(MATCH(AQ16,Terms_Key,0))+ISNA(MATCH(AS16,Terms_Key,0))+ISNA(MATCH(AU16,Terms_Key,0))+ISNA(MATCH(AW$8,Terms_Key,0))+ISNA(MATCH(AX$8,Terms_Key,0))+ISNA(MATCH(BB16,Terms_Key,0))+ISNA(MATCH(BD16,Terms_Key,0))+ISNA(MATCH(BF16,Terms_Key,0))+ISNA(MATCH(BH$8,Terms_Key,0))+ISNA(MATCH(BI$8,Terms_Key,0))+ISNA(MATCH(BK$8,Terms_Key,0))

Sheet Rating Buildings
B2: Rating Buildings: inputs, data fixes and the large-claim GLM
B3: Small claims are XGBoost (193 trees): scored on the next sheet, Rating Buildings Trees, which also combines small and large claims and applies the level step.
AS4: Rows off Python (0 = pass) | AT4: Keys not found (0 = pass)
B5: Checks sit above their own columns at the right. | AS5: =COUNTIF(AS10:AS16,">1E-9") | AT5: =SUM(AT10:AT16)
B7: Policy | G7: Inputs | Q7: Data fixes | T7: Large claims GLM | AR7: Check against Python
T8: buildings|large|soil_type | V8: buildings|large|construction_type | X8: buildings|large|flood_zone | Z8: buildings|large|sum_insured | AB8: buildings|large|elevation_m | AD8: buildings|large|year_built | AF8: buildings|large|distance_to_river_km | AI8: buildings|large|x_clay_dry|per unit | AK8: buildings|large|x_fz3_rain|per unit | AL8: buildings|large|(intercept)| | AM8: buildings|large|trend|log contribution in 2025 | AO8: buildings|large|Pareto adjustment|
B9: Policy row | C9: New business | D9: Period start | E9: Period end | F9: Exposure (model, D-01) | G9: soil_type | H9: construction_type | I9: flood_zone | J9: sum_insured | K9: elevation_m | L9: year_built | M9: distance_to_river_km | N9: dry_summer_index | O9: rainfall_mm | P9: energy_rating | Q9: Sum insured (D-02) | R9: Year built (D-27) | S9: Construction (mapped) | T9: soil_type: key | U9: soil_type: log | V9: construction_type: key | W9: construction_type: log | X9: flood_zone: band | Y9: flood_zone: log | Z9: sum_insured: key | AA9: sum_insured: log | AB9: elevation_m: key | AC9: elevation_m: log | AD9: year_built: key | AE9: year_built: log | AF9: distance_to_river_km: key | AG9: distance_to_river_km: log | AH9: x_clay_dry | AI9: x_clay_dry: log | AJ9: x_fz3_rain | AK9: x_fz3_rain: log | AL9: Intercept | AM9: Trend to 2025 | AN9: ln(exposure) | AO9: ln(Pareto adj.) | AP9: Log prediction | AQ9: Large claim (CU) | AR9: Python large claim | AS9: Relative difference | AT9: Keys not found
B10: ='Int. Inputs'!$B$23 | C10: =IF(ISBLANK(INDEX(Pol_Data,MATCH($B10,Pol_ID,0),MATCH("new_business",Pol_Head,0))),"",INDEX(Pol_Data,MATCH($B10,Pol_ID,0),MATCH("new_business",Pol_Head,0))) | D10: =IF(ISBLANK(INDEX(Pol_Data,MATCH($B10,Pol_ID,0),MATCH("period_start",Pol_Head,0))),"",INDEX(Pol_Data,MATCH($B10,Pol_ID,0),MATCH("period_start",Pol_Head,0))) | E10: =IF(ISBLANK(INDEX(Pol_Data,MATCH($B10,Pol_ID,0),MATCH("period_end",Pol_Head,0))),"",INDEX(Pol_Data,MATCH($B10,Pol_ID,0),MATCH("period_end",Pol_Head,0))) | F10: =(E10-D10+1)/365 | G10: =IF(ISBLANK(INDEX(Pol_Data,MATCH($B10,Pol_ID,0),MATCH("soil_type",Pol_Head,0))),"",INDEX(Pol_Data,MATCH($B10,Pol_ID,0),MATCH("soil_type",Pol_Head,0))) | H10: =IF(ISBLANK(INDEX(Pol_Data,MATCH($B10,Pol_ID,0),MATCH("construction_type",Pol_Head,0))),"",INDEX(Pol_Data,MATCH($B10,Pol_ID,0),MATCH("construction_type",Pol_Head,0))) | I10: =IF(ISBLANK(INDEX(Pol_Data,MATCH($B10,Pol_ID,0),MATCH("flood_zone",Pol_Head,0))),"",INDEX(Pol_Data,MATCH($B10,Pol_ID,0),MATCH("flood_zone",Pol_Head,0))) | J10: =IF(ISBLANK(INDEX(Pol_Data,MATCH($B10,Pol_ID,0),MATCH("sum_insured",Pol_Head,0))),"",INDEX(Pol_Data,MATCH($B10,Pol_ID,0),MATCH("sum_insured",Pol_Head,0))) | K10: =IF(ISBLANK(INDEX(Pol_Data,MATCH($B10,Pol_ID,0),MATCH("elevation_m",Pol_Head,0))),"",INDEX(Pol_Data,MATCH($B10,Pol_ID,0),MATCH("elevation_m",Pol_Head,0))) | L10: =IF(ISBLANK(INDEX(Pol_Data,MATCH($B10,Pol_ID,0),MATCH("year_built",Pol_Head,0))),"",INDEX(Pol_Data,MATCH($B10,Pol_ID,0),MATCH("year_built",Pol_Head,0))) | M10: =IF(ISBLANK(INDEX(Pol_Data,MATCH($B10,Pol_ID,0),MATCH("distance_to_river_km",Pol_Head,0))),"",INDEX(Pol_Data,MATCH($B10,Pol_ID,0),MATCH("distance_to_river_km",Pol_Head,0))) | N10: =IF(ISBLANK(INDEX(Pol_Data,MATCH($B10,Pol_ID,0),MATCH("dry_summer_index",Pol_Head,0))),"",INDEX(Pol_Data,MATCH($B10,Pol_ID,0),MATCH("dry_summer_index",Pol_Head,0))) | O10: =IF(ISBLANK(INDEX(Pol_Data,MATCH($B10,Pol_ID,0),MATCH("rainfall_mm",Pol_Head,0))),"",INDEX(Pol_Data,MATCH($B10,Pol_ID,0),MATCH("rainfall_mm",Pol_Head,0))) | P10: =IF(ISBLANK(INDEX(Pol_Data,MATCH($B10,Pol_ID,0),MATCH("energy_rating",Pol_Head,0))),"",INDEX(Pol_Data,MATCH($B10,Pol_ID,0),MATCH("energy_rating",Pol_Head,0))) | Q10: =IF(J10="","",IF(J10>=SI_Thr_Bld,J10/SI_Div,J10)) | R10: =IF(L10=1900,INDEX(YB_Fill,MATCH(IF(P10="","missing",P10),YB_Rating,0)),L10) | S10: =IF(H10="","",INDEX(Con_Model,MATCH(H10,Con_Raw,0))) | T10: =IFERROR(INDEX(Remap_To,MATCH(T$8&"|"&IF(G10="","MISSING",G10&""),Remap_Key,0)),T$8&"|"&IF(G10="","MISSING",G10&"")) | U10: =IFERROR(INDEX(Terms_Contrib,MATCH(T10,Terms_Key,0)),0) | V10: =IFERROR(INDEX(Remap_To,MATCH(V$8&"|"&IF(S10="","MISSING",S10&""),Remap_Key,0)),V$8&"|"&IF(S10="","MISSING",S10&"")) | W10: =IFERROR(INDEX(Terms_Contrib,MATCH(V10,Terms_Key,0)),0) | X10: =IF(I10="",X$8&"|MISSING",X$8&"|q"&TEXT(COUNTIFS(Terms_LCT,X$8,Terms_Kind,"band",Terms_Lower,"<"&I10)-1,"00")) | Y10: =IFERROR(INDEX(Terms_Contrib,MATCH(X10,Terms_Key,0)),0) | Z10: =IF(Q10="",Z$8&"|MISSING",Z$8&"|"&TEXT(Q10,INDEX(Fmt_Str,MATCH(Z$8,Fmt_LCT,0)))) | AA10: =IFERROR(INDEX(Terms_Contrib,MATCH(Z10,Terms_Key,0)),0) | AB10: =IF(K10="",AB$8&"|MISSING",AB$8&"|"&TEXT(K10,INDEX(Fmt_Str,MATCH(AB$8,Fmt_LCT,0)))) | AC10: =IFERROR(INDEX(Terms_Contrib,MATCH(AB10,Terms_Key,0)),0) | AD10: =IF(R10="",AD$8&"|MISSING",AD$8&"|"&TEXT(R10,INDEX(Fmt_Str,MATCH(AD$8,Fmt_LCT,0)))) | AE10: =IFERROR(INDEX(Terms_Contrib,MATCH(AD10,Terms_Key,0)),0) | AF10: =IF(M10="",AF$8&"|MISSING",AF$8&"|"&TEXT(M10,INDEX(Fmt_Str,MATCH(AF$8,Fmt_LCT,0)))) | AG10: =IFERROR(INDEX(Terms_Contrib,MATCH(AF10,Terms_Key,0)),0) | AH10: =IF(AND(G10="clay",ISNUMBER(N10)),N10,0) | AI10: =INDEX(Terms_Contrib,MATCH(AI$8,Terms_Key,0))*AH10 | AJ10: =IF(AND(IF(I10="",99,I10)>=3,ISNUMBER(O10)),O10/1000,0) | AK10: =INDEX(Terms_Contrib,MATCH(AK$8,Terms_Key,0))*AJ10 | AL10: =INDEX(Terms_Contrib,MATCH(AL$8,Terms_Key,0)) | AM10: =INDEX(Terms_Contrib,MATCH(AM$8,Terms_Key,0)) | AN10: =LN(F10) | AO10: =INDEX(Terms_Contrib,MATCH(AO$8,Terms_Key,0)) | AP10: =U10+W10+Y10+AA10+AC10+AE10+AG10+AI10+AK10+AL10+AM10+AN10+AO10 | AQ10: =EXP(AP10) | AR10: =INDEX(Py_Large,MATCH($B10,Py_ID,0)) | AS10: =ABS(AQ10/AR10-1) | AT10: =ISNA(MATCH(T10,Terms_Key,0))+ISNA(MATCH(V10,Terms_Key,0))+ISNA(MATCH(X10,Terms_Key,0))+ISNA(MATCH(Z10,Terms_Key,0))+ISNA(MATCH(AB10,Terms_Key,0))+ISNA(MATCH(AD10,Terms_Key,0))+ISNA(MATCH(AF10,Terms_Key,0))+ISNA(MATCH(AI$8,Terms_Key,0))+ISNA(MATCH(AK$8,Terms_Key,0))+ISNA(MATCH(AL$8,Terms_Key,0))+ISNA(MATCH(AM$8,Terms_Key,0))+ISNA(MATCH(AO$8,Terms_Key,0))
B11: ='Int. Inputs'!$B$24 | C11: =IF(ISBLANK(INDEX(Pol_Data,MATCH($B11,Pol_ID,0),MATCH("new_business",Pol_Head,0))),"",INDEX(Pol_Data,MATCH($B11,Pol_ID,0),MATCH("new_business",Pol_Head,0))) | D11: =IF(ISBLANK(INDEX(Pol_Data,MATCH($B11,Pol_ID,0),MATCH("period_start",Pol_Head,0))),"",INDEX(Pol_Data,MATCH($B11,Pol_ID,0),MATCH("period_start",Pol_Head,0))) | E11: =IF(ISBLANK(INDEX(Pol_Data,MATCH($B11,Pol_ID,0),MATCH("period_end",Pol_Head,0))),"",INDEX(Pol_Data,MATCH($B11,Pol_ID,0),MATCH("period_end",Pol_Head,0))) | F11: =(E11-D11+1)/365 | G11: =IF(ISBLANK(INDEX(Pol_Data,MATCH($B11,Pol_ID,0),MATCH("soil_type",Pol_Head,0))),"",INDEX(Pol_Data,MATCH($B11,Pol_ID,0),MATCH("soil_type",Pol_Head,0))) | H11: =IF(ISBLANK(INDEX(Pol_Data,MATCH($B11,Pol_ID,0),MATCH("construction_type",Pol_Head,0))),"",INDEX(Pol_Data,MATCH($B11,Pol_ID,0),MATCH("construction_type",Pol_Head,0))) | I11: =IF(ISBLANK(INDEX(Pol_Data,MATCH($B11,Pol_ID,0),MATCH("flood_zone",Pol_Head,0))),"",INDEX(Pol_Data,MATCH($B11,Pol_ID,0),MATCH("flood_zone",Pol_Head,0))) | J11: =IF(ISBLANK(INDEX(Pol_Data,MATCH($B11,Pol_ID,0),MATCH("sum_insured",Pol_Head,0))),"",INDEX(Pol_Data,MATCH($B11,Pol_ID,0),MATCH("sum_insured",Pol_Head,0))) | K11: =IF(ISBLANK(INDEX(Pol_Data,MATCH($B11,Pol_ID,0),MATCH("elevation_m",Pol_Head,0))),"",INDEX(Pol_Data,MATCH($B11,Pol_ID,0),MATCH("elevation_m",Pol_Head,0))) | L11: =IF(ISBLANK(INDEX(Pol_Data,MATCH($B11,Pol_ID,0),MATCH("year_built",Pol_Head,0))),"",INDEX(Pol_Data,MATCH($B11,Pol_ID,0),MATCH("year_built",Pol_Head,0))) | M11: =IF(ISBLANK(INDEX(Pol_Data,MATCH($B11,Pol_ID,0),MATCH("distance_to_river_km",Pol_Head,0))),"",INDEX(Pol_Data,MATCH($B11,Pol_ID,0),MATCH("distance_to_river_km",Pol_Head,0))) | N11: =IF(ISBLANK(INDEX(Pol_Data,MATCH($B11,Pol_ID,0),MATCH("dry_summer_index",Pol_Head,0))),"",INDEX(Pol_Data,MATCH($B11,Pol_ID,0),MATCH("dry_summer_index",Pol_Head,0))) | O11: =IF(ISBLANK(INDEX(Pol_Data,MATCH($B11,Pol_ID,0),MATCH("rainfall_mm",Pol_Head,0))),"",INDEX(Pol_Data,MATCH($B11,Pol_ID,0),MATCH("rainfall_mm",Pol_Head,0))) | P11: =IF(ISBLANK(INDEX(Pol_Data,MATCH($B11,Pol_ID,0),MATCH("energy_rating",Pol_Head,0))),"",INDEX(Pol_Data,MATCH($B11,Pol_ID,0),MATCH("energy_rating",Pol_Head,0))) | Q11: =IF(J11="","",IF(J11>=SI_Thr_Bld,J11/SI_Div,J11)) | R11: =IF(L11=1900,INDEX(YB_Fill,MATCH(IF(P11="","missing",P11),YB_Rating,0)),L11) | S11: =IF(H11="","",INDEX(Con_Model,MATCH(H11,Con_Raw,0))) | T11: =IFERROR(INDEX(Remap_To,MATCH(T$8&"|"&IF(G11="","MISSING",G11&""),Remap_Key,0)),T$8&"|"&IF(G11="","MISSING",G11&"")) | U11: =IFERROR(INDEX(Terms_Contrib,MATCH(T11,Terms_Key,0)),0) | V11: =IFERROR(INDEX(Remap_To,MATCH(V$8&"|"&IF(S11="","MISSING",S11&""),Remap_Key,0)),V$8&"|"&IF(S11="","MISSING",S11&"")) | W11: =IFERROR(INDEX(Terms_Contrib,MATCH(V11,Terms_Key,0)),0) | X11: =IF(I11="",X$8&"|MISSING",X$8&"|q"&TEXT(COUNTIFS(Terms_LCT,X$8,Terms_Kind,"band",Terms_Lower,"<"&I11)-1,"00")) | Y11: =IFERROR(INDEX(Terms_Contrib,MATCH(X11,Terms_Key,0)),0) | Z11: =IF(Q11="",Z$8&"|MISSING",Z$8&"|"&TEXT(Q11,INDEX(Fmt_Str,MATCH(Z$8,Fmt_LCT,0)))) | AA11: =IFERROR(INDEX(Terms_Contrib,MATCH(Z11,Terms_Key,0)),0) | AB11: =IF(K11="",AB$8&"|MISSING",AB$8&"|"&TEXT(K11,INDEX(Fmt_Str,MATCH(AB$8,Fmt_LCT,0)))) | AC11: =IFERROR(INDEX(Terms_Contrib,MATCH(AB11,Terms_Key,0)),0) | AD11: =IF(R11="",AD$8&"|MISSING",AD$8&"|"&TEXT(R11,INDEX(Fmt_Str,MATCH(AD$8,Fmt_LCT,0)))) | AE11: =IFERROR(INDEX(Terms_Contrib,MATCH(AD11,Terms_Key,0)),0) | AF11: =IF(M11="",AF$8&"|MISSING",AF$8&"|"&TEXT(M11,INDEX(Fmt_Str,MATCH(AF$8,Fmt_LCT,0)))) | AG11: =IFERROR(INDEX(Terms_Contrib,MATCH(AF11,Terms_Key,0)),0) | AH11: =IF(AND(G11="clay",ISNUMBER(N11)),N11,0) | AI11: =INDEX(Terms_Contrib,MATCH(AI$8,Terms_Key,0))*AH11 | AJ11: =IF(AND(IF(I11="",99,I11)>=3,ISNUMBER(O11)),O11/1000,0) | AK11: =INDEX(Terms_Contrib,MATCH(AK$8,Terms_Key,0))*AJ11 | AL11: =INDEX(Terms_Contrib,MATCH(AL$8,Terms_Key,0)) | AM11: =INDEX(Terms_Contrib,MATCH(AM$8,Terms_Key,0)) | AN11: =LN(F11) | AO11: =INDEX(Terms_Contrib,MATCH(AO$8,Terms_Key,0)) | AP11: =U11+W11+Y11+AA11+AC11+AE11+AG11+AI11+AK11+AL11+AM11+AN11+AO11 | AQ11: =EXP(AP11) | AR11: =INDEX(Py_Large,MATCH($B11,Py_ID,0)) | AS11: =ABS(AQ11/AR11-1) | AT11: =ISNA(MATCH(T11,Terms_Key,0))+ISNA(MATCH(V11,Terms_Key,0))+ISNA(MATCH(X11,Terms_Key,0))+ISNA(MATCH(Z11,Terms_Key,0))+ISNA(MATCH(AB11,Terms_Key,0))+ISNA(MATCH(AD11,Terms_Key,0))+ISNA(MATCH(AF11,Terms_Key,0))+ISNA(MATCH(AI$8,Terms_Key,0))+ISNA(MATCH(AK$8,Terms_Key,0))+ISNA(MATCH(AL$8,Terms_Key,0))+ISNA(MATCH(AM$8,Terms_Key,0))+ISNA(MATCH(AO$8,Terms_Key,0))
B12: ='Int. Inputs'!$B$25 | C12: =IF(ISBLANK(INDEX(Pol_Data,MATCH($B12,Pol_ID,0),MATCH("new_business",Pol_Head,0))),"",INDEX(Pol_Data,MATCH($B12,Pol_ID,0),MATCH("new_business",Pol_Head,0))) | D12: =IF(ISBLANK(INDEX(Pol_Data,MATCH($B12,Pol_ID,0),MATCH("period_start",Pol_Head,0))),"",INDEX(Pol_Data,MATCH($B12,Pol_ID,0),MATCH("period_start",Pol_Head,0))) | E12: =IF(ISBLANK(INDEX(Pol_Data,MATCH($B12,Pol_ID,0),MATCH("period_end",Pol_Head,0))),"",INDEX(Pol_Data,MATCH($B12,Pol_ID,0),MATCH("period_end",Pol_Head,0))) | F12: =(E12-D12+1)/365 | G12: =IF(ISBLANK(INDEX(Pol_Data,MATCH($B12,Pol_ID,0),MATCH("soil_type",Pol_Head,0))),"",INDEX(Pol_Data,MATCH($B12,Pol_ID,0),MATCH("soil_type",Pol_Head,0))) | H12: =IF(ISBLANK(INDEX(Pol_Data,MATCH($B12,Pol_ID,0),MATCH("construction_type",Pol_Head,0))),"",INDEX(Pol_Data,MATCH($B12,Pol_ID,0),MATCH("construction_type",Pol_Head,0))) | I12: =IF(ISBLANK(INDEX(Pol_Data,MATCH($B12,Pol_ID,0),MATCH("flood_zone",Pol_Head,0))),"",INDEX(Pol_Data,MATCH($B12,Pol_ID,0),MATCH("flood_zone",Pol_Head,0))) | J12: =IF(ISBLANK(INDEX(Pol_Data,MATCH($B12,Pol_ID,0),MATCH("sum_insured",Pol_Head,0))),"",INDEX(Pol_Data,MATCH($B12,Pol_ID,0),MATCH("sum_insured",Pol_Head,0))) | K12: =IF(ISBLANK(INDEX(Pol_Data,MATCH($B12,Pol_ID,0),MATCH("elevation_m",Pol_Head,0))),"",INDEX(Pol_Data,MATCH($B12,Pol_ID,0),MATCH("elevation_m",Pol_Head,0))) | L12: =IF(ISBLANK(INDEX(Pol_Data,MATCH($B12,Pol_ID,0),MATCH("year_built",Pol_Head,0))),"",INDEX(Pol_Data,MATCH($B12,Pol_ID,0),MATCH("year_built",Pol_Head,0))) | M12: =IF(ISBLANK(INDEX(Pol_Data,MATCH($B12,Pol_ID,0),MATCH("distance_to_river_km",Pol_Head,0))),"",INDEX(Pol_Data,MATCH($B12,Pol_ID,0),MATCH("distance_to_river_km",Pol_Head,0))) | N12: =IF(ISBLANK(INDEX(Pol_Data,MATCH($B12,Pol_ID,0),MATCH("dry_summer_index",Pol_Head,0))),"",INDEX(Pol_Data,MATCH($B12,Pol_ID,0),MATCH("dry_summer_index",Pol_Head,0))) | O12: =IF(ISBLANK(INDEX(Pol_Data,MATCH($B12,Pol_ID,0),MATCH("rainfall_mm",Pol_Head,0))),"",INDEX(Pol_Data,MATCH($B12,Pol_ID,0),MATCH("rainfall_mm",Pol_Head,0))) | P12: =IF(ISBLANK(INDEX(Pol_Data,MATCH($B12,Pol_ID,0),MATCH("energy_rating",Pol_Head,0))),"",INDEX(Pol_Data,MATCH($B12,Pol_ID,0),MATCH("energy_rating",Pol_Head,0))) | Q12: =IF(J12="","",IF(J12>=SI_Thr_Bld,J12/SI_Div,J12)) | R12: =IF(L12=1900,INDEX(YB_Fill,MATCH(IF(P12="","missing",P12),YB_Rating,0)),L12) | S12: =IF(H12="","",INDEX(Con_Model,MATCH(H12,Con_Raw,0))) | T12: =IFERROR(INDEX(Remap_To,MATCH(T$8&"|"&IF(G12="","MISSING",G12&""),Remap_Key,0)),T$8&"|"&IF(G12="","MISSING",G12&"")) | U12: =IFERROR(INDEX(Terms_Contrib,MATCH(T12,Terms_Key,0)),0) | V12: =IFERROR(INDEX(Remap_To,MATCH(V$8&"|"&IF(S12="","MISSING",S12&""),Remap_Key,0)),V$8&"|"&IF(S12="","MISSING",S12&"")) | W12: =IFERROR(INDEX(Terms_Contrib,MATCH(V12,Terms_Key,0)),0) | X12: =IF(I12="",X$8&"|MISSING",X$8&"|q"&TEXT(COUNTIFS(Terms_LCT,X$8,Terms_Kind,"band",Terms_Lower,"<"&I12)-1,"00")) | Y12: =IFERROR(INDEX(Terms_Contrib,MATCH(X12,Terms_Key,0)),0) | Z12: =IF(Q12="",Z$8&"|MISSING",Z$8&"|"&TEXT(Q12,INDEX(Fmt_Str,MATCH(Z$8,Fmt_LCT,0)))) | AA12: =IFERROR(INDEX(Terms_Contrib,MATCH(Z12,Terms_Key,0)),0) | AB12: =IF(K12="",AB$8&"|MISSING",AB$8&"|"&TEXT(K12,INDEX(Fmt_Str,MATCH(AB$8,Fmt_LCT,0)))) | AC12: =IFERROR(INDEX(Terms_Contrib,MATCH(AB12,Terms_Key,0)),0) | AD12: =IF(R12="",AD$8&"|MISSING",AD$8&"|"&TEXT(R12,INDEX(Fmt_Str,MATCH(AD$8,Fmt_LCT,0)))) | AE12: =IFERROR(INDEX(Terms_Contrib,MATCH(AD12,Terms_Key,0)),0) | AF12: =IF(M12="",AF$8&"|MISSING",AF$8&"|"&TEXT(M12,INDEX(Fmt_Str,MATCH(AF$8,Fmt_LCT,0)))) | AG12: =IFERROR(INDEX(Terms_Contrib,MATCH(AF12,Terms_Key,0)),0) | AH12: =IF(AND(G12="clay",ISNUMBER(N12)),N12,0) | AI12: =INDEX(Terms_Contrib,MATCH(AI$8,Terms_Key,0))*AH12 | AJ12: =IF(AND(IF(I12="",99,I12)>=3,ISNUMBER(O12)),O12/1000,0) | AK12: =INDEX(Terms_Contrib,MATCH(AK$8,Terms_Key,0))*AJ12 | AL12: =INDEX(Terms_Contrib,MATCH(AL$8,Terms_Key,0)) | AM12: =INDEX(Terms_Contrib,MATCH(AM$8,Terms_Key,0)) | AN12: =LN(F12) | AO12: =INDEX(Terms_Contrib,MATCH(AO$8,Terms_Key,0)) | AP12: =U12+W12+Y12+AA12+AC12+AE12+AG12+AI12+AK12+AL12+AM12+AN12+AO12 | AQ12: =EXP(AP12) | AR12: =INDEX(Py_Large,MATCH($B12,Py_ID,0)) | AS12: =ABS(AQ12/AR12-1) | AT12: =ISNA(MATCH(T12,Terms_Key,0))+ISNA(MATCH(V12,Terms_Key,0))+ISNA(MATCH(X12,Terms_Key,0))+ISNA(MATCH(Z12,Terms_Key,0))+ISNA(MATCH(AB12,Terms_Key,0))+ISNA(MATCH(AD12,Terms_Key,0))+ISNA(MATCH(AF12,Terms_Key,0))+ISNA(MATCH(AI$8,Terms_Key,0))+ISNA(MATCH(AK$8,Terms_Key,0))+ISNA(MATCH(AL$8,Terms_Key,0))+ISNA(MATCH(AM$8,Terms_Key,0))+ISNA(MATCH(AO$8,Terms_Key,0))
B13: ='Int. Inputs'!$B$26 | C13: =IF(ISBLANK(INDEX(Pol_Data,MATCH($B13,Pol_ID,0),MATCH("new_business",Pol_Head,0))),"",INDEX(Pol_Data,MATCH($B13,Pol_ID,0),MATCH("new_business",Pol_Head,0))) | D13: =IF(ISBLANK(INDEX(Pol_Data,MATCH($B13,Pol_ID,0),MATCH("period_start",Pol_Head,0))),"",INDEX(Pol_Data,MATCH($B13,Pol_ID,0),MATCH("period_start",Pol_Head,0))) | E13: =IF(ISBLANK(INDEX(Pol_Data,MATCH($B13,Pol_ID,0),MATCH("period_end",Pol_Head,0))),"",INDEX(Pol_Data,MATCH($B13,Pol_ID,0),MATCH("period_end",Pol_Head,0))) | F13: =(E13-D13+1)/365 | G13: =IF(ISBLANK(INDEX(Pol_Data,MATCH($B13,Pol_ID,0),MATCH("soil_type",Pol_Head,0))),"",INDEX(Pol_Data,MATCH($B13,Pol_ID,0),MATCH("soil_type",Pol_Head,0))) | H13: =IF(ISBLANK(INDEX(Pol_Data,MATCH($B13,Pol_ID,0),MATCH("construction_type",Pol_Head,0))),"",INDEX(Pol_Data,MATCH($B13,Pol_ID,0),MATCH("construction_type",Pol_Head,0))) | I13: =IF(ISBLANK(INDEX(Pol_Data,MATCH($B13,Pol_ID,0),MATCH("flood_zone",Pol_Head,0))),"",INDEX(Pol_Data,MATCH($B13,Pol_ID,0),MATCH("flood_zone",Pol_Head,0))) | J13: =IF(ISBLANK(INDEX(Pol_Data,MATCH($B13,Pol_ID,0),MATCH("sum_insured",Pol_Head,0))),"",INDEX(Pol_Data,MATCH($B13,Pol_ID,0),MATCH("sum_insured",Pol_Head,0))) | K13: =IF(ISBLANK(INDEX(Pol_Data,MATCH($B13,Pol_ID,0),MATCH("elevation_m",Pol_Head,0))),"",INDEX(Pol_Data,MATCH($B13,Pol_ID,0),MATCH("elevation_m",Pol_Head,0))) | L13: =IF(ISBLANK(INDEX(Pol_Data,MATCH($B13,Pol_ID,0),MATCH("year_built",Pol_Head,0))),"",INDEX(Pol_Data,MATCH($B13,Pol_ID,0),MATCH("year_built",Pol_Head,0))) | M13: =IF(ISBLANK(INDEX(Pol_Data,MATCH($B13,Pol_ID,0),MATCH("distance_to_river_km",Pol_Head,0))),"",INDEX(Pol_Data,MATCH($B13,Pol_ID,0),MATCH("distance_to_river_km",Pol_Head,0))) | N13: =IF(ISBLANK(INDEX(Pol_Data,MATCH($B13,Pol_ID,0),MATCH("dry_summer_index",Pol_Head,0))),"",INDEX(Pol_Data,MATCH($B13,Pol_ID,0),MATCH("dry_summer_index",Pol_Head,0))) | O13: =IF(ISBLANK(INDEX(Pol_Data,MATCH($B13,Pol_ID,0),MATCH("rainfall_mm",Pol_Head,0))),"",INDEX(Pol_Data,MATCH($B13,Pol_ID,0),MATCH("rainfall_mm",Pol_Head,0))) | P13: =IF(ISBLANK(INDEX(Pol_Data,MATCH($B13,Pol_ID,0),MATCH("energy_rating",Pol_Head,0))),"",INDEX(Pol_Data,MATCH($B13,Pol_ID,0),MATCH("energy_rating",Pol_Head,0))) | Q13: =IF(J13="","",IF(J13>=SI_Thr_Bld,J13/SI_Div,J13)) | R13: =IF(L13=1900,INDEX(YB_Fill,MATCH(IF(P13="","missing",P13),YB_Rating,0)),L13) | S13: =IF(H13="","",INDEX(Con_Model,MATCH(H13,Con_Raw,0))) | T13: =IFERROR(INDEX(Remap_To,MATCH(T$8&"|"&IF(G13="","MISSING",G13&""),Remap_Key,0)),T$8&"|"&IF(G13="","MISSING",G13&"")) | U13: =IFERROR(INDEX(Terms_Contrib,MATCH(T13,Terms_Key,0)),0) | V13: =IFERROR(INDEX(Remap_To,MATCH(V$8&"|"&IF(S13="","MISSING",S13&""),Remap_Key,0)),V$8&"|"&IF(S13="","MISSING",S13&"")) | W13: =IFERROR(INDEX(Terms_Contrib,MATCH(V13,Terms_Key,0)),0) | X13: =IF(I13="",X$8&"|MISSING",X$8&"|q"&TEXT(COUNTIFS(Terms_LCT,X$8,Terms_Kind,"band",Terms_Lower,"<"&I13)-1,"00")) | Y13: =IFERROR(INDEX(Terms_Contrib,MATCH(X13,Terms_Key,0)),0) | Z13: =IF(Q13="",Z$8&"|MISSING",Z$8&"|"&TEXT(Q13,INDEX(Fmt_Str,MATCH(Z$8,Fmt_LCT,0)))) | AA13: =IFERROR(INDEX(Terms_Contrib,MATCH(Z13,Terms_Key,0)),0) | AB13: =IF(K13="",AB$8&"|MISSING",AB$8&"|"&TEXT(K13,INDEX(Fmt_Str,MATCH(AB$8,Fmt_LCT,0)))) | AC13: =IFERROR(INDEX(Terms_Contrib,MATCH(AB13,Terms_Key,0)),0) | AD13: =IF(R13="",AD$8&"|MISSING",AD$8&"|"&TEXT(R13,INDEX(Fmt_Str,MATCH(AD$8,Fmt_LCT,0)))) | AE13: =IFERROR(INDEX(Terms_Contrib,MATCH(AD13,Terms_Key,0)),0) | AF13: =IF(M13="",AF$8&"|MISSING",AF$8&"|"&TEXT(M13,INDEX(Fmt_Str,MATCH(AF$8,Fmt_LCT,0)))) | AG13: =IFERROR(INDEX(Terms_Contrib,MATCH(AF13,Terms_Key,0)),0) | AH13: =IF(AND(G13="clay",ISNUMBER(N13)),N13,0) | AI13: =INDEX(Terms_Contrib,MATCH(AI$8,Terms_Key,0))*AH13 | AJ13: =IF(AND(IF(I13="",99,I13)>=3,ISNUMBER(O13)),O13/1000,0) | AK13: =INDEX(Terms_Contrib,MATCH(AK$8,Terms_Key,0))*AJ13 | AL13: =INDEX(Terms_Contrib,MATCH(AL$8,Terms_Key,0)) | AM13: =INDEX(Terms_Contrib,MATCH(AM$8,Terms_Key,0)) | AN13: =LN(F13) | AO13: =INDEX(Terms_Contrib,MATCH(AO$8,Terms_Key,0)) | AP13: =U13+W13+Y13+AA13+AC13+AE13+AG13+AI13+AK13+AL13+AM13+AN13+AO13 | AQ13: =EXP(AP13) | AR13: =INDEX(Py_Large,MATCH($B13,Py_ID,0)) | AS13: =ABS(AQ13/AR13-1) | AT13: =ISNA(MATCH(T13,Terms_Key,0))+ISNA(MATCH(V13,Terms_Key,0))+ISNA(MATCH(X13,Terms_Key,0))+ISNA(MATCH(Z13,Terms_Key,0))+ISNA(MATCH(AB13,Terms_Key,0))+ISNA(MATCH(AD13,Terms_Key,0))+ISNA(MATCH(AF13,Terms_Key,0))+ISNA(MATCH(AI$8,Terms_Key,0))+ISNA(MATCH(AK$8,Terms_Key,0))+ISNA(MATCH(AL$8,Terms_Key,0))+ISNA(MATCH(AM$8,Terms_Key,0))+ISNA(MATCH(AO$8,Terms_Key,0))
B14: ='Int. Inputs'!$B$27 | C14: =IF(ISBLANK(INDEX(Pol_Data,MATCH($B14,Pol_ID,0),MATCH("new_business",Pol_Head,0))),"",INDEX(Pol_Data,MATCH($B14,Pol_ID,0),MATCH("new_business",Pol_Head,0))) | D14: =IF(ISBLANK(INDEX(Pol_Data,MATCH($B14,Pol_ID,0),MATCH("period_start",Pol_Head,0))),"",INDEX(Pol_Data,MATCH($B14,Pol_ID,0),MATCH("period_start",Pol_Head,0))) | E14: =IF(ISBLANK(INDEX(Pol_Data,MATCH($B14,Pol_ID,0),MATCH("period_end",Pol_Head,0))),"",INDEX(Pol_Data,MATCH($B14,Pol_ID,0),MATCH("period_end",Pol_Head,0))) | F14: =(E14-D14+1)/365 | G14: =IF(ISBLANK(INDEX(Pol_Data,MATCH($B14,Pol_ID,0),MATCH("soil_type",Pol_Head,0))),"",INDEX(Pol_Data,MATCH($B14,Pol_ID,0),MATCH("soil_type",Pol_Head,0))) | H14: =IF(ISBLANK(INDEX(Pol_Data,MATCH($B14,Pol_ID,0),MATCH("construction_type",Pol_Head,0))),"",INDEX(Pol_Data,MATCH($B14,Pol_ID,0),MATCH("construction_type",Pol_Head,0))) | I14: =IF(ISBLANK(INDEX(Pol_Data,MATCH($B14,Pol_ID,0),MATCH("flood_zone",Pol_Head,0))),"",INDEX(Pol_Data,MATCH($B14,Pol_ID,0),MATCH("flood_zone",Pol_Head,0))) | J14: =IF(ISBLANK(INDEX(Pol_Data,MATCH($B14,Pol_ID,0),MATCH("sum_insured",Pol_Head,0))),"",INDEX(Pol_Data,MATCH($B14,Pol_ID,0),MATCH("sum_insured",Pol_Head,0))) | K14: =IF(ISBLANK(INDEX(Pol_Data,MATCH($B14,Pol_ID,0),MATCH("elevation_m",Pol_Head,0))),"",INDEX(Pol_Data,MATCH($B14,Pol_ID,0),MATCH("elevation_m",Pol_Head,0))) | L14: =IF(ISBLANK(INDEX(Pol_Data,MATCH($B14,Pol_ID,0),MATCH("year_built",Pol_Head,0))),"",INDEX(Pol_Data,MATCH($B14,Pol_ID,0),MATCH("year_built",Pol_Head,0))) | M14: =IF(ISBLANK(INDEX(Pol_Data,MATCH($B14,Pol_ID,0),MATCH("distance_to_river_km",Pol_Head,0))),"",INDEX(Pol_Data,MATCH($B14,Pol_ID,0),MATCH("distance_to_river_km",Pol_Head,0))) | N14: =IF(ISBLANK(INDEX(Pol_Data,MATCH($B14,Pol_ID,0),MATCH("dry_summer_index",Pol_Head,0))),"",INDEX(Pol_Data,MATCH($B14,Pol_ID,0),MATCH("dry_summer_index",Pol_Head,0))) | O14: =IF(ISBLANK(INDEX(Pol_Data,MATCH($B14,Pol_ID,0),MATCH("rainfall_mm",Pol_Head,0))),"",INDEX(Pol_Data,MATCH($B14,Pol_ID,0),MATCH("rainfall_mm",Pol_Head,0))) | P14: =IF(ISBLANK(INDEX(Pol_Data,MATCH($B14,Pol_ID,0),MATCH("energy_rating",Pol_Head,0))),"",INDEX(Pol_Data,MATCH($B14,Pol_ID,0),MATCH("energy_rating",Pol_Head,0))) | Q14: =IF(J14="","",IF(J14>=SI_Thr_Bld,J14/SI_Div,J14)) | R14: =IF(L14=1900,INDEX(YB_Fill,MATCH(IF(P14="","missing",P14),YB_Rating,0)),L14) | S14: =IF(H14="","",INDEX(Con_Model,MATCH(H14,Con_Raw,0))) | T14: =IFERROR(INDEX(Remap_To,MATCH(T$8&"|"&IF(G14="","MISSING",G14&""),Remap_Key,0)),T$8&"|"&IF(G14="","MISSING",G14&"")) | U14: =IFERROR(INDEX(Terms_Contrib,MATCH(T14,Terms_Key,0)),0) | V14: =IFERROR(INDEX(Remap_To,MATCH(V$8&"|"&IF(S14="","MISSING",S14&""),Remap_Key,0)),V$8&"|"&IF(S14="","MISSING",S14&"")) | W14: =IFERROR(INDEX(Terms_Contrib,MATCH(V14,Terms_Key,0)),0) | X14: =IF(I14="",X$8&"|MISSING",X$8&"|q"&TEXT(COUNTIFS(Terms_LCT,X$8,Terms_Kind,"band",Terms_Lower,"<"&I14)-1,"00")) | Y14: =IFERROR(INDEX(Terms_Contrib,MATCH(X14,Terms_Key,0)),0) | Z14: =IF(Q14="",Z$8&"|MISSING",Z$8&"|"&TEXT(Q14,INDEX(Fmt_Str,MATCH(Z$8,Fmt_LCT,0)))) | AA14: =IFERROR(INDEX(Terms_Contrib,MATCH(Z14,Terms_Key,0)),0) | AB14: =IF(K14="",AB$8&"|MISSING",AB$8&"|"&TEXT(K14,INDEX(Fmt_Str,MATCH(AB$8,Fmt_LCT,0)))) | AC14: =IFERROR(INDEX(Terms_Contrib,MATCH(AB14,Terms_Key,0)),0) | AD14: =IF(R14="",AD$8&"|MISSING",AD$8&"|"&TEXT(R14,INDEX(Fmt_Str,MATCH(AD$8,Fmt_LCT,0)))) | AE14: =IFERROR(INDEX(Terms_Contrib,MATCH(AD14,Terms_Key,0)),0) | AF14: =IF(M14="",AF$8&"|MISSING",AF$8&"|"&TEXT(M14,INDEX(Fmt_Str,MATCH(AF$8,Fmt_LCT,0)))) | AG14: =IFERROR(INDEX(Terms_Contrib,MATCH(AF14,Terms_Key,0)),0) | AH14: =IF(AND(G14="clay",ISNUMBER(N14)),N14,0) | AI14: =INDEX(Terms_Contrib,MATCH(AI$8,Terms_Key,0))*AH14 | AJ14: =IF(AND(IF(I14="",99,I14)>=3,ISNUMBER(O14)),O14/1000,0) | AK14: =INDEX(Terms_Contrib,MATCH(AK$8,Terms_Key,0))*AJ14 | AL14: =INDEX(Terms_Contrib,MATCH(AL$8,Terms_Key,0)) | AM14: =INDEX(Terms_Contrib,MATCH(AM$8,Terms_Key,0)) | AN14: =LN(F14) | AO14: =INDEX(Terms_Contrib,MATCH(AO$8,Terms_Key,0)) | AP14: =U14+W14+Y14+AA14+AC14+AE14+AG14+AI14+AK14+AL14+AM14+AN14+AO14 | AQ14: =EXP(AP14) | AR14: =INDEX(Py_Large,MATCH($B14,Py_ID,0)) | AS14: =ABS(AQ14/AR14-1) | AT14: =ISNA(MATCH(T14,Terms_Key,0))+ISNA(MATCH(V14,Terms_Key,0))+ISNA(MATCH(X14,Terms_Key,0))+ISNA(MATCH(Z14,Terms_Key,0))+ISNA(MATCH(AB14,Terms_Key,0))+ISNA(MATCH(AD14,Terms_Key,0))+ISNA(MATCH(AF14,Terms_Key,0))+ISNA(MATCH(AI$8,Terms_Key,0))+ISNA(MATCH(AK$8,Terms_Key,0))+ISNA(MATCH(AL$8,Terms_Key,0))+ISNA(MATCH(AM$8,Terms_Key,0))+ISNA(MATCH(AO$8,Terms_Key,0))
B15: ='Int. Inputs'!$B$28 | C15: =IF(ISBLANK(INDEX(Pol_Data,MATCH($B15,Pol_ID,0),MATCH("new_business",Pol_Head,0))),"",INDEX(Pol_Data,MATCH($B15,Pol_ID,0),MATCH("new_business",Pol_Head,0))) | D15: =IF(ISBLANK(INDEX(Pol_Data,MATCH($B15,Pol_ID,0),MATCH("period_start",Pol_Head,0))),"",INDEX(Pol_Data,MATCH($B15,Pol_ID,0),MATCH("period_start",Pol_Head,0))) | E15: =IF(ISBLANK(INDEX(Pol_Data,MATCH($B15,Pol_ID,0),MATCH("period_end",Pol_Head,0))),"",INDEX(Pol_Data,MATCH($B15,Pol_ID,0),MATCH("period_end",Pol_Head,0))) | F15: =(E15-D15+1)/365 | G15: =IF(ISBLANK(INDEX(Pol_Data,MATCH($B15,Pol_ID,0),MATCH("soil_type",Pol_Head,0))),"",INDEX(Pol_Data,MATCH($B15,Pol_ID,0),MATCH("soil_type",Pol_Head,0))) | H15: =IF(ISBLANK(INDEX(Pol_Data,MATCH($B15,Pol_ID,0),MATCH("construction_type",Pol_Head,0))),"",INDEX(Pol_Data,MATCH($B15,Pol_ID,0),MATCH("construction_type",Pol_Head,0))) | I15: =IF(ISBLANK(INDEX(Pol_Data,MATCH($B15,Pol_ID,0),MATCH("flood_zone",Pol_Head,0))),"",INDEX(Pol_Data,MATCH($B15,Pol_ID,0),MATCH("flood_zone",Pol_Head,0))) | J15: =IF(ISBLANK(INDEX(Pol_Data,MATCH($B15,Pol_ID,0),MATCH("sum_insured",Pol_Head,0))),"",INDEX(Pol_Data,MATCH($B15,Pol_ID,0),MATCH("sum_insured",Pol_Head,0))) | K15: =IF(ISBLANK(INDEX(Pol_Data,MATCH($B15,Pol_ID,0),MATCH("elevation_m",Pol_Head,0))),"",INDEX(Pol_Data,MATCH($B15,Pol_ID,0),MATCH("elevation_m",Pol_Head,0))) | L15: =IF(ISBLANK(INDEX(Pol_Data,MATCH($B15,Pol_ID,0),MATCH("year_built",Pol_Head,0))),"",INDEX(Pol_Data,MATCH($B15,Pol_ID,0),MATCH("year_built",Pol_Head,0))) | M15: =IF(ISBLANK(INDEX(Pol_Data,MATCH($B15,Pol_ID,0),MATCH("distance_to_river_km",Pol_Head,0))),"",INDEX(Pol_Data,MATCH($B15,Pol_ID,0),MATCH("distance_to_river_km",Pol_Head,0))) | N15: =IF(ISBLANK(INDEX(Pol_Data,MATCH($B15,Pol_ID,0),MATCH("dry_summer_index",Pol_Head,0))),"",INDEX(Pol_Data,MATCH($B15,Pol_ID,0),MATCH("dry_summer_index",Pol_Head,0))) | O15: =IF(ISBLANK(INDEX(Pol_Data,MATCH($B15,Pol_ID,0),MATCH("rainfall_mm",Pol_Head,0))),"",INDEX(Pol_Data,MATCH($B15,Pol_ID,0),MATCH("rainfall_mm",Pol_Head,0))) | P15: =IF(ISBLANK(INDEX(Pol_Data,MATCH($B15,Pol_ID,0),MATCH("energy_rating",Pol_Head,0))),"",INDEX(Pol_Data,MATCH($B15,Pol_ID,0),MATCH("energy_rating",Pol_Head,0))) | Q15: =IF(J15="","",IF(J15>=SI_Thr_Bld,J15/SI_Div,J15)) | R15: =IF(L15=1900,INDEX(YB_Fill,MATCH(IF(P15="","missing",P15),YB_Rating,0)),L15) | S15: =IF(H15="","",INDEX(Con_Model,MATCH(H15,Con_Raw,0))) | T15: =IFERROR(INDEX(Remap_To,MATCH(T$8&"|"&IF(G15="","MISSING",G15&""),Remap_Key,0)),T$8&"|"&IF(G15="","MISSING",G15&"")) | U15: =IFERROR(INDEX(Terms_Contrib,MATCH(T15,Terms_Key,0)),0) | V15: =IFERROR(INDEX(Remap_To,MATCH(V$8&"|"&IF(S15="","MISSING",S15&""),Remap_Key,0)),V$8&"|"&IF(S15="","MISSING",S15&"")) | W15: =IFERROR(INDEX(Terms_Contrib,MATCH(V15,Terms_Key,0)),0) | X15: =IF(I15="",X$8&"|MISSING",X$8&"|q"&TEXT(COUNTIFS(Terms_LCT,X$8,Terms_Kind,"band",Terms_Lower,"<"&I15)-1,"00")) | Y15: =IFERROR(INDEX(Terms_Contrib,MATCH(X15,Terms_Key,0)),0) | Z15: =IF(Q15="",Z$8&"|MISSING",Z$8&"|"&TEXT(Q15,INDEX(Fmt_Str,MATCH(Z$8,Fmt_LCT,0)))) | AA15: =IFERROR(INDEX(Terms_Contrib,MATCH(Z15,Terms_Key,0)),0) | AB15: =IF(K15="",AB$8&"|MISSING",AB$8&"|"&TEXT(K15,INDEX(Fmt_Str,MATCH(AB$8,Fmt_LCT,0)))) | AC15: =IFERROR(INDEX(Terms_Contrib,MATCH(AB15,Terms_Key,0)),0) | AD15: =IF(R15="",AD$8&"|MISSING",AD$8&"|"&TEXT(R15,INDEX(Fmt_Str,MATCH(AD$8,Fmt_LCT,0)))) | AE15: =IFERROR(INDEX(Terms_Contrib,MATCH(AD15,Terms_Key,0)),0) | AF15: =IF(M15="",AF$8&"|MISSING",AF$8&"|"&TEXT(M15,INDEX(Fmt_Str,MATCH(AF$8,Fmt_LCT,0)))) | AG15: =IFERROR(INDEX(Terms_Contrib,MATCH(AF15,Terms_Key,0)),0) | AH15: =IF(AND(G15="clay",ISNUMBER(N15)),N15,0) | AI15: =INDEX(Terms_Contrib,MATCH(AI$8,Terms_Key,0))*AH15 | AJ15: =IF(AND(IF(I15="",99,I15)>=3,ISNUMBER(O15)),O15/1000,0) | AK15: =INDEX(Terms_Contrib,MATCH(AK$8,Terms_Key,0))*AJ15 | AL15: =INDEX(Terms_Contrib,MATCH(AL$8,Terms_Key,0)) | AM15: =INDEX(Terms_Contrib,MATCH(AM$8,Terms_Key,0)) | AN15: =LN(F15) | AO15: =INDEX(Terms_Contrib,MATCH(AO$8,Terms_Key,0)) | AP15: =U15+W15+Y15+AA15+AC15+AE15+AG15+AI15+AK15+AL15+AM15+AN15+AO15 | AQ15: =EXP(AP15) | AR15: =INDEX(Py_Large,MATCH($B15,Py_ID,0)) | AS15: =ABS(AQ15/AR15-1) | AT15: =ISNA(MATCH(T15,Terms_Key,0))+ISNA(MATCH(V15,Terms_Key,0))+ISNA(MATCH(X15,Terms_Key,0))+ISNA(MATCH(Z15,Terms_Key,0))+ISNA(MATCH(AB15,Terms_Key,0))+ISNA(MATCH(AD15,Terms_Key,0))+ISNA(MATCH(AF15,Terms_Key,0))+ISNA(MATCH(AI$8,Terms_Key,0))+ISNA(MATCH(AK$8,Terms_Key,0))+ISNA(MATCH(AL$8,Terms_Key,0))+ISNA(MATCH(AM$8,Terms_Key,0))+ISNA(MATCH(AO$8,Terms_Key,0))
B16: ='Int. Inputs'!$B$29 | C16: =IF(ISBLANK(INDEX(Pol_Data,MATCH($B16,Pol_ID,0),MATCH("new_business",Pol_Head,0))),"",INDEX(Pol_Data,MATCH($B16,Pol_ID,0),MATCH("new_business",Pol_Head,0))) | D16: =IF(ISBLANK(INDEX(Pol_Data,MATCH($B16,Pol_ID,0),MATCH("period_start",Pol_Head,0))),"",INDEX(Pol_Data,MATCH($B16,Pol_ID,0),MATCH("period_start",Pol_Head,0))) | E16: =IF(ISBLANK(INDEX(Pol_Data,MATCH($B16,Pol_ID,0),MATCH("period_end",Pol_Head,0))),"",INDEX(Pol_Data,MATCH($B16,Pol_ID,0),MATCH("period_end",Pol_Head,0))) | F16: =(E16-D16+1)/365 | G16: =IF(ISBLANK(INDEX(Pol_Data,MATCH($B16,Pol_ID,0),MATCH("soil_type",Pol_Head,0))),"",INDEX(Pol_Data,MATCH($B16,Pol_ID,0),MATCH("soil_type",Pol_Head,0))) | H16: =IF(ISBLANK(INDEX(Pol_Data,MATCH($B16,Pol_ID,0),MATCH("construction_type",Pol_Head,0))),"",INDEX(Pol_Data,MATCH($B16,Pol_ID,0),MATCH("construction_type",Pol_Head,0))) | I16: =IF(ISBLANK(INDEX(Pol_Data,MATCH($B16,Pol_ID,0),MATCH("flood_zone",Pol_Head,0))),"",INDEX(Pol_Data,MATCH($B16,Pol_ID,0),MATCH("flood_zone",Pol_Head,0))) | J16: =IF(ISBLANK(INDEX(Pol_Data,MATCH($B16,Pol_ID,0),MATCH("sum_insured",Pol_Head,0))),"",INDEX(Pol_Data,MATCH($B16,Pol_ID,0),MATCH("sum_insured",Pol_Head,0))) | K16: =IF(ISBLANK(INDEX(Pol_Data,MATCH($B16,Pol_ID,0),MATCH("elevation_m",Pol_Head,0))),"",INDEX(Pol_Data,MATCH($B16,Pol_ID,0),MATCH("elevation_m",Pol_Head,0))) | L16: =IF(ISBLANK(INDEX(Pol_Data,MATCH($B16,Pol_ID,0),MATCH("year_built",Pol_Head,0))),"",INDEX(Pol_Data,MATCH($B16,Pol_ID,0),MATCH("year_built",Pol_Head,0))) | M16: =IF(ISBLANK(INDEX(Pol_Data,MATCH($B16,Pol_ID,0),MATCH("distance_to_river_km",Pol_Head,0))),"",INDEX(Pol_Data,MATCH($B16,Pol_ID,0),MATCH("distance_to_river_km",Pol_Head,0))) | N16: =IF(ISBLANK(INDEX(Pol_Data,MATCH($B16,Pol_ID,0),MATCH("dry_summer_index",Pol_Head,0))),"",INDEX(Pol_Data,MATCH($B16,Pol_ID,0),MATCH("dry_summer_index",Pol_Head,0))) | O16: =IF(ISBLANK(INDEX(Pol_Data,MATCH($B16,Pol_ID,0),MATCH("rainfall_mm",Pol_Head,0))),"",INDEX(Pol_Data,MATCH($B16,Pol_ID,0),MATCH("rainfall_mm",Pol_Head,0))) | P16: =IF(ISBLANK(INDEX(Pol_Data,MATCH($B16,Pol_ID,0),MATCH("energy_rating",Pol_Head,0))),"",INDEX(Pol_Data,MATCH($B16,Pol_ID,0),MATCH("energy_rating",Pol_Head,0))) | Q16: =IF(J16="","",IF(J16>=SI_Thr_Bld,J16/SI_Div,J16)) | R16: =IF(L16=1900,INDEX(YB_Fill,MATCH(IF(P16="","missing",P16),YB_Rating,0)),L16) | S16: =IF(H16="","",INDEX(Con_Model,MATCH(H16,Con_Raw,0))) | T16: =IFERROR(INDEX(Remap_To,MATCH(T$8&"|"&IF(G16="","MISSING",G16&""),Remap_Key,0)),T$8&"|"&IF(G16="","MISSING",G16&"")) | U16: =IFERROR(INDEX(Terms_Contrib,MATCH(T16,Terms_Key,0)),0) | V16: =IFERROR(INDEX(Remap_To,MATCH(V$8&"|"&IF(S16="","MISSING",S16&""),Remap_Key,0)),V$8&"|"&IF(S16="","MISSING",S16&"")) | W16: =IFERROR(INDEX(Terms_Contrib,MATCH(V16,Terms_Key,0)),0) | X16: =IF(I16="",X$8&"|MISSING",X$8&"|q"&TEXT(COUNTIFS(Terms_LCT,X$8,Terms_Kind,"band",Terms_Lower,"<"&I16)-1,"00")) | Y16: =IFERROR(INDEX(Terms_Contrib,MATCH(X16,Terms_Key,0)),0) | Z16: =IF(Q16="",Z$8&"|MISSING",Z$8&"|"&TEXT(Q16,INDEX(Fmt_Str,MATCH(Z$8,Fmt_LCT,0)))) | AA16: =IFERROR(INDEX(Terms_Contrib,MATCH(Z16,Terms_Key,0)),0) | AB16: =IF(K16="",AB$8&"|MISSING",AB$8&"|"&TEXT(K16,INDEX(Fmt_Str,MATCH(AB$8,Fmt_LCT,0)))) | AC16: =IFERROR(INDEX(Terms_Contrib,MATCH(AB16,Terms_Key,0)),0) | AD16: =IF(R16="",AD$8&"|MISSING",AD$8&"|"&TEXT(R16,INDEX(Fmt_Str,MATCH(AD$8,Fmt_LCT,0)))) | AE16: =IFERROR(INDEX(Terms_Contrib,MATCH(AD16,Terms_Key,0)),0) | AF16: =IF(M16="",AF$8&"|MISSING",AF$8&"|"&TEXT(M16,INDEX(Fmt_Str,MATCH(AF$8,Fmt_LCT,0)))) | AG16: =IFERROR(INDEX(Terms_Contrib,MATCH(AF16,Terms_Key,0)),0) | AH16: =IF(AND(G16="clay",ISNUMBER(N16)),N16,0) | AI16: =INDEX(Terms_Contrib,MATCH(AI$8,Terms_Key,0))*AH16 | AJ16: =IF(AND(IF(I16="",99,I16)>=3,ISNUMBER(O16)),O16/1000,0) | AK16: =INDEX(Terms_Contrib,MATCH(AK$8,Terms_Key,0))*AJ16 | AL16: =INDEX(Terms_Contrib,MATCH(AL$8,Terms_Key,0)) | AM16: =INDEX(Terms_Contrib,MATCH(AM$8,Terms_Key,0)) | AN16: =LN(F16) | AO16: =INDEX(Terms_Contrib,MATCH(AO$8,Terms_Key,0)) | AP16: =U16+W16+Y16+AA16+AC16+AE16+AG16+AI16+AK16+AL16+AM16+AN16+AO16 | AQ16: =EXP(AP16) | AR16: =INDEX(Py_Large,MATCH($B16,Py_ID,0)) | AS16: =ABS(AQ16/AR16-1) | AT16: =ISNA(MATCH(T16,Terms_Key,0))+ISNA(MATCH(V16,Terms_Key,0))+ISNA(MATCH(X16,Terms_Key,0))+ISNA(MATCH(Z16,Terms_Key,0))+ISNA(MATCH(AB16,Terms_Key,0))+ISNA(MATCH(AD16,Terms_Key,0))+ISNA(MATCH(AF16,Terms_Key,0))+ISNA(MATCH(AI$8,Terms_Key,0))+ISNA(MATCH(AK$8,Terms_Key,0))+ISNA(MATCH(AL$8,Terms_Key,0))+ISNA(MATCH(AM$8,Terms_Key,0))+ISNA(MATCH(AO$8,Terms_Key,0))

Sheet Rating Buildings Trees
B2: Rating Buildings Trees: small claims from the 193 trees, then small + large, then the level step
B3: Left: each policy's 52 inputs as the trees see them (category inputs become codes). Middle: the walk, three steps per tree to a leaf. Right: the prediction. Excel adds the leaves in double precision, XGBoost in single, so small claims differ from XGBoost by up to about 1e-5 relative (Ger's export README).
CJ4: 0 = pass | CL4: 0 = pass | CM4: 0 = pass | CN4: 0 = pass
B5: Checks sit above their own columns at the right. | CJ5: =COUNTIF(CJ10:CJ16,">1E-5") | CL5: =COUNTIF(CL10:CL16,">1E-5") | CM5: =SUM(CM10:CM16) | CN5: =SUM(CN10:CN16)
B7: Feature | E7: Policy 1 | H7: Policy 2 | K7: Policy 3 | N7: Policy 4 | Q7: Policy 5 | T7: Policy 6 | W7: Policy 7 | AA7: Tree | AB7: Policy 1: walk | AI7: Policy 2: walk | AP7: Policy 3: walk | AW7: Policy 4: walk | BD7: Policy 5: walk | BK7: Policy 6: walk | BR7: Policy 7: walk | BZ7: Prediction and checks
E8: ='Rating Buildings'!$B$10 | H8: ='Rating Buildings'!$B$11 | K8: ='Rating Buildings'!$B$12 | N8: ='Rating Buildings'!$B$13 | Q8: ='Rating Buildings'!$B$14 | T8: ='Rating Buildings'!$B$15 | W8: ='Rating Buildings'!$B$16 | AB8: =E$8 | AI8: =H$8 | AP8: =K$8 | AW8: =N$8 | BD8: =Q$8 | BK8: =T$8 | BR8: =W$8
B9: Position | C9: Feature | D9: Type | E9: Input | F9: Level key | G9: x (value or code) | H9: Input | I9: Level key | J9: x (value or code) | K9: Input | L9: Level key | M9: x (value or code) | N9: Input | O9: Level key | P9: x (value or code) | Q9: Input | R9: Level key | S9: x (value or code) | T9: Input | U9: Level key | V9: x (value or code) | W9: Input | X9: Level key | Y9: x (value or code) | AA9: Tree | AB9: Row of node 0 | AC9: Node at depth 1 | AD9: Row | AE9: Node at depth 2 | AF9: Row | AG9: Node at depth 3 | AH9: Leaf value | AI9: Row of node 0 | AJ9: Node at depth 1 | AK9: Row | AL9: Node at depth 2 | AM9: Row | AN9: Node at depth 3 | AO9: Leaf value | AP9: Row of node 0 | AQ9: Node at depth 1 | AR9: Row | AS9: Node at depth 2 | AT9: Row | AU9: Node at depth 3 | AV9: Leaf value | AW9: Row of node 0 | AX9: Node at depth 1 | AY9: Row | AZ9: Node at depth 2 | BA9: Row | BB9: Node at depth 3 | BC9: Leaf value | BD9: Row of node 0 | BE9: Node at depth 1 | BF9: Row | BG9: Node at depth 2 | BH9: Row | BI9: Node at depth 3 | BJ9: Leaf value | BK9: Row of node 0 | BL9: Node at depth 1 | BM9: Row | BN9: Node at depth 2 | BO9: Row | BP9: Node at depth 3 | BQ9: Leaf value | BR9: Row of node 0 | BS9: Node at depth 1 | BT9: Row | BU9: Node at depth 2 | BV9: Row | BW9: Node at depth 3 | BX9: Leaf value | BZ9: Policy row | CA9: Exposure (model) | CB9: Sum of leaves | CC9: Margin (log) | CD9: Small claim (CU) | CE9: Large claim (CU) | CF9: As is (CU) | CG9: Level step | CH9: Final risk premium (CU) | CI9: XGBoost small (Python) | CJ9: Small: relative difference | CK9: Python final | CL9: Final: relative difference | CM9: Category inputs without a code | CN9: Trees not ending in a leaf
B10: 0 | C10: sum_insured | D10: numeric | E10: ='Rating Buildings'!$Q$10 | G10: =IF(E10="","",E10) | H10: ='Rating Buildings'!$Q$11 | J10: =IF(H10="","",H10) | K10: ='Rating Buildings'!$Q$12 | M10: =IF(K10="","",K10) | N10: ='Rating Buildings'!$Q$13 | P10: =IF(N10="","",N10) | Q10: ='Rating Buildings'!$Q$14 | S10: =IF(Q10="","",Q10) | T10: ='Rating Buildings'!$Q$15 | V10: =IF(T10="","",T10) | W10: ='Rating Buildings'!$Q$16 | Y10: =IF(W10="","",W10) | AA10: 0 | AB10: =MATCH($AA10&"|0",Node_Key,0) | AC10: =IF(INDEX(Node_Kind,AB10)="leaf",0,IF(INDEX($G$10:$G$61,INDEX(Node_Pos,AB10)+1)="",IF(INDEX(Node_Miss,AB10)="left",INDEX(Node_Left,AB10),INDEX(Node_Right,AB10)),IF(INDEX(Node_Kind,AB10)="split",IF(INDEX($G$10:$G$61,INDEX(Node_Pos,AB10)+1)<INDEX(Node_Thr,AB10),INDEX(Node_Left,AB10),INDEX(Node_Right,AB10)),IF(ISNUMBER(SEARCH(";"&INDEX($G$10:$G$61,INDEX(Node_Pos,AB10)+1)&";",";"&INDEX(Node_RCodes,AB10)&";")),INDEX(Node_Right,AB10),INDEX(Node_Left,AB10))))) | AD10: =MATCH($AA10&"|"&AC10,Node_Key,0) | AE10: =IF(INDEX(Node_Kind,AD10)="leaf",AC10,IF(INDEX($G$10:$G$61,INDEX(Node_Pos,AD10)+1)="",IF(INDEX(Node_Miss,AD10)="left",INDEX(Node_Left,AD10),INDEX(Node_Right,AD10)),IF(INDEX(Node_Kind,AD10)="split",IF(INDEX($G$10:$G$61,INDEX(Node_Pos,AD10)+1)<INDEX(Node_Thr,AD10),INDEX(Node_Left,AD10),INDEX(Node_Right,AD10)),IF(ISNUMBER(SEARCH(";"&INDEX($G$10:$G$61,INDEX(Node_Pos,AD10)+1)&";",";"&INDEX(Node_RCodes,AD10)&";")),INDEX(Node_Right,AD10),INDEX(Node_Left,AD10))))) | AF10: =MATCH($AA10&"|"&AE10,Node_Key,0) | AG10: =IF(INDEX(Node_Kind,AF10)="leaf",AE10,IF(INDEX($G$10:$G$61,INDEX(Node_Pos,AF10)+1)="",IF(INDEX(Node_Miss,AF10)="left",INDEX(Node_Left,AF10),INDEX(Node_Right,AF10)),IF(INDEX(Node_Kind,AF10)="split",IF(INDEX($G$10:$G$61,INDEX(Node_Pos,AF10)+1)<INDEX(Node_Thr,AF10),INDEX(Node_Left,AF10),INDEX(Node_Right,AF10)),IF(ISNUMBER(SEARCH(";"&INDEX($G$10:$G$61,INDEX(Node_Pos,AF10)+1)&";",";"&INDEX(Node_RCodes,AF10)&";")),INDEX(Node_Right,AF10),INDEX(Node_Left,AF10))))) | AH10: =IF(INDEX(Node_Kind,MATCH($AA10&"|"&AG10,Node_Key,0))="leaf",INDEX(Node_Leaf,MATCH($AA10&"|"&AG10,Node_Key,0)),"not a leaf") | AI10: =MATCH($AA10&"|0",Node_Key,0) | AJ10: =IF(INDEX(Node_Kind,AI10)="leaf",0,IF(INDEX($J$10:$J$61,INDEX(Node_Pos,AI10)+1)="",IF(INDEX(Node_Miss,AI10)="left",INDEX(Node_Left,AI10),INDEX(Node_Right,AI10)),IF(INDEX(Node_Kind,AI10)="split",IF(INDEX($J$10:$J$61,INDEX(Node_Pos,AI10)+1)<INDEX(Node_Thr,AI10),INDEX(Node_Left,AI10),INDEX(Node_Right,AI10)),IF(ISNUMBER(SEARCH(";"&INDEX($J$10:$J$61,INDEX(Node_Pos,AI10)+1)&";",";"&INDEX(Node_RCodes,AI10)&";")),INDEX(Node_Right,AI10),INDEX(Node_Left,AI10))))) | AK10: =MATCH($AA10&"|"&AJ10,Node_Key,0) | AL10: =IF(INDEX(Node_Kind,AK10)="leaf",AJ10,IF(INDEX($J$10:$J$61,INDEX(Node_Pos,AK10)+1)="",IF(INDEX(Node_Miss,AK10)="left",INDEX(Node_Left,AK10),INDEX(Node_Right,AK10)),IF(INDEX(Node_Kind,AK10)="split",IF(INDEX($J$10:$J$61,INDEX(Node_Pos,AK10)+1)<INDEX(Node_Thr,AK10),INDEX(Node_Left,AK10),INDEX(Node_Right,AK10)),IF(ISNUMBER(SEARCH(";"&INDEX($J$10:$J$61,INDEX(Node_Pos,AK10)+1)&";",";"&INDEX(Node_RCodes,AK10)&";")),INDEX(Node_Right,AK10),INDEX(Node_Left,AK10))))) | AM10: =MATCH($AA10&"|"&AL10,Node_Key,0) | AN10: =IF(INDEX(Node_Kind,AM10)="leaf",AL10,IF(INDEX($J$10:$J$61,INDEX(Node_Pos,AM10)+1)="",IF(INDEX(Node_Miss,AM10)="left",INDEX(Node_Left,AM10),INDEX(Node_Right,AM10)),IF(INDEX(Node_Kind,AM10)="split",IF(INDEX($J$10:$J$61,INDEX(Node_Pos,AM10)+1)<INDEX(Node_Thr,AM10),INDEX(Node_Left,AM10),INDEX(Node_Right,AM10)),IF(ISNUMBER(SEARCH(";"&INDEX($J$10:$J$61,INDEX(Node_Pos,AM10)+1)&";",";"&INDEX(Node_RCodes,AM10)&";")),INDEX(Node_Right,AM10),INDEX(Node_Left,AM10))))) | AO10: =IF(INDEX(Node_Kind,MATCH($AA10&"|"&AN10,Node_Key,0))="leaf",INDEX(Node_Leaf,MATCH($AA10&"|"&AN10,Node_Key,0)),"not a leaf") | AP10: =MATCH($AA10&"|0",Node_Key,0) | AQ10: =IF(INDEX(Node_Kind,AP10)="leaf",0,IF(INDEX($M$10:$M$61,INDEX(Node_Pos,AP10)+1)="",IF(INDEX(Node_Miss,AP10)="left",INDEX(Node_Left,AP10),INDEX(Node_Right,AP10)),IF(INDEX(Node_Kind,AP10)="split",IF(INDEX($M$10:$M$61,INDEX(Node_Pos,AP10)+1)<INDEX(Node_Thr,AP10),INDEX(Node_Left,AP10),INDEX(Node_Right,AP10)),IF(ISNUMBER(SEARCH(";"&INDEX($M$10:$M$61,INDEX(Node_Pos,AP10)+1)&";",";"&INDEX(Node_RCodes,AP10)&";")),INDEX(Node_Right,AP10),INDEX(Node_Left,AP10))))) | AR10: =MATCH($AA10&"|"&AQ10,Node_Key,0) | AS10: =IF(INDEX(Node_Kind,AR10)="leaf",AQ10,IF(INDEX($M$10:$M$61,INDEX(Node_Pos,AR10)+1)="",IF(INDEX(Node_Miss,AR10)="left",INDEX(Node_Left,AR10),INDEX(Node_Right,AR10)),IF(INDEX(Node_Kind,AR10)="split",IF(INDEX($M$10:$M$61,INDEX(Node_Pos,AR10)+1)<INDEX(Node_Thr,AR10),INDEX(Node_Left,AR10),INDEX(Node_Right,AR10)),IF(ISNUMBER(SEARCH(";"&INDEX($M$10:$M$61,INDEX(Node_Pos,AR10)+1)&";",";"&INDEX(Node_RCodes,AR10)&";")),INDEX(Node_Right,AR10),INDEX(Node_Left,AR10))))) | AT10: =MATCH($AA10&"|"&AS10,Node_Key,0) | AU10: =IF(INDEX(Node_Kind,AT10)="leaf",AS10,IF(INDEX($M$10:$M$61,INDEX(Node_Pos,AT10)+1)="",IF(INDEX(Node_Miss,AT10)="left",INDEX(Node_Left,AT10),INDEX(Node_Right,AT10)),IF(INDEX(Node_Kind,AT10)="split",IF(INDEX($M$10:$M$61,INDEX(Node_Pos,AT10)+1)<INDEX(Node_Thr,AT10),INDEX(Node_Left,AT10),INDEX(Node_Right,AT10)),IF(ISNUMBER(SEARCH(";"&INDEX($M$10:$M$61,INDEX(Node_Pos,AT10)+1)&";",";"&INDEX(Node_RCodes,AT10)&";")),INDEX(Node_Right,AT10),INDEX(Node_Left,AT10))))) | AV10: =IF(INDEX(Node_Kind,MATCH($AA10&"|"&AU10,Node_Key,0))="leaf",INDEX(Node_Leaf,MATCH($AA10&"|"&AU10,Node_Key,0)),"not a leaf") | AW10: =MATCH($AA10&"|0",Node_Key,0) | AX10: =IF(INDEX(Node_Kind,AW10)="leaf",0,IF(INDEX($P$10:$P$61,INDEX(Node_Pos,AW10)+1)="",IF(INDEX(Node_Miss,AW10)="left",INDEX(Node_Left,AW10),INDEX(Node_Right,AW10)),IF(INDEX(Node_Kind,AW10)="split",IF(INDEX($P$10:$P$61,INDEX(Node_Pos,AW10)+1)<INDEX(Node_Thr,AW10),INDEX(Node_Left,AW10),INDEX(Node_Right,AW10)),IF(ISNUMBER(SEARCH(";"&INDEX($P$10:$P$61,INDEX(Node_Pos,AW10)+1)&";",";"&INDEX(Node_RCodes,AW10)&";")),INDEX(Node_Right,AW10),INDEX(Node_Left,AW10))))) | AY10: =MATCH($AA10&"|"&AX10,Node_Key,0) | AZ10: =IF(INDEX(Node_Kind,AY10)="leaf",AX10,IF(INDEX($P$10:$P$61,INDEX(Node_Pos,AY10)+1)="",IF(INDEX(Node_Miss,AY10)="left",INDEX(Node_Left,AY10),INDEX(Node_Right,AY10)),IF(INDEX(Node_Kind,AY10)="split",IF(INDEX($P$10:$P$61,INDEX(Node_Pos,AY10)+1)<INDEX(Node_Thr,AY10),INDEX(Node_Left,AY10),INDEX(Node_Right,AY10)),IF(ISNUMBER(SEARCH(";"&INDEX($P$10:$P$61,INDEX(Node_Pos,AY10)+1)&";",";"&INDEX(Node_RCodes,AY10)&";")),INDEX(Node_Right,AY10),INDEX(Node_Left,AY10))))) | BA10: =MATCH($AA10&"|"&AZ10,Node_Key,0) | BB10: =IF(INDEX(Node_Kind,BA10)="leaf",AZ10,IF(INDEX($P$10:$P$61,INDEX(Node_Pos,BA10)+1)="",IF(INDEX(Node_Miss,BA10)="left",INDEX(Node_Left,BA10),INDEX(Node_Right,BA10)),IF(INDEX(Node_Kind,BA10)="split",IF(INDEX($P$10:$P$61,INDEX(Node_Pos,BA10)+1)<INDEX(Node_Thr,BA10),INDEX(Node_Left,BA10),INDEX(Node_Right,BA10)),IF(ISNUMBER(SEARCH(";"&INDEX($P$10:$P$61,INDEX(Node_Pos,BA10)+1)&";",";"&INDEX(Node_RCodes,BA10)&";")),INDEX(Node_Right,BA10),INDEX(Node_Left,BA10))))) | BC10: =IF(INDEX(Node_Kind,MATCH($AA10&"|"&BB10,Node_Key,0))="leaf",INDEX(Node_Leaf,MATCH($AA10&"|"&BB10,Node_Key,0)),"not a leaf") | BD10: =MATCH($AA10&"|0",Node_Key,0) | BE10: =IF(INDEX(Node_Kind,BD10)="leaf",0,IF(INDEX($S$10:$S$61,INDEX(Node_Pos,BD10)+1)="",IF(INDEX(Node_Miss,BD10)="left",INDEX(Node_Left,BD10),INDEX(Node_Right,BD10)),IF(INDEX(Node_Kind,BD10)="split",IF(INDEX($S$10:$S$61,INDEX(Node_Pos,BD10)+1)<INDEX(Node_Thr,BD10),INDEX(Node_Left,BD10),INDEX(Node_Right,BD10)),IF(ISNUMBER(SEARCH(";"&INDEX($S$10:$S$61,INDEX(Node_Pos,BD10)+1)&";",";"&INDEX(Node_RCodes,BD10)&";")),INDEX(Node_Right,BD10),INDEX(Node_Left,BD10))))) | BF10: =MATCH($AA10&"|"&BE10,Node_Key,0) | BG10: =IF(INDEX(Node_Kind,BF10)="leaf",BE10,IF(INDEX($S$10:$S$61,INDEX(Node_Pos,BF10)+1)="",IF(INDEX(Node_Miss,BF10)="left",INDEX(Node_Left,BF10),INDEX(Node_Right,BF10)),IF(INDEX(Node_Kind,BF10)="split",IF(INDEX($S$10:$S$61,INDEX(Node_Pos,BF10)+1)<INDEX(Node_Thr,BF10),INDEX(Node_Left,BF10),INDEX(Node_Right,BF10)),IF(ISNUMBER(SEARCH(";"&INDEX($S$10:$S$61,INDEX(Node_Pos,BF10)+1)&";",";"&INDEX(Node_RCodes,BF10)&";")),INDEX(Node_Right,BF10),INDEX(Node_Left,BF10))))) | BH10: =MATCH($AA10&"|"&BG10,Node_Key,0) | BI10: =IF(INDEX(Node_Kind,BH10)="leaf",BG10,IF(INDEX($S$10:$S$61,INDEX(Node_Pos,BH10)+1)="",IF(INDEX(Node_Miss,BH10)="left",INDEX(Node_Left,BH10),INDEX(Node_Right,BH10)),IF(INDEX(Node_Kind,BH10)="split",IF(INDEX($S$10:$S$61,INDEX(Node_Pos,BH10)+1)<INDEX(Node_Thr,BH10),INDEX(Node_Left,BH10),INDEX(Node_Right,BH10)),IF(ISNUMBER(SEARCH(";"&INDEX($S$10:$S$61,INDEX(Node_Pos,BH10)+1)&";",";"&INDEX(Node_RCodes,BH10)&";")),INDEX(Node_Right,BH10),INDEX(Node_Left,BH10))))) | BJ10: =IF(INDEX(Node_Kind,MATCH($AA10&"|"&BI10,Node_Key,0))="leaf",INDEX(Node_Leaf,MATCH($AA10&"|"&BI10,Node_Key,0)),"not a leaf") | BK10: =MATCH($AA10&"|0",Node_Key,0) | BL10: =IF(INDEX(Node_Kind,BK10)="leaf",0,IF(INDEX($V$10:$V$61,INDEX(Node_Pos,BK10)+1)="",IF(INDEX(Node_Miss,BK10)="left",INDEX(Node_Left,BK10),INDEX(Node_Right,BK10)),IF(INDEX(Node_Kind,BK10)="split",IF(INDEX($V$10:$V$61,INDEX(Node_Pos,BK10)+1)<INDEX(Node_Thr,BK10),INDEX(Node_Left,BK10),INDEX(Node_Right,BK10)),IF(ISNUMBER(SEARCH(";"&INDEX($V$10:$V$61,INDEX(Node_Pos,BK10)+1)&";",";"&INDEX(Node_RCodes,BK10)&";")),INDEX(Node_Right,BK10),INDEX(Node_Left,BK10))))) | BM10: =MATCH($AA10&"|"&BL10,Node_Key,0) | BN10: =IF(INDEX(Node_Kind,BM10)="leaf",BL10,IF(INDEX($V$10:$V$61,INDEX(Node_Pos,BM10)+1)="",IF(INDEX(Node_Miss,BM10)="left",INDEX(Node_Left,BM10),INDEX(Node_Right,BM10)),IF(INDEX(Node_Kind,BM10)="split",IF(INDEX($V$10:$V$61,INDEX(Node_Pos,BM10)+1)<INDEX(Node_Thr,BM10),INDEX(Node_Left,BM10),INDEX(Node_Right,BM10)),IF(ISNUMBER(SEARCH(";"&INDEX($V$10:$V$61,INDEX(Node_Pos,BM10)+1)&";",";"&INDEX(Node_RCodes,BM10)&";")),INDEX(Node_Right,BM10),INDEX(Node_Left,BM10))))) | BO10: =MATCH($AA10&"|"&BN10,Node_Key,0) | BP10: =IF(INDEX(Node_Kind,BO10)="leaf",BN10,IF(INDEX($V$10:$V$61,INDEX(Node_Pos,BO10)+1)="",IF(INDEX(Node_Miss,BO10)="left",INDEX(Node_Left,BO10),INDEX(Node_Right,BO10)),IF(INDEX(Node_Kind,BO10)="split",IF(INDEX($V$10:$V$61,INDEX(Node_Pos,BO10)+1)<INDEX(Node_Thr,BO10),INDEX(Node_Left,BO10),INDEX(Node_Right,BO10)),IF(ISNUMBER(SEARCH(";"&INDEX($V$10:$V$61,INDEX(Node_Pos,BO10)+1)&";",";"&INDEX(Node_RCodes,BO10)&";")),INDEX(Node_Right,BO10),INDEX(Node_Left,BO10))))) | BQ10: =IF(INDEX(Node_Kind,MATCH($AA10&"|"&BP10,Node_Key,0))="leaf",INDEX(Node_Leaf,MATCH($AA10&"|"&BP10,Node_Key,0)),"not a leaf") | BR10: =MATCH($AA10&"|0",Node_Key,0) | BS10: =IF(INDEX(Node_Kind,BR10)="leaf",0,IF(INDEX($Y$10:$Y$61,INDEX(Node_Pos,BR10)+1)="",IF(INDEX(Node_Miss,BR10)="left",INDEX(Node_Left,BR10),INDEX(Node_Right,BR10)),IF(INDEX(Node_Kind,BR10)="split",IF(INDEX($Y$10:$Y$61,INDEX(Node_Pos,BR10)+1)<INDEX(Node_Thr,BR10),INDEX(Node_Left,BR10),INDEX(Node_Right,BR10)),IF(ISNUMBER(SEARCH(";"&INDEX($Y$10:$Y$61,INDEX(Node_Pos,BR10)+1)&";",";"&INDEX(Node_RCodes,BR10)&";")),INDEX(Node_Right,BR10),INDEX(Node_Left,BR10))))) | BT10: =MATCH($AA10&"|"&BS10,Node_Key,0) | BU10: =IF(INDEX(Node_Kind,BT10)="leaf",BS10,IF(INDEX($Y$10:$Y$61,INDEX(Node_Pos,BT10)+1)="",IF(INDEX(Node_Miss,BT10)="left",INDEX(Node_Left,BT10),INDEX(Node_Right,BT10)),IF(INDEX(Node_Kind,BT10)="split",IF(INDEX($Y$10:$Y$61,INDEX(Node_Pos,BT10)+1)<INDEX(Node_Thr,BT10),INDEX(Node_Left,BT10),INDEX(Node_Right,BT10)),IF(ISNUMBER(SEARCH(";"&INDEX($Y$10:$Y$61,INDEX(Node_Pos,BT10)+1)&";",";"&INDEX(Node_RCodes,BT10)&";")),INDEX(Node_Right,BT10),INDEX(Node_Left,BT10))))) | BV10: =MATCH($AA10&"|"&BU10,Node_Key,0) | BW10: =IF(INDEX(Node_Kind,BV10)="leaf",BU10,IF(INDEX($Y$10:$Y$61,INDEX(Node_Pos,BV10)+1)="",IF(INDEX(Node_Miss,BV10)="left",INDEX(Node_Left,BV10),INDEX(Node_Right,BV10)),IF(INDEX(Node_Kind,BV10)="split",IF(INDEX($Y$10:$Y$61,INDEX(Node_Pos,BV10)+1)<INDEX(Node_Thr,BV10),INDEX(Node_Left,BV10),INDEX(Node_Right,BV10)),IF(ISNUMBER(SEARCH(";"&INDEX($Y$10:$Y$61,INDEX(Node_Pos,BV10)+1)&";",";"&INDEX(Node_RCodes,BV10)&";")),INDEX(Node_Right,BV10),INDEX(Node_Left,BV10))))) | BX10: =IF(INDEX(Node_Kind,MATCH($AA10&"|"&BW10,Node_Key,0))="leaf",INDEX(Node_Leaf,MATCH($AA10&"|"&BW10,Node_Key,0)),"not a leaf") | BZ10: =E$8 | CA10: ='Rating Buildings'!$F$10 | CB10: =SUM($AH$10:$AH$202) | CC10: =LN(CA10)+LN(XGB_Base)+LN(XGB_Trend)+CB10 | CD10: =EXP(CC10) | CE10: ='Rating Buildings'!$AQ$10 | CF10: =CD10+CE10 | CG10: =Lvl_Bld | CH10: =CF10*CG10 | CI10: =INDEX(Py_Small,MATCH(BZ10,Py_ID,0)) | CJ10: =ABS(CD10/CI10-1) | CK10: =INDEX(Py_Final,MATCH(BZ10,Py_ID,0)) | CL10: =ABS(CH10/CK10-1) | CM10: =SUMPRODUCT((F$10:F$61<>"")*(G$10:G$61="")*(RIGHT(F$10:F$61,8)<>"|MISSING")) | CN10: =COUNTIF($AH$10:$AH$202,"not a leaf")
B11: 1 | C11: days_unoccupied | D11: numeric | E11: =IF(ISBLANK(INDEX(Pol_Data,MATCH(E$8,Pol_ID,0),MATCH($C11,Pol_Head,0))),"",INDEX(Pol_Data,MATCH(E$8,Pol_ID,0),MATCH($C11,Pol_Head,0))) | G11: =IF(E11="","",E11) | H11: =IF(ISBLANK(INDEX(Pol_Data,MATCH(H$8,Pol_ID,0),MATCH($C11,Pol_Head,0))),"",INDEX(Pol_Data,MATCH(H$8,Pol_ID,0),MATCH($C11,Pol_Head,0))) | J11: =IF(H11="","",H11) | K11: =IF(ISBLANK(INDEX(Pol_Data,MATCH(K$8,Pol_ID,0),MATCH($C11,Pol_Head,0))),"",INDEX(Pol_Data,MATCH(K$8,Pol_ID,0),MATCH($C11,Pol_Head,0))) | M11: =IF(K11="","",K11) | N11: =IF(ISBLANK(INDEX(Pol_Data,MATCH(N$8,Pol_ID,0),MATCH($C11,Pol_Head,0))),"",INDEX(Pol_Data,MATCH(N$8,Pol_ID,0),MATCH($C11,Pol_Head,0))) | P11: =IF(N11="","",N11) | Q11: =IF(ISBLANK(INDEX(Pol_Data,MATCH(Q$8,Pol_ID,0),MATCH($C11,Pol_Head,0))),"",INDEX(Pol_Data,MATCH(Q$8,Pol_ID,0),MATCH($C11,Pol_Head,0))) | S11: =IF(Q11="","",Q11) | T11: =IF(ISBLANK(INDEX(Pol_Data,MATCH(T$8,Pol_ID,0),MATCH($C11,Pol_Head,0))),"",INDEX(Pol_Data,MATCH(T$8,Pol_ID,0),MATCH($C11,Pol_Head,0))) | V11: =IF(T11="","",T11) | W11: =IF(ISBLANK(INDEX(Pol_Data,MATCH(W$8,Pol_ID,0),MATCH($C11,Pol_Head,0))),"",INDEX(Pol_Data,MATCH(W$8,Pol_ID,0),MATCH($C11,Pol_Head,0))) | Y11: =IF(W11="","",W11) | AA11: 1 | AB11: =MATCH($AA11&"|0",Node_Key,0) | AC11: =IF(INDEX(Node_Kind,AB11)="leaf",0,IF(INDEX($G$10:$G$61,INDEX(Node_Pos,AB11)+1)="",IF(INDEX(Node_Miss,AB11)="left",INDEX(Node_Left,AB11),INDEX(Node_Right,AB11)),IF(INDEX(Node_Kind,AB11)="split",IF(INDEX($G$10:$G$61,INDEX(Node_Pos,AB11)+1)<INDEX(Node_Thr,AB11),INDEX(Node_Left,AB11),INDEX(Node_Right,AB11)),IF(ISNUMBER(SEARCH(";"&INDEX($G$10:$G$61,INDEX(Node_Pos,AB11)+1)&";",";"&INDEX(Node_RCodes,AB11)&";")),INDEX(Node_Right,AB11),INDEX(Node_Left,AB11))))) | AD11: =MATCH($AA11&"|"&AC11,Node_Key,0) | AE11: =IF(INDEX(Node_Kind,AD11)="leaf",AC11,IF(INDEX($G$10:$G$61,INDEX(Node_Pos,AD11)+1)="",IF(INDEX(Node_Miss,AD11)="left",INDEX(Node_Left,AD11),INDEX(Node_Right,AD11)),IF(INDEX(Node_Kind,AD11)="split",IF(INDEX($G$10:$G$61,INDEX(Node_Pos,AD11)+1)<INDEX(Node_Thr,AD11),INDEX(Node_Left,AD11),INDEX(Node_Right,AD11)),IF(ISNUMBER(SEARCH(";"&INDEX($G$10:$G$61,INDEX(Node_Pos,AD11)+1)&";",";"&INDEX(Node_RCodes,AD11)&";")),INDEX(Node_Right,AD11),INDEX(Node_Left,AD11))))) | AF11: =MATCH($AA11&"|"&AE11,Node_Key,0) | AG11: =IF(INDEX(Node_Kind,AF11)="leaf",AE11,IF(INDEX($G$10:$G$61,INDEX(Node_Pos,AF11)+1)="",IF(INDEX(Node_Miss,AF11)="left",INDEX(Node_Left,AF11),INDEX(Node_Right,AF11)),IF(INDEX(Node_Kind,AF11)="split",IF(INDEX($G$10:$G$61,INDEX(Node_Pos,AF11)+1)<INDEX(Node_Thr,AF11),INDEX(Node_Left,AF11),INDEX(Node_Right,AF11)),IF(ISNUMBER(SEARCH(";"&INDEX($G$10:$G$61,INDEX(Node_Pos,AF11)+1)&";",";"&INDEX(Node_RCodes,AF11)&";")),INDEX(Node_Right,AF11),INDEX(Node_Left,AF11))))) | AH11: =IF(INDEX(Node_Kind,MATCH($AA11&"|"&AG11,Node_Key,0))="leaf",INDEX(Node_Leaf,MATCH($AA11&"|"&AG11,Node_Key,0)),"not a leaf") | AI11: =MATCH($AA11&"|0",Node_Key,0) | AJ11: =IF(INDEX(Node_Kind,AI11)="leaf",0,IF(INDEX($J$10:$J$61,INDEX(Node_Pos,AI11)+1)="",IF(INDEX(Node_Miss,AI11)="left",INDEX(Node_Left,AI11),INDEX(Node_Right,AI11)),IF(INDEX(Node_Kind,AI11)="split",IF(INDEX($J$10:$J$61,INDEX(Node_Pos,AI11)+1)<INDEX(Node_Thr,AI11),INDEX(Node_Left,AI11),INDEX(Node_Right,AI11)),IF(ISNUMBER(SEARCH(";"&INDEX($J$10:$J$61,INDEX(Node_Pos,AI11)+1)&";",";"&INDEX(Node_RCodes,AI11)&";")),INDEX(Node_Right,AI11),INDEX(Node_Left,AI11))))) | AK11: =MATCH($AA11&"|"&AJ11,Node_Key,0) | AL11: =IF(INDEX(Node_Kind,AK11)="leaf",AJ11,IF(INDEX($J$10:$J$61,INDEX(Node_Pos,AK11)+1)="",IF(INDEX(Node_Miss,AK11)="left",INDEX(Node_Left,AK11),INDEX(Node_Right,AK11)),IF(INDEX(Node_Kind,AK11)="split",IF(INDEX($J$10:$J$61,INDEX(Node_Pos,AK11)+1)<INDEX(Node_Thr,AK11),INDEX(Node_Left,AK11),INDEX(Node_Right,AK11)),IF(ISNUMBER(SEARCH(";"&INDEX($J$10:$J$61,INDEX(Node_Pos,AK11)+1)&";",";"&INDEX(Node_RCodes,AK11)&";")),INDEX(Node_Right,AK11),INDEX(Node_Left,AK11))))) | AM11: =MATCH($AA11&"|"&AL11,Node_Key,0) | AN11: =IF(INDEX(Node_Kind,AM11)="leaf",AL11,IF(INDEX($J$10:$J$61,INDEX(Node_Pos,AM11)+1)="",IF(INDEX(Node_Miss,AM11)="left",INDEX(Node_Left,AM11),INDEX(Node_Right,AM11)),IF(INDEX(Node_Kind,AM11)="split",IF(INDEX($J$10:$J$61,INDEX(Node_Pos,AM11)+1)<INDEX(Node_Thr,AM11),INDEX(Node_Left,AM11),INDEX(Node_Right,AM11)),IF(ISNUMBER(SEARCH(";"&INDEX($J$10:$J$61,INDEX(Node_Pos,AM11)+1)&";",";"&INDEX(Node_RCodes,AM11)&";")),INDEX(Node_Right,AM11),INDEX(Node_Left,AM11))))) | AO11: =IF(INDEX(Node_Kind,MATCH($AA11&"|"&AN11,Node_Key,0))="leaf",INDEX(Node_Leaf,MATCH($AA11&"|"&AN11,Node_Key,0)),"not a leaf") | AP11: =MATCH($AA11&"|0",Node_Key,0) | AQ11: =IF(INDEX(Node_Kind,AP11)="leaf",0,IF(INDEX($M$10:$M$61,INDEX(Node_Pos,AP11)+1)="",IF(INDEX(Node_Miss,AP11)="left",INDEX(Node_Left,AP11),INDEX(Node_Right,AP11)),IF(INDEX(Node_Kind,AP11)="split",IF(INDEX($M$10:$M$61,INDEX(Node_Pos,AP11)+1)<INDEX(Node_Thr,AP11),INDEX(Node_Left,AP11),INDEX(Node_Right,AP11)),IF(ISNUMBER(SEARCH(";"&INDEX($M$10:$M$61,INDEX(Node_Pos,AP11)+1)&";",";"&INDEX(Node_RCodes,AP11)&";")),INDEX(Node_Right,AP11),INDEX(Node_Left,AP11))))) | AR11: =MATCH($AA11&"|"&AQ11,Node_Key,0) | AS11: =IF(INDEX(Node_Kind,AR11)="leaf",AQ11,IF(INDEX($M$10:$M$61,INDEX(Node_Pos,AR11)+1)="",IF(INDEX(Node_Miss,AR11)="left",INDEX(Node_Left,AR11),INDEX(Node_Right,AR11)),IF(INDEX(Node_Kind,AR11)="split",IF(INDEX($M$10:$M$61,INDEX(Node_Pos,AR11)+1)<INDEX(Node_Thr,AR11),INDEX(Node_Left,AR11),INDEX(Node_Right,AR11)),IF(ISNUMBER(SEARCH(";"&INDEX($M$10:$M$61,INDEX(Node_Pos,AR11)+1)&";",";"&INDEX(Node_RCodes,AR11)&";")),INDEX(Node_Right,AR11),INDEX(Node_Left,AR11))))) | AT11: =MATCH($AA11&"|"&AS11,Node_Key,0) | AU11: =IF(INDEX(Node_Kind,AT11)="leaf",AS11,IF(INDEX($M$10:$M$61,INDEX(Node_Pos,AT11)+1)="",IF(INDEX(Node_Miss,AT11)="left",INDEX(Node_Left,AT11),INDEX(Node_Right,AT11)),IF(INDEX(Node_Kind,AT11)="split",IF(INDEX($M$10:$M$61,INDEX(Node_Pos,AT11)+1)<INDEX(Node_Thr,AT11),INDEX(Node_Left,AT11),INDEX(Node_Right,AT11)),IF(ISNUMBER(SEARCH(";"&INDEX($M$10:$M$61,INDEX(Node_Pos,AT11)+1)&";",";"&INDEX(Node_RCodes,AT11)&";")),INDEX(Node_Right,AT11),INDEX(Node_Left,AT11))))) | AV11: =IF(INDEX(Node_Kind,MATCH($AA11&"|"&AU11,Node_Key,0))="leaf",INDEX(Node_Leaf,MATCH($AA11&"|"&AU11,Node_Key,0)),"not a leaf") | AW11: =MATCH($AA11&"|0",Node_Key,0) | AX11: =IF(INDEX(Node_Kind,AW11)="leaf",0,IF(INDEX($P$10:$P$61,INDEX(Node_Pos,AW11)+1)="",IF(INDEX(Node_Miss,AW11)="left",INDEX(Node_Left,AW11),INDEX(Node_Right,AW11)),IF(INDEX(Node_Kind,AW11)="split",IF(INDEX($P$10:$P$61,INDEX(Node_Pos,AW11)+1)<INDEX(Node_Thr,AW11),INDEX(Node_Left,AW11),INDEX(Node_Right,AW11)),IF(ISNUMBER(SEARCH(";"&INDEX($P$10:$P$61,INDEX(Node_Pos,AW11)+1)&";",";"&INDEX(Node_RCodes,AW11)&";")),INDEX(Node_Right,AW11),INDEX(Node_Left,AW11))))) | AY11: =MATCH($AA11&"|"&AX11,Node_Key,0) | AZ11: =IF(INDEX(Node_Kind,AY11)="leaf",AX11,IF(INDEX($P$10:$P$61,INDEX(Node_Pos,AY11)+1)="",IF(INDEX(Node_Miss,AY11)="left",INDEX(Node_Left,AY11),INDEX(Node_Right,AY11)),IF(INDEX(Node_Kind,AY11)="split",IF(INDEX($P$10:$P$61,INDEX(Node_Pos,AY11)+1)<INDEX(Node_Thr,AY11),INDEX(Node_Left,AY11),INDEX(Node_Right,AY11)),IF(ISNUMBER(SEARCH(";"&INDEX($P$10:$P$61,INDEX(Node_Pos,AY11)+1)&";",";"&INDEX(Node_RCodes,AY11)&";")),INDEX(Node_Right,AY11),INDEX(Node_Left,AY11))))) | BA11: =MATCH($AA11&"|"&AZ11,Node_Key,0) | BB11: =IF(INDEX(Node_Kind,BA11)="leaf",AZ11,IF(INDEX($P$10:$P$61,INDEX(Node_Pos,BA11)+1)="",IF(INDEX(Node_Miss,BA11)="left",INDEX(Node_Left,BA11),INDEX(Node_Right,BA11)),IF(INDEX(Node_Kind,BA11)="split",IF(INDEX($P$10:$P$61,INDEX(Node_Pos,BA11)+1)<INDEX(Node_Thr,BA11),INDEX(Node_Left,BA11),INDEX(Node_Right,BA11)),IF(ISNUMBER(SEARCH(";"&INDEX($P$10:$P$61,INDEX(Node_Pos,BA11)+1)&";",";"&INDEX(Node_RCodes,BA11)&";")),INDEX(Node_Right,BA11),INDEX(Node_Left,BA11))))) | BC11: =IF(INDEX(Node_Kind,MATCH($AA11&"|"&BB11,Node_Key,0))="leaf",INDEX(Node_Leaf,MATCH($AA11&"|"&BB11,Node_Key,0)),"not a leaf") | BD11: =MATCH($AA11&"|0",Node_Key,0) | BE11: =IF(INDEX(Node_Kind,BD11)="leaf",0,IF(INDEX($S$10:$S$61,INDEX(Node_Pos,BD11)+1)="",IF(INDEX(Node_Miss,BD11)="left",INDEX(Node_Left,BD11),INDEX(Node_Right,BD11)),IF(INDEX(Node_Kind,BD11)="split",IF(INDEX($S$10:$S$61,INDEX(Node_Pos,BD11)+1)<INDEX(Node_Thr,BD11),INDEX(Node_Left,BD11),INDEX(Node_Right,BD11)),IF(ISNUMBER(SEARCH(";"&INDEX($S$10:$S$61,INDEX(Node_Pos,BD11)+1)&";",";"&INDEX(Node_RCodes,BD11)&";")),INDEX(Node_Right,BD11),INDEX(Node_Left,BD11))))) | BF11: =MATCH($AA11&"|"&BE11,Node_Key,0) | BG11: =IF(INDEX(Node_Kind,BF11)="leaf",BE11,IF(INDEX($S$10:$S$61,INDEX(Node_Pos,BF11)+1)="",IF(INDEX(Node_Miss,BF11)="left",INDEX(Node_Left,BF11),INDEX(Node_Right,BF11)),IF(INDEX(Node_Kind,BF11)="split",IF(INDEX($S$10:$S$61,INDEX(Node_Pos,BF11)+1)<INDEX(Node_Thr,BF11),INDEX(Node_Left,BF11),INDEX(Node_Right,BF11)),IF(ISNUMBER(SEARCH(";"&INDEX($S$10:$S$61,INDEX(Node_Pos,BF11)+1)&";",";"&INDEX(Node_RCodes,BF11)&";")),INDEX(Node_Right,BF11),INDEX(Node_Left,BF11))))) | BH11: =MATCH($AA11&"|"&BG11,Node_Key,0) | BI11: =IF(INDEX(Node_Kind,BH11)="leaf",BG11,IF(INDEX($S$10:$S$61,INDEX(Node_Pos,BH11)+1)="",IF(INDEX(Node_Miss,BH11)="left",INDEX(Node_Left,BH11),INDEX(Node_Right,BH11)),IF(INDEX(Node_Kind,BH11)="split",IF(INDEX($S$10:$S$61,INDEX(Node_Pos,BH11)+1)<INDEX(Node_Thr,BH11),INDEX(Node_Left,BH11),INDEX(Node_Right,BH11)),IF(ISNUMBER(SEARCH(";"&INDEX($S$10:$S$61,INDEX(Node_Pos,BH11)+1)&";",";"&INDEX(Node_RCodes,BH11)&";")),INDEX(Node_Right,BH11),INDEX(Node_Left,BH11))))) | BJ11: =IF(INDEX(Node_Kind,MATCH($AA11&"|"&BI11,Node_Key,0))="leaf",INDEX(Node_Leaf,MATCH($AA11&"|"&BI11,Node_Key,0)),"not a leaf") | BK11: =MATCH($AA11&"|0",Node_Key,0) | BL11: =IF(INDEX(Node_Kind,BK11)="leaf",0,IF(INDEX($V$10:$V$61,INDEX(Node_Pos,BK11)+1)="",IF(INDEX(Node_Miss,BK11)="left",INDEX(Node_Left,BK11),INDEX(Node_Right,BK11)),IF(INDEX(Node_Kind,BK11)="split",IF(INDEX($V$10:$V$61,INDEX(Node_Pos,BK11)+1)<INDEX(Node_Thr,BK11),INDEX(Node_Left,BK11),INDEX(Node_Right,BK11)),IF(ISNUMBER(SEARCH(";"&INDEX($V$10:$V$61,INDEX(Node_Pos,BK11)+1)&";",";"&INDEX(Node_RCodes,BK11)&";")),INDEX(Node_Right,BK11),INDEX(Node_Left,BK11))))) | BM11: =MATCH($AA11&"|"&BL11,Node_Key,0) | BN11: =IF(INDEX(Node_Kind,BM11)="leaf",BL11,IF(INDEX($V$10:$V$61,INDEX(Node_Pos,BM11)+1)="",IF(INDEX(Node_Miss,BM11)="left",INDEX(Node_Left,BM11),INDEX(Node_Right,BM11)),IF(INDEX(Node_Kind,BM11)="split",IF(INDEX($V$10:$V$61,INDEX(Node_Pos,BM11)+1)<INDEX(Node_Thr,BM11),INDEX(Node_Left,BM11),INDEX(Node_Right,BM11)),IF(ISNUMBER(SEARCH(";"&INDEX($V$10:$V$61,INDEX(Node_Pos,BM11)+1)&";",";"&INDEX(Node_RCodes,BM11)&";")),INDEX(Node_Right,BM11),INDEX(Node_Left,BM11))))) | BO11: =MATCH($AA11&"|"&BN11,Node_Key,0) | BP11: =IF(INDEX(Node_Kind,BO11)="leaf",BN11,IF(INDEX($V$10:$V$61,INDEX(Node_Pos,BO11)+1)="",IF(INDEX(Node_Miss,BO11)="left",INDEX(Node_Left,BO11),INDEX(Node_Right,BO11)),IF(INDEX(Node_Kind,BO11)="split",IF(INDEX($V$10:$V$61,INDEX(Node_Pos,BO11)+1)<INDEX(Node_Thr,BO11),INDEX(Node_Left,BO11),INDEX(Node_Right,BO11)),IF(ISNUMBER(SEARCH(";"&INDEX($V$10:$V$61,INDEX(Node_Pos,BO11)+1)&";",";"&INDEX(Node_RCodes,BO11)&";")),INDEX(Node_Right,BO11),INDEX(Node_Left,BO11))))) | BQ11: =IF(INDEX(Node_Kind,MATCH($AA11&"|"&BP11,Node_Key,0))="leaf",INDEX(Node_Leaf,MATCH($AA11&"|"&BP11,Node_Key,0)),"not a leaf") | BR11: =MATCH($AA11&"|0",Node_Key,0) | BS11: =IF(INDEX(Node_Kind,BR11)="leaf",0,IF(INDEX($Y$10:$Y$61,INDEX(Node_Pos,BR11)+1)="",IF(INDEX(Node_Miss,BR11)="left",INDEX(Node_Left,BR11),INDEX(Node_Right,BR11)),IF(INDEX(Node_Kind,BR11)="split",IF(INDEX($Y$10:$Y$61,INDEX(Node_Pos,BR11)+1)<INDEX(Node_Thr,BR11),INDEX(Node_Left,BR11),INDEX(Node_Right,BR11)),IF(ISNUMBER(SEARCH(";"&INDEX($Y$10:$Y$61,INDEX(Node_Pos,BR11)+1)&";",";"&INDEX(Node_RCodes,BR11)&";")),INDEX(Node_Right,BR11),INDEX(Node_Left,BR11))))) | BT11: =MATCH($AA11&"|"&BS11,Node_Key,0) | BU11: =IF(INDEX(Node_Kind,BT11)="leaf",BS11,IF(INDEX($Y$10:$Y$61,INDEX(Node_Pos,BT11)+1)="",IF(INDEX(Node_Miss,BT11)="left",INDEX(Node_Left,BT11),INDEX(Node_Right,BT11)),IF(INDEX(Node_Kind,BT11)="split",IF(INDEX($Y$10:$Y$61,INDEX(Node_Pos,BT11)+1)<INDEX(Node_Thr,BT11),INDEX(Node_Left,BT11),INDEX(Node_Right,BT11)),IF(ISNUMBER(SEARCH(";"&INDEX($Y$10:$Y$61,INDEX(Node_Pos,BT11)+1)&";",";"&INDEX(Node_RCodes,BT11)&";")),INDEX(Node_Right,BT11),INDEX(Node_Left,BT11))))) | BV11: =MATCH($AA11&"|"&BU11,Node_Key,0) | BW11: =IF(INDEX(Node_Kind,BV11)="leaf",BU11,IF(INDEX($Y$10:$Y$61,INDEX(Node_Pos,BV11)+1)="",IF(INDEX(Node_Miss,BV11)="left",INDEX(Node_Left,BV11),INDEX(Node_Right,BV11)),IF(INDEX(Node_Kind,BV11)="split",IF(INDEX($Y$10:$Y$61,INDEX(Node_Pos,BV11)+1)<INDEX(Node_Thr,BV11),INDEX(Node_Left,BV11),INDEX(Node_Right,BV11)),IF(ISNUMBER(SEARCH(";"&INDEX($Y$10:$Y$61,INDEX(Node_Pos,BV11)+1)&";",";"&INDEX(Node_RCodes,BV11)&";")),INDEX(Node_Right,BV11),INDEX(Node_Left,BV11))))) | BX11: =IF(INDEX(Node_Kind,MATCH($AA11&"|"&BW11,Node_Key,0))="leaf",INDEX(Node_Leaf,MATCH($AA11&"|"&BW11,Node_Key,0)),"not a leaf") | BZ11: =H$8 | CA11: ='Rating Buildings'!$F$11 | CB11: =SUM($AO$10:$AO$202) | CC11: =LN(CA11)+LN(XGB_Base)+LN(XGB_Trend)+CB11 | CD11: =EXP(CC11) | CE11: ='Rating Buildings'!$AQ$11 | CF11: =CD11+CE11 | CG11: =Lvl_Bld | CH11: =CF11*CG11 | CI11: =INDEX(Py_Small,MATCH(BZ11,Py_ID,0)) | CJ11: =ABS(CD11/CI11-1) | CK11: =INDEX(Py_Final,MATCH(BZ11,Py_ID,0)) | CL11: =ABS(CH11/CK11-1) | CM11: =SUMPRODUCT((I$10:I$61<>"")*(J$10:J$61="")*(RIGHT(I$10:I$61,8)<>"|MISSING")) | CN11: =COUNTIF($AO$10:$AO$202,"not a leaf")
